Workbook

Sheet map7
A1: № точки | B1: Адрес | C1: Широта | D1: Долгота | E1: инспектор | F1: Список | G1: Время/дата входа | H1: Время/дата выхода | I1: Время на объекте | J1: Ссылка на чек | K1: Ссылка на яндекс | L1: Предыдущий инспектор | M1: Инспектор | N1: Время открытия рабочего дня | O1: Координаты открытия дня | P1: Время закрытия рабочего дня | Q1: Координаты закрытия дня
M2: Наволокин Андрей Александрович | N2: 45975.37 | O2: 55.891891891891895, 37.497629338494576
M3: Поляков Сергей Алексеевич | N3: 45975.364 | O3: 55.972911479310675, 37.431479050169955
M4: Лашин Александр Николаевич | N4: 45975.37 | O4: 55.7991937, 37.777514
M5: Джинджолия Леван Раульевич | N5: 45975.35 | O5: 55.712123749999996, 37.737975
M6: Гытлан Роман Валентинович | N6: 45975.357 | O6: 55.6724904, 37.7444511
M7: Удалкин Иван Вячеславович | N7: 45975.368 | O7: 55.63512225578537, 37.64980215579271
M8: Осипенко Юрий Владимирович | N8: 45975.365 | O8: 55.3860511, 37.4123357
M9: Данилов Семен Юрьевич | N9: 45975.357 | O9: 55.3084117, 37.3676117
M10: Терехин Александр Андреевич | N10: 45975.374 | O10: 55.5761512, 37.236635
M11: Пулатов Алекс Шухратович | N11: 45975.358 | O11: 55.6803906, 37.3412664
M12: Макаров Илья Алексеевич
M13: Куликов Илья Александрович
M14: Шурпаев Нажмутдин Гаджиатаевич
M15: Старостин Кирилл Владимирович
M16: Дрозд Александр Викторович | N16: 45975.35 | O16: 55.7002553, 37.7818266
M17: Иванов Иван Иванович
A18: 713 | B18: =VLOOKUP($A18,'Реестр объектов'!$A:$I,5,0) -> Веерная улица, земельный участок 28А район Очаково-Матвеевское, ул. Веерная, вл. 28А | C18: =VLOOKUP($A18,'Реестр объектов'!$A:$I,6,0) -> 55.710226 | D18: =VLOOKUP($A18,'Реестр объектов'!$A:$I,7,0) -> 37.480970 | E18: Admin | F18: МФР 26 | J18: =VLOOKUP($A18,'Реестр объектов'!$A:$I,8,0) -> https://docs.google.com/spreadsheets/d/1rbCD10ySi4YZEkJW2_Slmn9z7AI1WEsGsZaIJmnnT18/edit?gid=1754531219#gid=1754531219 | K18: =VLOOKUP($A18,'Реестр объектов'!$A:$I,9,0) -> https://disk.yandex.ru/client/disk/Осмотры%20объектов%20АНО%20СМГ/713.%20Жилой%20дом%20ул.%20Веерная%2028а
A19: 700 | B19: =VLOOKUP($A19,'Реестр объектов'!$A:$I,5,0) -> Жилой дом с подземной автостоянкой, инженерными сетями и благоустройством территории по адресу: район Нагатино-Садовники, Нагатинская ул, вл.1/4 (Нагатинская ул, вл.1) район Нагатино-Садовники, Нагатинская ул, вл.1/4 (Нагатинская ул, вл.1) | C19: =VLOOKUP($A19,'Реестр объектов'!$A:$I,6,0) -> 55.684985 | D19: =VLOOKUP($A19,'Реестр объектов'!$A:$I,7,0) -> 37.624634 | E19: Гытлан Роман Валентинович | F19: МФР 26 | J19: =VLOOKUP($A19,'Реестр объектов'!$A:$I,8,0) -> https://docs.google.com/spreadsheets/d/1rbCD10ySi4YZEkJW2_Slmn9z7AI1WEsGsZaIJmnnT18/edit?gid=732973558#gid=732973558 | K19: =VLOOKUP($A19,'Реестр объектов'!$A:$I,9,0) -> https://disk.yandex.ru/client/disk/Осмотры%20объектов%20АНО%20СМГ/700.%20Нагатинская%20ул.%20вл.%201.%20Жилой%09дом
A20: 738 | B20: =VLOOKUP($A20,'Реестр объектов'!$A:$I,5,0) -> ул. Шепелюгинская, вл. 14 район Лефортово, ул. Шепелюгинская, вл. 14 | C20: =VLOOKUP($A20,'Реестр объектов'!$A:$I,6,0) -> 55.745914 | D20: =VLOOKUP($A20,'Реестр объектов'!$A:$I,7,0) -> 37.702358 | E20: Джинджолия Леван Раульевич | F20: МФР 26 | G20: 45975.502 | J20: =VLOOKUP($A20,'Реестр объектов'!$A:$I,8,0) -> https://docs.google.com/spreadsheets/d/1rbCD10ySi4YZEkJW2_Slmn9z7AI1WEsGsZaIJmnnT18/edit?gid=2128103220#gid=2128103220 | K20: =VLOOKUP($A20,'Реестр объектов'!$A:$I,9,0) -> https://disk.yandex.ru/client/disk/%D0%9E%D1%81%D0%BC%D0%BE%D1%82%D1%80%D1%8B%20%D0%BE%D0%B1%D1%8A%D0%B5%D0%BA%D1%82%D0%BE%D0%B2%20%D0%90%D0%9D%D0%9E%20%D0%A1%D0%9C%D0%93/738.%20%D0%A8%D0%B5%D0%BF%D0%B5%D0%BB%D1%8E%D0%B3%D0%B8%D0%BD%D1%81%D0%BA%D0%B0%D1%8F%20%D0%B2%D0%BB%2014%20
A21: 740 | B21: =VLOOKUP($A21,'Реестр объектов'!$A:$I,5,0) -> Шепелюгинский пер., вл. 7 (Приобретение объектов недвижимости) район Лефортово, Шепелюгинский пер., вл. 7 | C21: =VLOOKUP($A21,'Реестр объектов'!$A:$I,6,0) -> 55.746929 | D21: =VLOOKUP($A21,'Реестр объектов'!$A:$I,7,0) -> 37.701113 | E21: Джинджолия Леван Раульевич | F21: МФР 26 | J21: =VLOOKUP($A21,'Реестр объектов'!$A:$I,8,0) -> https://docs.google.com/spreadsheets/d/1rbCD10ySi4YZEkJW2_Slmn9z7AI1WEsGsZaIJmnnT18/edit?gid=1195206502#gid=1195206502 | K21: =VLOOKUP($A21,'Реестр объектов'!$A:$I,9,0) -> https://disk.yandex.ru/client/disk/Осмотры%20объектов%20АНО%20СМГ/740.%20Шепелюгинский%20пер%20вл%207
A22: 661 | B22: =VLOOKUP($A22,'Реестр объектов'!$A:$I,5,0) -> б-р Яна Райниса, вл.2, к 2,3 район Северное Тушино, мкр. 4, б-р Яна Райниса, вл.2, к 2,3. | C22: =VLOOKUP($A22,'Реестр объектов'!$A:$I,6,0) -> 55.852135 | D22: =VLOOKUP($A22,'Реестр объектов'!$A:$I,7,0) -> 37.431852 | E22: Поляков Сергей Алексеевич | F22: МФР 26 | J22: =VLOOKUP($A22,'Реестр объектов'!$A:$I,8,0) -> https://docs.google.com/spreadsheets/d/1rbCD10ySi4YZEkJW2_Slmn9z7AI1WEsGsZaIJmnnT18/edit?gid=988598667#gid=988598667 | K22: =VLOOKUP($A22,'Реестр объектов'!$A:$I,9,0) -> https://disk.yandex.ru/client/disk/Осмотры%20объектов%20АНО%20СМГ/661.%20Яна%20Райниса%20б-р%2C%20влд.%202%2C%20к.%202%2C%203 | L22: Поляков Сергей Алексеевич
A23: 636 | B23: =VLOOKUP($A23,'Реестр объектов'!$A:$I,5,0) -> улица Смольная,земельный участок 23 внутригородское муниципальное образование Головинское, улица Смольная,земельный участок 23 (ул. Смольная, 23) | C23: =VLOOKUP($A23,'Реестр объектов'!$A:$I,6,0) -> 55.849033 | D23: =VLOOKUP($A23,'Реестр объектов'!$A:$I,7,0) -> 37.494706 | E23: Admin | F23: МФР 26 | J23: =VLOOKUP($A23,'Реестр объектов'!$A:$I,8,0) -> https://docs.google.com/spreadsheets/d/1rbCD10ySi4YZEkJW2_Slmn9z7AI1WEsGsZaIJmnnT18/edit?gid=1665166606#gid=1665166606 | K23: =VLOOKUP($A23,'Реестр объектов'!$A:$I,9,0) -> https://disk.yandex.ru/client/disk/Осмотры%20объектов%20АНО%20СМГ/636.%20Смольная%20зу%2023
A24: 624 | B24: =VLOOKUP($A24,'Реестр объектов'!$A:$I,5,0) -> улица Тайнинская, земельный участок 3 (вл. 3) район Лосиноостровский, Тайнинская ул., вл. 3 | C24: =VLOOKUP($A24,'Реестр объектов'!$A:$I,6,0) -> 55.878112 | D24: =VLOOKUP($A24,'Реестр объектов'!$A:$I,7,0) -> 37.681312 | E24: Admin | F24: МФР 26 | J24: =VLOOKUP($A24,'Реестр объектов'!$A:$I,8,0) -> https://docs.google.com/spreadsheets/d/1rbCD10ySi4YZEkJW2_Slmn9z7AI1WEsGsZaIJmnnT18/edit?gid=1331480544#gid=1331480544 | K24: =VLOOKUP($A24,'Реестр объектов'!$A:$I,9,0) -> https://disk.yandex.ru/client/disk/Осмотры%20объектов%20АНО%20СМГ/624.%20Тайнинская%20ул.%2C%20зу%203
A25: 802 | B25: =VLOOKUP($A25,'Реестр объектов'!$A:$I,5,0) -> Кржижановского ул., вл. 31 район Котловка Кржижановского ул., вл. 31 микрорайонов 67,68, кварталов 103,104,105,106 за границами ППТ | C25: =VLOOKUP($A25,'Реестр объектов'!$A:$I,6,0) -> 55.673297 | D25: =VLOOKUP($A25,'Реестр объектов'!$A:$I,7,0) -> 37.581276 | E25: Удалкин Иван Вячеславович | F25: МФР 26 | G25: 45975.47 | J25: =VLOOKUP($A25,'Реестр объектов'!$A:$I,8,0) -> https://docs.google.com/spreadsheets/d/1rbCD10ySi4YZEkJW2_Slmn9z7AI1WEsGsZaIJmnnT18/edit?gid=79728110#gid=79728110 | K25: =VLOOKUP($A25,'Реестр объектов'!$A:$I,9,0) -> https://disk.yandex.ru/client/disk/Осмотры%20объектов%20АНО%20СМГ/802.%20Котловка%2C%20ул.%20Кржижановского%20вл.%2031
A26: 805 | B26: =VLOOKUP($A26,'Реестр объектов'!$A:$I,5,0) -> Нижегородская ул., з/у 92А (зона №2.4) кв. 80, район Нижегородский (зона № 2.4) (ул. Нижегородская, д. 94, к.2) | C26: =VLOOKUP($A26,'Реестр объектов'!$A:$I,6,0) -> 55.729701 | D26: =VLOOKUP($A26,'Реестр объектов'!$A:$I,7,0) -> 37.721204 | E26: Джинджолия Леван Раульевич | F26: МФР 26 | G26: 45975.465 | H26: 45975.493 | I26: 40 мин | J26: =VLOOKUP($A26,'Реестр объектов'!$A:$I,8,0) -> https://docs.google.com/spreadsheets/d/1rbCD10ySi4YZEkJW2_Slmn9z7AI1WEsGsZaIJmnnT18/edit?gid=1527817991#gid=1527817991 | K26: =VLOOKUP($A26,'Реестр объектов'!$A:$I,9,0) -> https://disk.yandex.ru/client/disk/Осмотры%20объектов%20АНО%20СМГ/805.%20Нижегородская%20ул.%2C%20з-у%2092А%2C%20зона%202.4
A27: 609 | B27: =VLOOKUP($A27,'Реестр объектов'!$A:$I,5,0) -> ул. Лобачевского, влд. 62 район Проспект Вернадского, Лобачевского ул., вл. 62 | C27: =VLOOKUP($A27,'Реестр объектов'!$A:$I,6,0) -> 55.675595 | D27: =VLOOKUP($A27,'Реестр объектов'!$A:$I,7,0) -> 37.492644 | E27: Admin | F27: МФР 26 | J27: =VLOOKUP($A27,'Реестр объектов'!$A:$I,8,0) -> https://docs.google.com/spreadsheets/d/1rbCD10ySi4YZEkJW2_Slmn9z7AI1WEsGsZaIJmnnT18/edit?gid=387655725#gid=387655725 | K27: =VLOOKUP($A27,'Реестр объектов'!$A:$I,9,0) -> https://disk.yandex.ru/client/disk/Осмотры%20объектов%20АНО%20СМГ/609.%20ЗАО%20проспект%20Вернадского%2C%20Лобачевского%20улица.%2C%20вл.62
A28: 644 | B28: =VLOOKUP($A28,'Реестр объектов'!$A:$I,5,0) -> 9 Мая ул., вл. 24 район Восточный, 9 Мая ул., вл. 24 | C28: =VLOOKUP($A28,'Реестр объектов'!$A:$I,6,0) -> 55.818169 | D28: =VLOOKUP($A28,'Реестр объектов'!$A:$I,7,0) -> 37.872541 | E28: Лашин Александр Николаевич | F28: МФР 26 | J28: =VLOOKUP($A28,'Реестр объектов'!$A:$I,8,0) -> https://docs.google.com/spreadsheets/d/1rbCD10ySi4YZEkJW2_Slmn9z7AI1WEsGsZaIJmnnT18/edit?gid=692135392#gid=692135392 | K28: =VLOOKUP($A28,'Реестр объектов'!$A:$I,9,0) -> https://disk.yandex.ru/client/disk/%D0%9E%D1%81%D0%BC%D0%BE%D1%82%D1%80%D1%8B%20%D0%BE%D0%B1%D1%8A%D0%B5%D0%BA%D1%82%D0%BE%D0%B2%20%D0%90%D0%9D%D0%9E%20%D0%A1%D0%9C%D0%93/644%20%D0%A3%D0%BB.%209%20%D0%9C%D0%B0%D1%8F%20%D0%B2%D0%BB%2024%20%D1%80-%D0%BD%20%D0%92%D0%BE%D1%81%D1%82%D0%BE%D1%87%D0%BD%D1%8B%D0%B9%2C%20%D1%81%D0%BE%20%D1%81%D0%BD%D0%BE%D1%81%D0%BE%D0%BC%20%D0%96.%D0%A1.%20%20
A29: 605 | B29: =VLOOKUP($A29,'Реестр объектов'!$A:$I,5,0) -> 1-й Саратовский пр-д, з/у 5 (1-й Саратовский пр-д, вл.5) район Текстильщики, 1-й Саратовский пр-д, вл.5 | C29: =VLOOKUP($A29,'Реестр объектов'!$A:$I,6,0) -> 55.711841 | D29: =VLOOKUP($A29,'Реестр объектов'!$A:$I,7,0) -> 37.737222 | E29: Джинджолия Леван Раульевич | F29: МФР 26 | G29: 45975.354 | H29: 45975.381 | I29: 39 мин | J29: =VLOOKUP($A29,'Реестр объектов'!$A:$I,8,0) -> https://docs.google.com/spreadsheets/d/1rbCD10ySi4YZEkJW2_Slmn9z7AI1WEsGsZaIJmnnT18/edit?gid=847490134#gid=847490134 | K29: =VLOOKUP($A29,'Реестр объектов'!$A:$I,9,0) -> https://disk.yandex.ru/client/disk/Осмотры%20объектов%20АНО%20СМГ/605.%201-й%20Саратовский%20проезд%2C%205%20Реновация
A30: 728 | B30: =VLOOKUP($A30,'Реестр объектов'!$A:$I,5,0) -> ул. 2-я Синичкина, з/у 9 (ул. 2-я Синичкина, вл. 9) район Лефортово, улица 2-я Синичкина, земельный участок 9 (ул. 2-я Синичкина, вл. 9) | C30: =VLOOKUP($A30,'Реестр объектов'!$A:$I,6,0) -> 55.763275 | D30: =VLOOKUP($A30,'Реестр объектов'!$A:$I,7,0) -> 37.712926 | E30: Admin | F30: МФР 26 | J30: =VLOOKUP($A30,'Реестр объектов'!$A:$I,8,0) -> https://docs.google.com/spreadsheets/d/1rbCD10ySi4YZEkJW2_Slmn9z7AI1WEsGsZaIJmnnT18/edit?gid=943458292#gid=943458292 | K30: =VLOOKUP($A30,'Реестр объектов'!$A:$I,9,0) -> https://disk.yandex.ru/client/disk/%D0%9E%D1%81%D0%BC%D0%BE%D1%82%D1%80%D1%8B%20%D0%BE%D0%B1%D1%8A%D0%B5%D0%BA%D1%82%D0%BE%D0%B2%20%D0%90%D0%9D%D0%9E%20%D0%A1%D0%9C%D0%93/728.%20%D1%80%D0%B0%D0%B9%D0%BE%D0%BD%20%D0%9B%D0%B5%D1%84%D0%BE%D1%80%D1%82%D0%BE%D0%B2%D0%BE%2C%202-%D1%8F%20%D0%A1%D0%B8%D0%BD%D0%B8%D1%87%D0%BA%D0%B8%D0%BD%D0%B0%2C%20%D0%B7.%D1%83%209%20(%D1%81%D0%BE%20%D1%81%D0%BD%D0%BE%D1%81%D0%BE%D0%BC%20%D0%B6%D0%B8%D0%BB%D0%BE%D0%B3%D0%BE%20%D0%B4%D0%BE%D0%BC%D0%B0%20%D0%BF%D0%BE%20%D0%B0%D0%B4%D1%80%D0%B5%D1%81%D1%83%3A%202-%D1%8F%20%D1%83%D0%BB%D0%B8%D1%86%D0%B0%20%D0%A1%D0%B8%D0%BD%D0%B8%D1%87%D0%BA%D0%B8%D0%BD%D0%B0%2C%20%D0%B4%D0%BE%D0%BC%209)
A31: 645 | B31: =VLOOKUP($A31,'Реестр объектов'!$A:$I,5,0) -> Щербаковская ул., влд. 5А район Соколиная гора, Щербаковская улица, влд. 5А | C31: =VLOOKUP($A31,'Реестр объектов'!$A:$I,6,0) -> 55.783473 | D31: =VLOOKUP($A31,'Реестр объектов'!$A:$I,7,0) -> 37.725236 | E31: Admin | F31: МФР 26 | J31: =VLOOKUP($A31,'Реестр объектов'!$A:$I,8,0) -> https://docs.google.com/spreadsheets/d/1rbCD10ySi4YZEkJW2_Slmn9z7AI1WEsGsZaIJmnnT18/edit?gid=1166394533#gid=1166394533 | K31: =VLOOKUP($A31,'Реестр объектов'!$A:$I,9,0) -> https://disk.yandex.ru/client/disk/%D0%9E%D1%81%D0%BC%D0%BE%D1%82%D1%80%D1%8B%20%D0%BE%D0%B1%D1%8A%D0%B5%D0%BA%D1%82%D0%BE%D0%B2%20%D0%90%D0%9D%D0%9E%20%D0%A1%D0%9C%D0%93/645.%20%D0%A9%D0%B5%D1%80%D0%B1%D0%B0%D0%BA%D0%BE%D0%B2%D1%81%D0%BA%D0%B0%D1%8F%20%D0%B7%D1%83%205%D0%90%20
A32: 550 | B32: =VLOOKUP($A32,'Реестр объектов'!$A:$I,5,0) -> гор.Щербинка, 40 лет Октября ул., з/у 12 ТиНАО, г.о. Щербинка, ул. 40 лет Октября, з/у 12 (Симферопольская ул., д. 2, ул. 40 лет Октября, д. 12, д. 16/1) | C32: =VLOOKUP($A32,'Реестр объектов'!$A:$I,6,0) -> 55.510648 | D32: =VLOOKUP($A32,'Реестр объектов'!$A:$I,7,0) -> 37.572771 | E32: Admin | F32: МФР 26 | J32: =VLOOKUP($A32,'Реестр объектов'!$A:$I,8,0) -> https://docs.google.com/spreadsheets/d/1rbCD10ySi4YZEkJW2_Slmn9z7AI1WEsGsZaIJmnnT18/edit?gid=811633138#gid=811633138 | K32: =VLOOKUP($A32,'Реестр объектов'!$A:$I,9,0) -> https://disk.yandex.ru/client/disk/Осмотры%20объектов%20АНО%20СМГ/550.%20г.о.%20Щербинка%2C%20ул.%2040%20лет%20Октября%2C%20з.у%2012%20Симферопольская%20ул.%2C%20д.%202%2C%20ул.%2040%20лет%20Октября%2C%20д.%2012%2C%20д.%2016.1)
A33: 655 | B33: =VLOOKUP($A33,'Реестр объектов'!$A:$I,5,0) -> ул. Корнейчука, вл.47А СВАО, район Бибирево, ул. Корнейчука, вл. 47А (со сносом здания по адресу: ул. Корнейчука, д. 47А) | C33: =VLOOKUP($A33,'Реестр объектов'!$A:$I,6,0) -> 55.893110 | D33: =VLOOKUP($A33,'Реестр объектов'!$A:$I,7,0) -> 37.630685 | E33: Admin | F33: МФР 26 | J33: =VLOOKUP($A33,'Реестр объектов'!$A:$I,8,0) -> https://docs.google.com/spreadsheets/d/1rbCD10ySi4YZEkJW2_Slmn9z7AI1WEsGsZaIJmnnT18/edit?gid=1300345470#gid=1300345470 | K33: =VLOOKUP($A33,'Реестр объектов'!$A:$I,9,0) -> https://disk.yandex.ru/client/disk/Осмотры%20объектов%20АНО%20СМГ/655.%20ул.%20Корнейчука%2C%20вл.%2047%20А
A34: 712 | B34: =VLOOKUP($A34,'Реестр объектов'!$A:$I,5,0) -> ул. Большая Очаковская, з/у 45А (Большая Очаковская ул., вл.45А) ЗАО, район Очаково - Матвеевское, Большая Очаковская, влд. 45А, квартал 2,4 зона 15.1 (со сносом жилых зданий по адресу: ул. Большая Очаковская, 45 к.1, ул. Проектируемый проезд №1980, д.3) | C34: =VLOOKUP($A34,'Реестр объектов'!$A:$I,6,0) -> 55.674464 | D34: =VLOOKUP($A34,'Реестр объектов'!$A:$I,7,0) -> 37.446148 | E34: Admin | F34: МФР 26 | J34: =VLOOKUP($A34,'Реестр объектов'!$A:$I,8,0) -> https://docs.google.com/spreadsheets/d/1rbCD10ySi4YZEkJW2_Slmn9z7AI1WEsGsZaIJmnnT18/edit?gid=1525507838#gid=1525507838 | K34: =VLOOKUP($A34,'Реестр объектов'!$A:$I,9,0) -> https://disk.yandex.ru/client/disk/Осмотры%20объектов%20АНО%20СМГ/712.%20Большая%20Очаковская%2C%20влд.%2045А%2C%20квартал%202%2C4%20зона%2015.1
A35: 698 | B35: =VLOOKUP($A35,'Реестр объектов'!$A:$I,5,0) -> Шишкин Лес, зона 6.2 ТАО, пос. Михайлово-Ярцевское, п. Шишкин Лес, з/у 5 зона № 6.2 | C35: =VLOOKUP($A35,'Реестр объектов'!$A:$I,6,0) -> 55.413660 | D35: =VLOOKUP($A35,'Реестр объектов'!$A:$I,7,0) -> 37.192563 | E35: Осипенко Юрий Владимирович | F35: МФР 26 | J35: =VLOOKUP($A35,'Реестр объектов'!$A:$I,8,0) -> https://docs.google.com/spreadsheets/d/1rbCD10ySi4YZEkJW2_Slmn9z7AI1WEsGsZaIJmnnT18/edit?gid=1721879742#gid=1721879742 | K35: =VLOOKUP($A35,'Реестр объектов'!$A:$I,9,0) -> https://disk.yandex.ru/client/disk/Осмотры%20объектов%20АНО%20СМГ/698.%20пос.%20Михайлово-Ярцевское%2C%20п.%20Шишкин%20Лес%2C%20зу%205%20зона%20№%206.2
A36: 653 | B36: =VLOOKUP($A36,'Реестр объектов'!$A:$I,5,0) -> ул. Госпитальный Вал, вл.5, корп.10 , ул. Госпитальный Вал, д.5, стр.20; ул. Госпитальный Вал, д.5, к.10) ЦАО, район Басманный, ул. Госпитальный Вал, вл.5, корп.20 (со сносом нежилого здания ГБОУ школа на Яузе Дошкольное отделение корпус № 7 по адресу: ул. Госпитальный Вал, д.5, стр.20 и жилого дома по адресу: ул. Госпитальный Вал, д.5, к.10) | C36: =VLOOKUP($A36,'Реестр объектов'!$A:$I,6,0) -> 55.772856 | D36: =VLOOKUP($A36,'Реестр объектов'!$A:$I,7,0) -> 37.708026 | E36: Admin | F36: МФР 26 | J36: =VLOOKUP($A36,'Реестр объектов'!$A:$I,8,0) -> https://docs.google.com/spreadsheets/d/1rbCD10ySi4YZEkJW2_Slmn9z7AI1WEsGsZaIJmnnT18/edit?gid=1637195585#gid=1637195585 | K36: =VLOOKUP($A36,'Реестр объектов'!$A:$I,9,0) -> https://disk.yandex.ru/client/disk/Осмотры%20объектов%20АНО%20СМГ/653.%20Госпитальный%20Вал%20ул.%2C%20вл.%205%2C%20Корп.20
A37: 694 | B37: =VLOOKUP($A37,'Реестр объектов'!$A:$I,5,0) -> ул. Госпитальный Вал, вл.3 ЦАО, район Басманный, ул. Госпитальный Вал, вл.3 (со сносом жилых домов по адресам: ул. Госпитальный Вал, д.3 и д.3, корп.1) | C37: =VLOOKUP($A37,'Реестр объектов'!$A:$I,6,0) -> 55.772318 | D37: =VLOOKUP($A37,'Реестр объектов'!$A:$I,7,0) -> 37.706787 | E37: Admin | F37: МФР 26 | J37: =VLOOKUP($A37,'Реестр объектов'!$A:$I,8,0) -> https://docs.google.com/spreadsheets/d/1rbCD10ySi4YZEkJW2_Slmn9z7AI1WEsGsZaIJmnnT18/edit?gid=1429286292#gid=1429286292 | K37: =VLOOKUP($A37,'Реестр объектов'!$A:$I,9,0) -> https://disk.yandex.ru/client/disk/Осмотры%20объектов%20АНО%20СМГ/694.%20Госпитальный%20Вал%20ул.%2C%20вл.%203
A38: 666 | B38: =VLOOKUP($A38,'Реестр объектов'!$A:$I,5,0) -> ул. Константинова, з/у 2 (ул. Константинова, вл. 2) СВАО, район Алексеевский, ул. Константинова, влд. 2 | C38: =VLOOKUP($A38,'Реестр объектов'!$A:$I,6,0) -> 55.813415 | D38: =VLOOKUP($A38,'Реестр объектов'!$A:$I,7,0) -> 37.652562 | E38: Admin | F38: МФР 26 | J38: =VLOOKUP($A38,'Реестр объектов'!$A:$I,8,0) -> https://docs.google.com/spreadsheets/d/1rbCD10ySi4YZEkJW2_Slmn9z7AI1WEsGsZaIJmnnT18/edit?gid=989644917#gid=989644917 | K38: =VLOOKUP($A38,'Реестр объектов'!$A:$I,9,0) -> https://disk.yandex.ru/client/disk/Осмотры%20объектов%20АНО%20СМГ/666.%20Константинова%20ул.%2C%20вл.%202
A39: 961 | B39: =VLOOKUP($A39,'Реестр объектов'!$A:$I,5,0) -> пр-д Береговой, з/у 9/1 (Береговой пр-д, вл.9, корп.1) район Филевский парк, Береговой пр-д, вл. 9, корп. 1 | C39: =VLOOKUP($A39,'Реестр объектов'!$A:$I,6,0) -> 55.754325 | D39: =VLOOKUP($A39,'Реестр объектов'!$A:$I,7,0) -> 37.504466 | E39: Admin | F39: МФР 26 | J39: =VLOOKUP($A39,'Реестр объектов'!$A:$I,8,0) -> https://docs.google.com/spreadsheets/d/1rbCD10ySi4YZEkJW2_Slmn9z7AI1WEsGsZaIJmnnT18/edit?gid=3034090#gid=3034090 | K39: =VLOOKUP($A39,'Реестр объектов'!$A:$I,9,0) -> https://disk.yandex.ru/client/disk/Осмотры%20объектов%20АНО%20СМГ/961.%20Жилой%20дом%20Береговой%20проезд%209к1
A40: 673 | B40: =VLOOKUP($A40,'Реестр объектов'!$A:$I,5,0) -> Велозаводская ул., з/у 2 ЮАО, район Даниловский, Велозаводская ул., вл.2 | C40: =VLOOKUP($A40,'Реестр объектов'!$A:$I,6,0) -> 55.715704 | D40: =VLOOKUP($A40,'Реестр объектов'!$A:$I,7,0) -> 37.663933 | E40: Гытлан Роман Валентинович | F40: МФР 26 | J40: =VLOOKUP($A40,'Реестр объектов'!$A:$I,8,0) -> https://docs.google.com/spreadsheets/d/1rbCD10ySi4YZEkJW2_Slmn9z7AI1WEsGsZaIJmnnT18/edit?gid=1509964288#gid=1509964288 | K40: =VLOOKUP($A40,'Реестр объектов'!$A:$I,9,0) -> https://disk.yandex.ru/client/disk/Осмотры%20объектов%20АНО%20СМГ/673.%20Велозаводская%20ул.%2C%20з.у%202
A41: 819 | B41: =VLOOKUP($A41,'Реестр объектов'!$A:$I,5,0) -> микрорайон 6 района Коньково, зона № 1.3 района Коньково ул. Введенского, 9 микрорайон 6, зона № 1.3 (со сносом жилых зданий по адресам: ул. Введенского, д. 9; ул. Введенского, д. 11, корп. 1; ул. Введенского, д. 11, корп. 2; ул. Введенского, д. 11, корп. 3) | C41: =VLOOKUP($A41,'Реестр объектов'!$A:$I,6,0) -> 55.642963 | D41: =VLOOKUP($A41,'Реестр объектов'!$A:$I,7,0) -> 37.542380 | E41: Данилов Семен Юрьевич | F41: МФР 26 | J41: =VLOOKUP($A41,'Реестр объектов'!$A:$I,8,0) -> https://docs.google.com/spreadsheets/d/1rbCD10ySi4YZEkJW2_Slmn9z7AI1WEsGsZaIJmnnT18/edit?gid=1872184030#gid=1872184030 | K41: =VLOOKUP($A41,'Реестр объектов'!$A:$I,9,0) -> https://disk.yandex.ru/client/disk/Осмотры%20объектов%20АНО%20СМГ/819.%20района%20Коньково%20ул.%20Введенского%2C%209%20микрорайон%206%2C%20зона%20№%201.3
... A50: 598 | B50: =VLOOKUP($A50,'Реестр объектов'!$A:$I,5,0) -> ул. Амурская, земельный участок 1/11 (зоны 3.1, 3.2) район Гольяново, Амурская ул., вл. 1, зона № 3.1, 3.2 (улица Амурская, з/у 1/11) | C50: =VLOOKUP($A50,'Реестр объектов'!$A:$I,6,0) -> 55.808457 | D50: =VLOOKUP($A50,'Реестр объектов'!$A:$I,7,0) -> 37.753995 | E50: Лашин Александр Николаевич | F50: МФР 26 | J50: =VLOOKUP($A50,'Реестр объектов'!$A:$I,8,0) -> https://docs.google.com/spreadsheets/d/1rbCD10ySi4YZEkJW2_Slmn9z7AI1WEsGsZaIJmnnT18/edit?gid=798053940#gid=798053940 | K50: =VLOOKUP($A50,'Реестр объектов'!$A:$I,9,0) -> https://disk.yandex.ru/client/disk/Осмотры%20объектов%20АНО%20СМГ/598.%20ВАО%2C%20Амурская%20ул%20вл.1%20зона%20N%203.1%2C3.2%20(з_у%201_11)
A51: 829 | B51: =VLOOKUP($A51,'Реестр объектов'!$A:$I,5,0) -> улица Юных Ленинцев, земельный участок 103 (участок 12.4) улица Юных Ленинцев, земельный участок 103 (участок 12.4) | C51: =VLOOKUP($A51,'Реестр объектов'!$A:$I,6,0) -> 55.699947 | D51: =VLOOKUP($A51,'Реестр объектов'!$A:$I,7,0) -> 37.781703 | E51: Дрозд Александр Викторович | F51: МФР 26 | G51: 45975.351 | H51: 45975.423 | I51: 103 мин | J51: =VLOOKUP($A51,'Реестр объектов'!$A:$I,8,0) -> https://docs.google.com/spreadsheets/d/1rbCD10ySi4YZEkJW2_Slmn9z7AI1WEsGsZaIJmnnT18/edit?gid=256251800#gid=256251800 | K51: =VLOOKUP($A51,'Реестр объектов'!$A:$I,9,0) -> https://disk.yandex.ru/client/disk/Осмотры%20объектов%20АНО%20СМГ/829.%20Ул.%20Юных%20Ленинцев%2C%20з-у%20103%20(уч.%2012.4).%20Жилой%20дом
A52: 832 | B52: =VLOOKUP($A52,'Реестр объектов'!$A:$I,5,0) -> шоссе Волоколамское, земельный участок 106 СЗАО шоссе Волоколамское, земельный участок 106 | C52: =VLOOKUP($A52,'Реестр объектов'!$A:$I,6,0) -> 55.826736 | D52: =VLOOKUP($A52,'Реестр объектов'!$A:$I,7,0) -> 37.428314 | E52: Admin | F52: МФР 26 | J52: =VLOOKUP($A52,'Реестр объектов'!$A:$I,8,0) -> https://docs.google.com/spreadsheets/d/1rbCD10ySi4YZEkJW2_Slmn9z7AI1WEsGsZaIJmnnT18/edit?gid=1402094174#gid=1402094174 | K52: =VLOOKUP($A52,'Реестр объектов'!$A:$I,9,0) -> https://disk.yandex.ru/client/disk/Осмотры%20объектов%20АНО%20СМГ/832.%20Волоколамское%20шоссе%2C%20зу%20106
A53: 717 | B53: =VLOOKUP($A53,'Реестр объектов'!$A:$I,5,0) -> Даниловская набережная, земельный участок 8 (вл. 8) ЮАО, район Даниловский, Даниловская набережная, земельный участок 8 (Даниловская наб., вл. 8) | C53: =VLOOKUP($A53,'Реестр объектов'!$A:$I,6,0) -> 55.709430 | D53: =VLOOKUP($A53,'Реестр объектов'!$A:$I,7,0) -> 37.636083 | E53: Гытлан Роман Валентинович | F53: МФР 26 | J53: =VLOOKUP($A53,'Реестр объектов'!$A:$I,8,0) -> https://docs.google.com/spreadsheets/d/1rbCD10ySi4YZEkJW2_Slmn9z7AI1WEsGsZaIJmnnT18/edit?gid=756416994#gid=756416994 | K53: =VLOOKUP($A53,'Реестр объектов'!$A:$I,9,0) -> https://disk.yandex.ru/client/disk/Осмотры%20объектов%20АНО%20СМГ/717.%20Даниловская%20набережная%2C%20вл.%208
A54: 1156 | B54: =VLOOKUP($A54,'Реестр объектов'!$A:$I,5,0) -> улица Леснорядская, земельный участок 7 ЦАО, район Красносельский, Леснорядская ул., вл. 7, 2-я Леснорядская ул., д. 10-12, стр. 1 | C54: =VLOOKUP($A54,'Реестр объектов'!$A:$I,6,0) -> 55.782122 | D54: =VLOOKUP($A54,'Реестр объектов'!$A:$I,7,0) -> 37.676403 | E54: Admin | F54: МФР 26 | J54: =VLOOKUP($A54,'Реестр объектов'!$A:$I,8,0) -> https://docs.google.com/spreadsheets/d/1rbCD10ySi4YZEkJW2_Slmn9z7AI1WEsGsZaIJmnnT18/edit?gid=2030780082#gid=2030780082 | K54: =VLOOKUP($A54,'Реестр объектов'!$A:$I,9,0) -> https://disk.yandex.ru/client/disk/Осмотры%20объектов%20АНО%20СМГ/1156.%20Леснорядская%20улица%20земельный%20участок%207
A55: 622 | B55: =VLOOKUP($A55,'Реестр объектов'!$A:$I,5,0) -> Новохорошёвский пр-д, влд. 6/1 (вл. 6) СЗАО Новохорошёвский пр-д, влд. 6/1 (вл. 6) | C55: =VLOOKUP($A55,'Реестр объектов'!$A:$I,6,0) -> 55.778451 | D55: =VLOOKUP($A55,'Реестр объектов'!$A:$I,7,0) -> 37.498935 | E55: Admin | F55: МФР 26 | J55: =VLOOKUP($A55,'Реестр объектов'!$A:$I,8,0) -> https://docs.google.com/spreadsheets/d/1rbCD10ySi4YZEkJW2_Slmn9z7AI1WEsGsZaIJmnnT18/edit?gid=808253211#gid=808253211 | K55: =VLOOKUP($A55,'Реестр объектов'!$A:$I,9,0) -> https://disk.yandex.ru/client/disk/Осмотры%20объектов%20АНО%20СМГ/622.%20Новохорошевский%20пр-д.%2C%20вл.%206.1
A56: 634 | B56: =VLOOKUP($A56,'Реестр объектов'!$A:$I,5,0) -> Новохорошёвский пр-д, влд. 24/3/1 (вл. 24, к. 3) СЗАО, район Хорошево-Мневники, Новохорошевский проезд, вл. 24/3/1 | C56: =VLOOKUP($A56,'Реестр объектов'!$A:$I,6,0) -> 55.779797 | D56: =VLOOKUP($A56,'Реестр объектов'!$A:$I,7,0) -> 37.492350 | E56: Admin | F56: МФР 26 | J56: =VLOOKUP($A56,'Реестр объектов'!$A:$I,8,0) -> https://docs.google.com/spreadsheets/d/1rbCD10ySi4YZEkJW2_Slmn9z7AI1WEsGsZaIJmnnT18/edit?gid=326389439#gid=326389439 | K56: =VLOOKUP($A56,'Реестр объектов'!$A:$I,9,0) -> https://disk.yandex.ru/client/disk/Осмотры%20объектов%20АНО%20СМГ/634.%20Новохорошевский%20пр-д.%2C%20вл.%2024.3.1
A57: 621 | B57: =VLOOKUP($A57,'Реестр объектов'!$A:$I,5,0) -> Жилой дом с инженерными сетями и благоустройством территории, САО, район Коптево, Генерала Рычагова ул., вл. 14 САО, район Коптево, Генерала Рычагова ул., вл. 14 | C57: =VLOOKUP($A57,'Реестр объектов'!$A:$I,6,0) -> 55.840465 | D57: =VLOOKUP($A57,'Реестр объектов'!$A:$I,7,0) -> 37.536380 | E57: Admin | F57: МФР 26 | J57: =VLOOKUP($A57,'Реестр объектов'!$A:$I,8,0) -> https://docs.google.com/spreadsheets/d/1rbCD10ySi4YZEkJW2_Slmn9z7AI1WEsGsZaIJmnnT18/edit?gid=1726616701#gid=1726616701 | K57: =VLOOKUP($A57,'Реестр объектов'!$A:$I,9,0) -> https://disk.yandex.ru/client/disk/Осмотры%20объектов%20АНО%20СМГ/621.%20Район%20Коптево%2C%20Генерала%20Рычагова%20ул.%2C%20вл.14
A58: 647 | B58: =VLOOKUP($A58,'Реестр объектов'!$A:$I,5,0) -> ул. Давыдковская, вл.16 ЗАО, район Фили-Давыдково, Давыдковская ул., вл. 16 (рефинансирование) | C58: =VLOOKUP($A58,'Реестр объектов'!$A:$I,6,0) -> 55.719924 | D58: =VLOOKUP($A58,'Реестр объектов'!$A:$I,7,0) -> 37.466579 | E58: Admin | F58: МФР 26 | J58: =VLOOKUP($A58,'Реестр объектов'!$A:$I,8,0) -> https://docs.google.com/spreadsheets/d/1rbCD10ySi4YZEkJW2_Slmn9z7AI1WEsGsZaIJmnnT18/edit?gid=676192549#gid=676192549 | K58: =VLOOKUP($A58,'Реестр объектов'!$A:$I,9,0) -> https://disk.yandex.ru/client/disk/Осмотры%20объектов%20АНО%20СМГ/647.%20Жилой%20дом%20ул.%20Давыдковская%20вл16
A59: 573 | B59: =VLOOKUP($A59,'Реестр объектов'!$A:$I,5,0) -> Б. Черемушкинская ул., вл. 25Б) за границами ППТ, микрорайонов 67,68, кв-лов 103,104,105,106 ЮЗАО, район Котловка, микрорайонов 67,68, кварталов 103,104,105,106, Б.Черемушкинская ул. (Б. Черемушкинская ул., вл. 25Б) | C59: =VLOOKUP($A59,'Реестр объектов'!$A:$I,6,0) -> 55.677745 | D59: =VLOOKUP($A59,'Реестр объектов'!$A:$I,7,0) -> 37.592998 | E59: Удалкин Иван Вячеславович | F59: МФР 26 | J59: =VLOOKUP($A59,'Реестр объектов'!$A:$I,8,0) -> https://docs.google.com/spreadsheets/d/1rbCD10ySi4YZEkJW2_Slmn9z7AI1WEsGsZaIJmnnT18/edit?gid=2138822298#gid=2138822298 | K59: =VLOOKUP($A59,'Реестр объектов'!$A:$I,9,0) -> https://disk.yandex.ru/client/disk/Осмотры%20объектов%20АНО%20СМГ/573.%20Б.Черемушкинская%2025Б%20Жилой%20дом
A60: 618 | B60: =VLOOKUP($A60,'Реестр объектов'!$A:$I,5,0) -> ул. Подвойского, з/у 12/15 (зона 1.1) ЦАО, район Пресненский,кв. 804, 798 зона 1.1 Подвойского ул., вл. 12/15 | C60: =VLOOKUP($A60,'Реестр объектов'!$A:$I,6,0) -> 55.761833 | D60: =VLOOKUP($A60,'Реестр объектов'!$A:$I,7,0) -> 37.537364 | E60: Admin | F60: МФР 26 | J60: =VLOOKUP($A60,'Реестр объектов'!$A:$I,8,0) -> https://docs.google.com/spreadsheets/d/1rbCD10ySi4YZEkJW2_Slmn9z7AI1WEsGsZaIJmnnT18/edit?gid=188482008#gid=188482008 | K60: =VLOOKUP($A60,'Реестр объектов'!$A:$I,9,0) -> https://disk.yandex.ru/client/disk/Осмотры%20объектов%20АНО%20СМГ/618.%20Подвойского%20вл%2012%5C15
A61: 637 | B61: =VLOOKUP($A61,'Реестр объектов'!$A:$I,5,0) -> Хорошево-Мневники, мкр. 83, 84-85, 86, зона № 9.1 район Хорошево-Мневники,Новикова Прибоя, зу 6/2, мкр. 83, 84-85, 86, зона № 9.1 (со сносом жилых зданий по адресам: наб. Новикова-Прибоя, д. 6, корп. 2; наб. Новикова-Прибоя, д. 6, корп. 3) | C61: =VLOOKUP($A61,'Реестр объектов'!$A:$I,6,0) -> 55.782351 | D61: =VLOOKUP($A61,'Реестр объектов'!$A:$I,7,0) -> 37.448956 | E61: Admin | F61: МФР 26 | J61: =VLOOKUP($A61,'Реестр объектов'!$A:$I,8,0) -> https://docs.google.com/spreadsheets/d/1rbCD10ySi4YZEkJW2_Slmn9z7AI1WEsGsZaIJmnnT18/edit?gid=370993780#gid=370993780 | K61: =VLOOKUP($A61,'Реестр объектов'!$A:$I,9,0) -> https://disk.yandex.ru/client/disk/Осмотры%20объектов%20АНО%20СМГ/637.%20Хорошево-Мневники%2CНовикова%20Прибоя%2C%20зу%206.2
A62: 620 | B62: =VLOOKUP($A62,'Реестр объектов'!$A:$I,5,0) -> ул. Долгопрудная, з/у 6 САО, район Дмитровский, улица Долгопрудная, з/у 6, мкр. 15, 16, 17, 18 (Зона 10.5) (со сносом жилых зданий по адресам: Долгопрудная ул., д.6, к.1; Дмитровское шоссе, д.143, к.1) | C62: =VLOOKUP($A62,'Реестр объектов'!$A:$I,6,0) -> 55.893782 | D62: =VLOOKUP($A62,'Реестр объектов'!$A:$I,7,0) -> 37.540875 | E62: Admin | F62: МФР 26 | J62: =VLOOKUP($A62,'Реестр объектов'!$A:$I,8,0) -> https://docs.google.com/spreadsheets/d/1rbCD10ySi4YZEkJW2_Slmn9z7AI1WEsGsZaIJmnnT18/edit?gid=953902791#gid=953902791 | K62: =VLOOKUP($A62,'Реестр объектов'!$A:$I,9,0) -> https://disk.yandex.ru/client/disk/Осмотры%20объектов%20АНО%20СМГ/620.%20%20ул.%20Долгопрудная%20з.у.%206
A63: 930 | B63: =VLOOKUP($A63,'Реестр объектов'!$A:$I,5,0) -> Жилой дом с приспособлением подземной автостоянки под защитное сооружение гражданской обороны - «укрытие» (ЗСГО) с инженерными сетями и благоустройством территории (со сносом жилого здания по адресу: ул. Изумрудная, д. 12) по адресу: г. Москва, внутригородское муниципальное образование Лосиноостровское, Изумрудная улица, земельный участок 12А Лосиноостровское, Изумрудная улица, земельный участок 12А | C63: =VLOOKUP($A63,'Реестр объектов'!$A:$I,6,0) -> 55.869268 | D63: =VLOOKUP($A63,'Реестр объектов'!$A:$I,7,0) -> 37.680814 | E63: Admin | F63: МФР 26 | J63: =VLOOKUP($A63,'Реестр объектов'!$A:$I,8,0) -> https://docs.google.com/spreadsheets/d/1rbCD10ySi4YZEkJW2_Slmn9z7AI1WEsGsZaIJmnnT18/edit?gid=1131436691#gid=1131436691 | K63: =VLOOKUP($A63,'Реестр объектов'!$A:$I,9,0) -> https://disk.yandex.ru/client/disk/Осмотры%20объектов%20АНО%20СМГ/930%20Изумрудная%20ул.%2C%20зу%2012А
A64: 923 | B64: =VLOOKUP($A64,'Реестр объектов'!$A:$I,5,0) -> Жилой дом с инженерными сетями и благоустройством территории (со сносом жилых домов по адресам: г. Москва, ул. Бахтерева, д. 3, к. 1, ул. Бахтерева, д. 3, к. 2, ул. Бахтерева, д. 5), ЮАО, район Царицыно, Бехтерева ул., вл. 3/5 ул. Бехтерева, з/у 3/5 | C64: =VLOOKUP($A64,'Реестр объектов'!$A:$I,6,0) -> 55.635583 | D64: =VLOOKUP($A64,'Реестр объектов'!$A:$I,7,0) -> 37.649688 | E64: Удалкин Иван Вячеславович | F64: МФР 26 | G64: 45975.368 | H64: 45975.443 | I64: 108 мин | J64: =VLOOKUP($A64,'Реестр объектов'!$A:$I,8,0) -> https://docs.google.com/spreadsheets/d/1rbCD10ySi4YZEkJW2_Slmn9z7AI1WEsGsZaIJmnnT18/edit?gid=657849366#gid=657849366 | K64: =VLOOKUP($A64,'Реестр объектов'!$A:$I,9,0) -> https://disk.yandex.ru/client/disk/Осмотры%20объектов%20АНО%20СМГ/923.%20Бехтерева%20ул.%2C%20з-у%203-5.%20Жилой%20дом
A65: 611 | B65: =VLOOKUP($A65,'Реестр объектов'!$A:$I,5,0) -> Жилой дом с подземной автостоянкой, инженерными сетями и благоустройством территории по адресу: г. Москва, район Дмитровский, Карельский бульвар, вл. 1/24 (Клязьминская ул., вл.26) район Дмитровский, Карельский бульвар, вл. 1/24 (Клязьминская ул., вл.26) | C65: =VLOOKUP($A65,'Реестр объектов'!$A:$I,6,0) -> 55.892306 | D65: =VLOOKUP($A65,'Реестр объектов'!$A:$I,7,0) -> 37.530438 | E65: Admin | F65: МФР 26 | J65: =VLOOKUP($A65,'Реестр объектов'!$A:$I,8,0) -> https://docs.google.com/spreadsheets/d/1rbCD10ySi4YZEkJW2_Slmn9z7AI1WEsGsZaIJmnnT18/edit?gid=44169429#gid=44169429 | K65: =VLOOKUP($A65,'Реестр объектов'!$A:$I,9,0) -> https://disk.yandex.ru/client/disk/Осмотры%20объектов%20АНО%20СМГ/611.%20Карельский%20бульвар%2C%20вл.%201.24
A66: 719 | B66: =VLOOKUP($A66,'Реестр объектов'!$A:$I,5,0) -> ул. Гарибальди, вл. 25, корп. 1 (6.1) (Профсоюзная ул., з/у 37 (зоны 6.1 и 6.2) (со сносом: ул. Профсоюзная д. 37)) ЮЗАО, Черемушки, ул. Гарибальди, вл. 25, жилых зданий по адресам: ул. Профсоюзная д.39; ул. Гарибальди д.25 к.1; Гарибильди д.25 стр.2) | C66: =VLOOKUP($A66,'Реестр объектов'!$A:$I,6,0) -> 55.670546 | D66: =VLOOKUP($A66,'Реестр объектов'!$A:$I,7,0) -> 37.556150 | E66: Удалкин Иван Вячеславович | F66: МФР 26 | J66: =VLOOKUP($A66,'Реестр объектов'!$A:$I,8,0) -> https://docs.google.com/spreadsheets/d/1rbCD10ySi4YZEkJW2_Slmn9z7AI1WEsGsZaIJmnnT18/edit?gid=1797830857#gid=1797830857 | K66: =VLOOKUP($A66,'Реестр объектов'!$A:$I,9,0) -> https://disk.yandex.ru/client/disk/Осмотры%20объектов%20АНО%20СМГ/719.%20ул.%20Грибальди%20вл25%2C%20Профсоюзная%20д39%20(Гарибальди%20д25%20к1%2C%20д25%20стр2)
A67: 687 | B67: =VLOOKUP($A67,'Реестр объектов'!$A:$I,5,0) -> Жилой дом с инженерными сетями и благоустройством территории (со сносом жилых зданий по адресам: ул. Восточная д.1, корп. 1 и Пересветов пер., д.1, корп.2), ЮАО, район Даниловский, Восточная ул., 1 ЮАО, район Даниловский, Восточная ул., 1 | C67: =VLOOKUP($A67,'Реестр объектов'!$A:$I,6,0) -> 55.716559 | D67: =VLOOKUP($A67,'Реестр объектов'!$A:$I,7,0) -> 37.662180 | E67: Admin | F67: МФР 26 | J67: =VLOOKUP($A67,'Реестр объектов'!$A:$I,8,0) -> https://docs.google.com/spreadsheets/d/1rbCD10ySi4YZEkJW2_Slmn9z7AI1WEsGsZaIJmnnT18/edit?gid=1343620006#gid=1343620006 | K67: =VLOOKUP($A67,'Реестр объектов'!$A:$I,9,0) -> https://disk.yandex.ru/client/disk/Осмотры%20объектов%20АНО%20СМГ/687.%20Даниловский%2C%20Восточная%20ул%201
A68: 731 | B68: =VLOOKUP($A68,'Реестр объектов'!$A:$I,5,0) -> ул. Циолковского, вл. 3 район Покровское-Стрешнево, ул. Циолковского, вл. 3 (со сносом нежилых зданий по адресам: г. Москва, район Покровское-Стрешнево, улица Циолковского, д. 3 стр. 1, д. 3 стр. 2, д. 3 стр. 3) | C68: =VLOOKUP($A68,'Реестр объектов'!$A:$I,6,0) -> 55.828250 | D68: =VLOOKUP($A68,'Реестр объектов'!$A:$I,7,0) -> 37.450018 | E68: Admin | F68: МФР 26 | J68: =VLOOKUP($A68,'Реестр объектов'!$A:$I,8,0) -> https://docs.google.com/spreadsheets/d/1rbCD10ySi4YZEkJW2_Slmn9z7AI1WEsGsZaIJmnnT18/edit?gid=24415394#gid=24415394 | K68: =VLOOKUP($A68,'Реестр объектов'!$A:$I,9,0) -> https://disk.yandex.ru/client/disk/Осмотры%20объектов%20АНО%20СМГ/731.%20ул.%20Циолковского%2C%20вл.%203
A69: 688 | B69: =VLOOKUP($A69,'Реестр объектов'!$A:$I,5,0) -> Рязанский просп., з/у 6А (Рязанский пр-т, вл. 6А) ЮВАО, район Рязанский, Рязанский проспект, земельный участок 6А (Рязанский пр-т, вл.6А) | C69: =VLOOKUP($A69,'Реестр объектов'!$A:$I,6,0) -> 55.723657 | D69: =VLOOKUP($A69,'Реестр объектов'!$A:$I,7,0) -> 37.742319 | E69: Джинджолия Леван Раульевич | F69: МФР 26 | G69: 45975.392 | H69: 45975.455 | I69: 91 мин | J69: =VLOOKUP($A69,'Реестр объектов'!$A:$I,8,0) -> https://docs.google.com/spreadsheets/d/1rbCD10ySi4YZEkJW2_Slmn9z7AI1WEsGsZaIJmnnT18/edit?gid=1617286788#gid=1617286788 | K69: =VLOOKUP($A69,'Реестр объектов'!$A:$I,9,0) -> https://disk.yandex.ru/client/disk/Осмотры%20объектов%20АНО%20СМГ/688.%20ЮВАО%2C%20район%20Рязанский%2C%20Рязанский%20проспект%2C%20земельный%20участок%206А%20(Рязанский%20пр-т%2C%20вл.6А)
A70: 675 | B70: =VLOOKUP($A70,'Реестр объектов'!$A:$I,5,0) -> ул. Байкальская, з/у 28/3 (ул. Байкалькая, влд.28) ВАО, район Гольяново, ул. Байкальская, з/у. 28/3, мкр. 3, 4, 5, зона 8.1 (со сносом зданий по адресу: ул. Байкальская, д. 28, к. 3) | C70: =VLOOKUP($A70,'Реестр объектов'!$A:$I,6,0) -> 55.814913 | D70: =VLOOKUP($A70,'Реестр объектов'!$A:$I,7,0) -> 37.802368 | E70: Лашин Александр Николаевич | F70: МФР 26 | J70: =VLOOKUP($A70,'Реестр объектов'!$A:$I,8,0) -> https://docs.google.com/spreadsheets/d/1rbCD10ySi4YZEkJW2_Slmn9z7AI1WEsGsZaIJmnnT18/edit?gid=1349297378#gid=1349297378 | K70: =VLOOKUP($A70,'Реестр объектов'!$A:$I,9,0) -> https://disk.yandex.ru/client/disk/Осмотры%20объектов%20АНО%20СМГ/675%20Гольяново%2C%20ул%20Байкальская%20зу%2028.3%20мкрн%203%2C4%2C5%20зона%208.1%20со%20сносом%20здания | L70: Лашин Александр Николаевич
A71: 729 | B71: =VLOOKUP($A71,'Реестр объектов'!$A:$I,5,0) -> ул. Хлобыстова, земельныйучасток 16/2/1 (Зоны 1.1, 1.2, 1.3) ЮВАО, мкр. 128 Б-В, район Выхино-Жулебино зона 1.1, 1.2, 1.3 Хлобыстова ул., зу 16/2/1 (со сносом жилых домов по адресам: Рязанский проспект д. 95, корп. 3; Рязанский проспект д. 95, корп. 4, Рязанский проспект д. 91, корп. 4) | C71: =VLOOKUP($A71,'Реестр объектов'!$A:$I,6,0) -> 55.716129 | D71: =VLOOKUP($A71,'Реестр объектов'!$A:$I,7,0) -> 37.807696 | E71: Дрозд Александр Викторович | F71: МФР 26 | J71: =VLOOKUP($A71,'Реестр объектов'!$A:$I,8,0) -> https://docs.google.com/spreadsheets/d/1rbCD10ySi4YZEkJW2_Slmn9z7AI1WEsGsZaIJmnnT18/edit?gid=1910790925#gid=1910790925 | K71: =VLOOKUP($A71,'Реестр объектов'!$A:$I,9,0) -> https://disk.yandex.ru/client/disk/Осмотры%20объектов%20АНО%20СМГ/729%20ЮВАО%2C%20мкр.%20128%20Б-В%2C%20район%20Выхино-Жулебино%20зона%201.1%2C%201.2%2C%201.3%20Хлобыстова%20ул.%2C%20зу%2016.2.1
A72: 690 | B72: =VLOOKUP($A72,'Реестр объектов'!$A:$I,5,0) -> Ломоносовский район, микрорайон 15, номер зоны 1.2 ЮЗАО, район Ломоносовский, ул. Вавилова ул., 76, микрорайон 15, зона 1.2, (со сносом жилых зданий по адресам: ул. Вавилова, д.76; ул. Панферова, д.16 корп.2) | C72: =VLOOKUP($A72,'Реестр объектов'!$A:$I,6,0) -> 55.680083 | D72: =VLOOKUP($A72,'Реестр объектов'!$A:$I,7,0) -> 37.544428 | E72: Удалкин Иван Вячеславович | F72: МФР 26 | J72: =VLOOKUP($A72,'Реестр объектов'!$A:$I,8,0) -> https://docs.google.com/spreadsheets/d/1rbCD10ySi4YZEkJW2_Slmn9z7AI1WEsGsZaIJmnnT18/edit?gid=1573037531#gid=1573037531 | K72: =VLOOKUP($A72,'Реестр объектов'!$A:$I,9,0) -> https://disk.yandex.ru/client/disk/Осмотры%20объектов%20АНО%20СМГ/690.%20район%20Ломоносовский%2C%20ул.%20Вавилова%20ул.%2C%2076%2C%20микрорайон%2015%2C%20зона%201.2%2C
A73: 654 | B73: =VLOOKUP($A73,'Реестр объектов'!$A:$I,5,0) -> Полярная ул., з/у 16 (Полярная ул., вл. 16) СВАО, район Южное Медведково, ул. Полярная, з/у 16 (со сносом жилого здания по адресу: ул. Полярная д.16, корп.1) (рефинансирование) | C73: =VLOOKUP($A73,'Реестр объектов'!$A:$I,6,0) -> 55.876612 | D73: =VLOOKUP($A73,'Реестр объектов'!$A:$I,7,0) -> 37.637299 | E73: Admin | F73: МФР 26 | J73: =VLOOKUP($A73,'Реестр объектов'!$A:$I,8,0) -> https://docs.google.com/spreadsheets/d/1rbCD10ySi4YZEkJW2_Slmn9z7AI1WEsGsZaIJmnnT18/edit?gid=877224124#gid=877224124 | K73: =VLOOKUP($A73,'Реестр объектов'!$A:$I,9,0) -> https://disk.yandex.ru/client/disk/Осмотры%20объектов%20АНО%20СМГ/654.%20ул.%20Полярная%2C%20з.у.%2016
A74: 649 | B74: =VLOOKUP($A74,'Реестр объектов'!$A:$I,5,0) -> 3-я Прядильная ул., з/у 4 (3-я Прядильная ул. вл.4) ВАО, район Измайлово, 3-я Прядильная ул., зу 4 (рефинансирование) | C74: =VLOOKUP($A74,'Реестр объектов'!$A:$I,6,0) -> 55.797134 | D74: =VLOOKUP($A74,'Реестр объектов'!$A:$I,7,0) -> 37.771091 | E74: Лашин Александр Николаевич | F74: МФР 26 | G74: 45975.406 | H74: 45975.487 | I74: 117 мин | J74: =VLOOKUP($A74,'Реестр объектов'!$A:$I,8,0) -> https://docs.google.com/spreadsheets/d/1rbCD10ySi4YZEkJW2_Slmn9z7AI1WEsGsZaIJmnnT18/edit?gid=9074212#gid=9074212 | K74: =VLOOKUP($A74,'Реестр объектов'!$A:$I,9,0) -> https://disk.yandex.ru/client/disk/Осмотры%20объектов%20АНО%20СМГ/649%203-я%20Прядильная%20ул.%2C%20зу%204
A75: 971 | B75: =VLOOKUP($A75,'Реестр объектов'!$A:$I,5,0) -> ул. Судакова, з/у 5 (Судакова ул., влд. 5) ул. Судакова, з/у 5 (судакова ул., влд. 5) | C75: =VLOOKUP($A75,'Реестр объектов'!$A:$I,6,0) -> 55.672750 | D75: =VLOOKUP($A75,'Реестр объектов'!$A:$I,7,0) -> 37.742580 | E75: Гытлан Роман Валентинович | F75: МФР 26 | G75: 45975.358 | H75: 45975.426 | I75: 99 мин | J75: =VLOOKUP($A75,'Реестр объектов'!$A:$I,8,0) -> https://docs.google.com/spreadsheets/d/1rbCD10ySi4YZEkJW2_Slmn9z7AI1WEsGsZaIJmnnT18/edit?gid=1956094116#gid=1956094116 | K75: =VLOOKUP($A75,'Реестр объектов'!$A:$I,9,0) -> https://disk.yandex.ru/client/disk/Осмотры%20объектов%20АНО%20СМГ/971.%20ул.%20Судакова%2C%20з.у%205%20(Судакова%20ул.%2C%20влд.%205)
A76: 792 | B76: =VLOOKUP($A76,'Реестр объектов'!$A:$I,5,0) -> Бескудниковский бульвар, земельный участок 48 (Зоны 3.2, 3.4) (Приобретение объектов недвижимости) Бескудниковский бульвар, земельный участок 48 (Зоны 3.2, 3.4) (Приобретение объектов недвижимости) | C76: =VLOOKUP($A76,'Реестр объектов'!$A:$I,6,0) -> 55.873961 | D76: =VLOOKUP($A76,'Реестр объектов'!$A:$I,7,0) -> 37.542338 | E76: Admin | F76: МФР 26 | J76: =VLOOKUP($A76,'Реестр объектов'!$A:$I,8,0) -> https://docs.google.com/spreadsheets/d/1rbCD10ySi4YZEkJW2_Slmn9z7AI1WEsGsZaIJmnnT18/edit?gid=105663629#gid=105663629 | K76: =VLOOKUP($A76,'Реестр объектов'!$A:$I,9,0) -> https://disk.yandex.ru/client/disk/Осмотры%20объектов%20АНО%20СМГ/792.%20Бескудниковский%20бульвар%2048
A77: 583 | B77: =VLOOKUP($A77,'Реестр объектов'!$A:$I,5,0) -> ул. Кубинка, з/у 16/1 (ул. Кубинка вл. 16-1) ЗАО, Можайский район, ул. Кубинка, земельный участок 16/1 (со сносом жилых зданий по адресу: ул. Кубинка, д.16 к.1) (кв. 71-72, 75 зона 4.1) | C77: =VLOOKUP($A77,'Реестр объектов'!$A:$I,6,0) -> 55.721179 | D77: =VLOOKUP($A77,'Реестр объектов'!$A:$I,7,0) -> 37.407834 | E77: Терехин Александр Андреевич | F77: МФР 26 | J77: =VLOOKUP($A77,'Реестр объектов'!$A:$I,8,0) -> https://docs.google.com/spreadsheets/d/1rbCD10ySi4YZEkJW2_Slmn9z7AI1WEsGsZaIJmnnT18/edit?gid=795869723#gid=795869723 | K77: =VLOOKUP($A77,'Реестр объектов'!$A:$I,9,0) -> https://disk.yandex.ru/client/disk/Осмотры%20объектов%20АНО%20СМГ/583.%20ЗАО%2C%20Можайский%20район%2C%20ул.%20Кубинка%2C%20земельный%20участок%2016-1%20%20(со%20сносом%20жилых%20зданий%20по%20адресу%3A%20ул.%20Кубинка%2C%20д.16%20к.1)%20(кв.%2071-72%2C%2075%20зона%204.1) | L77: Пулатов Алекс Шухратович
A78: 900 | B78: =VLOOKUP($A78,'Реестр объектов'!$A:$I,5,0) -> кв-л 9 района Академический, зона № 2.1 кв-л 9 района Академический, зона № 2.1 | C78: =VLOOKUP($A78,'Реестр объектов'!$A:$I,6,0) -> 55.675145 | D78: =VLOOKUP($A78,'Реестр объектов'!$A:$I,7,0) -> 37.574192 | E78: Удалкин Иван Вячеславович | F78: МФР 26 | J78: =VLOOKUP($A78,'Реестр объектов'!$A:$I,8,0) -> https://docs.google.com/spreadsheets/d/1rbCD10ySi4YZEkJW2_Slmn9z7AI1WEsGsZaIJmnnT18/edit?gid=1264505014#gid=1264505014 | K78: =VLOOKUP($A78,'Реестр объектов'!$A:$I,9,0) -> https://disk.yandex.ru/client/disk/Осмотры%20объектов%20АНО%20СМГ/900.%20кв-л%209%20района%20Академический%2C%20зона%20№%202.1
A79: 1332 | B79: =VLOOKUP($A79,'Реестр объектов'!$A:$I,5,0) -> Жилой дом с инженерными сетями и благоустройством территории (со сносом нежилых зданий по адресам: Варшавское шоссе, д.8А; Варшавское шоссе, д.10А), ЮАО, район Донской, Варшавское шоссе, земельный участок 8/10 (Варшавское шоссе, вл.8А-10А) Варшавское шоссе, вл.8А-10А | C79: =VLOOKUP($A79,'Реестр объектов'!$A:$I,6,0) -> 55.699085 | D79: =VLOOKUP($A79,'Реестр объектов'!$A:$I,7,0) -> 37.617942 | E79: Гытлан Роман Валентинович | F79: МФР 26 | J79: =VLOOKUP($A79,'Реестр объектов'!$A:$I,8,0) -> https://docs.google.com/spreadsheets/d/1rbCD10ySi4YZEkJW2_Slmn9z7AI1WEsGsZaIJmnnT18/edit?gid=1676819339#gid=1676819339 | K79: =VLOOKUP($A79,'Реестр объектов'!$A:$I,9,0)
A80: 926 | B80: =VLOOKUP($A80,'Реестр объектов'!$A:$I,5,0) -> Жилой дом с инженерными сетями и благоустройством территории (со сносом жилых зданий по адресам: ул. Минусинская, д. 10, ул. Минусинская, д. 12, ул. Минусинская, д. 14) по адресу: район Лосиноостровский, Минусинская улица, земельный участок 14А (ул. Минусинская, вл. 12-14) Минусинская ул., з/у 14А (ул. Минусинская, вл. 12-14) | C80: =VLOOKUP($A80,'Реестр объектов'!$A:$I,6,0) -> 55.874321 | D80: =VLOOKUP($A80,'Реестр объектов'!$A:$I,7,0) -> 37.692214 | E80: Admin | F80: МФР 26 | J80: =VLOOKUP($A80,'Реестр объектов'!$A:$I,8,0) -> https://docs.google.com/spreadsheets/d/1rbCD10ySi4YZEkJW2_Slmn9z7AI1WEsGsZaIJmnnT18/edit?gid=1472127211#gid=1472127211 | K80: =VLOOKUP($A80,'Реестр объектов'!$A:$I,9,0) -> https://disk.yandex.ru/client/disk/Осмотры%20объектов%20АНО%20СМГ/926%20Минусинская%2C%20зу%2014%20А
A81: 959 | B81: =VLOOKUP($A81,'Реестр объектов'!$A:$I,5,0) -> Приобретение жилых помещений, создаваемых в многоквартирных домах, предназначенных для переселения граждан при реализации Программы реновации жилищного фонда в городе Москве район Хорошевский, 3-й Хорошевский пр-д, вл. 5, корпус 1 | C81: =VLOOKUP($A81,'Реестр объектов'!$A:$I,6,0) -> 55.773687 | D81: =VLOOKUP($A81,'Реестр объектов'!$A:$I,7,0) -> 37.533742 | E81: Admin | F81: МФР 26 | J81: =VLOOKUP($A81,'Реестр объектов'!$A:$I,8,0) -> https://docs.google.com/spreadsheets/d/1rbCD10ySi4YZEkJW2_Slmn9z7AI1WEsGsZaIJmnnT18/edit?gid=868904483#gid=868904483 | K81: =VLOOKUP($A81,'Реестр объектов'!$A:$I,9,0) -> https://disk.yandex.ru/client/disk/Осмотры%20объектов%20АНО%20СМГ/959.%203-й%20Хорошевский%20пр-д%2C%20вл.%205%2C%20корп.%201
A82: 709 | B82: =VLOOKUP($A82,'Реестр объектов'!$A:$I,5,0) -> Жилой дом с инженерными сетями и благоустройством территории (со сносом жилых домов по адресам: 1-й квартал Капотня, дом 3; 1-й квартал Капотня, дом 4; 1-й квартал Капотня, дом 5; 1-й квартал Капотня, дом 12) ЮВАО, район Капотня, 1-й кв-л Капотни, зу 4 (со сносом жилых домов по адресам: 1-й квартал Капотня, дом 3; 1-й квартал Капотня, дом 4; 1-й квартал Капотня, дом 5; 1-й квартал Капотня, дом 12) | C82: =VLOOKUP($A82,'Реестр объектов'!$A:$I,6,0) -> 55.641518 | D82: =VLOOKUP($A82,'Реестр объектов'!$A:$I,7,0) -> 37.789049 | E82: Дрозд Александр Викторович | F82: МФР 26 | J82: =VLOOKUP($A82,'Реестр объектов'!$A:$I,8,0) -> https://docs.google.com/spreadsheets/d/1rbCD10ySi4YZEkJW2_Slmn9z7AI1WEsGsZaIJmnnT18/edit?gid=482221305#gid=482221305 | K82: =VLOOKUP($A82,'Реестр объектов'!$A:$I,9,0) -> https://disk.yandex.ru/client/disk/Осмотры%20объектов%20АНО%20СМГ/709.%201-й%20Квартал%20Капотни%2C%20з!у%204%2C%20д.3%2C%204%2C%205%2C%2012.%20Жилой%20дом
A83: 640 | B83: =VLOOKUP($A83,'Реестр объектов'!$A:$I,5,0) -> Суворовская ул., з/у 2А/1 (ул. Суворовская, вл. 2/1, корп. 3,4) район Преображенское, Суворовская улица, земельный участок 2А/1 (ул. Суворовская, вл. 2/1, корп. 3, 4) (со сносом жилых домов по адресам: г. Москва, район Преображенское, ул. Суворовская, д. 2/1, корп. 4; ул. Суворовская, д. 2/1, корп. 3) | C83: =VLOOKUP($A83,'Реестр объектов'!$A:$I,6,0) -> 55.787566 | D83: =VLOOKUP($A83,'Реестр объектов'!$A:$I,7,0) -> 37.710284 | E83: Admin | F83: МФР 26 | J83: =VLOOKUP($A83,'Реестр объектов'!$A:$I,8,0) -> https://docs.google.com/spreadsheets/d/1rbCD10ySi4YZEkJW2_Slmn9z7AI1WEsGsZaIJmnnT18/edit?gid=1703617430#gid=1703617430 | K83: =VLOOKUP($A83,'Реестр объектов'!$A:$I,9,0) -> https://disk.yandex.ru/client/disk/Осмотры%20объектов%20АНО%20СМГ/640.%20Суворовская%20ул.%2C%20зу%202А-1
A84: 676 | B84: =VLOOKUP($A84,'Реестр объектов'!$A:$I,5,0) -> Дмитровское ш., влд. 89 САО, район Бескудниковский, Дмитровское ш., вл. 89 (рефинансирование - 29,5 тыс.кв.м) | C84: =VLOOKUP($A84,'Реестр объектов'!$A:$I,6,0) -> 55.869208 | D84: =VLOOKUP($A84,'Реестр объектов'!$A:$I,7,0) -> 37.545436 | E84: Admin | F84: МФР 26 | J84: =VLOOKUP($A84,'Реестр объектов'!$A:$I,8,0) -> https://docs.google.com/spreadsheets/d/1rbCD10ySi4YZEkJW2_Slmn9z7AI1WEsGsZaIJmnnT18/edit?gid=915615615#gid=915615615 | K84: =VLOOKUP($A84,'Реестр объектов'!$A:$I,9,0) -> https://disk.yandex.ru/client/disk/Осмотры%20объектов%20АНО%20СМГ/676%20Дмитровское%20шоссе%20вл%2089
A85: 739 | B85: =VLOOKUP($A85,'Реестр объектов'!$A:$I,5,0) -> Сиреневый б-р, вл. 70 (Приобретение объектов недвижимости) ул. Сиреневый бульвар вл. 70 | C85: =VLOOKUP($A85,'Реестр объектов'!$A:$I,6,0) -> 55.801611 | D85: =VLOOKUP($A85,'Реестр объектов'!$A:$I,7,0) -> 37.833587 | E85: Лашин Александр Николаевич | F85: МФР 26 | J85: =VLOOKUP($A85,'Реестр объектов'!$A:$I,8,0) -> https://docs.google.com/spreadsheets/d/1rbCD10ySi4YZEkJW2_Slmn9z7AI1WEsGsZaIJmnnT18/edit?gid=64186922#gid=64186922 | K85: =VLOOKUP($A85,'Реестр объектов'!$A:$I,9,0) -> https://disk.yandex.ru/client/disk/Осмотры%20объектов%20АНО%20СМГ/739.%20Сиреневый%20бульвар%20вл%2070
A86: 726 | B86: =VLOOKUP($A86,'Реестр объектов'!$A:$I,5,0) -> Жилой дом с приспособлением подземного гаража под защитное сооружение гражданской обороны – «укрытие» (ЗСГО) с инженерными сетями и благоустройством территории (со сносом жилого дома по адресу: Самаркандский б-р. д.15 к.5) по адресу: г. Москва, внутригородское муниципальное образование Выхино- Жулебино, Самаркандский бульвар, земельный участок 15/5 (зона 5.3) район Выхино-Жулебино, Самаркандский бульвар, земельный участок 15/5 (зона 5.3) | C86: =VLOOKUP($A86,'Реестр объектов'!$A:$I,6,0) -> 55.697530 | D86: =VLOOKUP($A86,'Реестр объектов'!$A:$I,7,0) -> 37.817079 | E86: Дрозд Александр Викторович | F86: МФР 26 | J86: =VLOOKUP($A86,'Реестр объектов'!$A:$I,8,0) -> https://docs.google.com/spreadsheets/d/1rbCD10ySi4YZEkJW2_Slmn9z7AI1WEsGsZaIJmnnT18/edit?gid=178347413#gid=178347413 | K86: =VLOOKUP($A86,'Реестр объектов'!$A:$I,9,0) -> https://disk.yandex.ru/client/disk/Осмотры%20объектов%20АНО%20СМГ/726.%20Самаркандский%20б-р%2C%2015-5(реновация)
A87: 761 | B87: =VLOOKUP($A87,'Реестр объектов'!$A:$I,5,0) -> Жилой дом с инженерными сетями и благоустройством территории (со сносом жилых домов по адресам: Самаркандский б-р. д.15 к.2 и Самаркандский б-р. д.15 к.3) по адресу: г.Москва, внутригородское муниципальное образование Выхино-Жулебино, Самаркандский бульвар, земельный участок 15/2 (участок 5.1) ЮВАО Самаркандский бульвар, земельный участок 15/2 (участок 5.1) (ЮВАО) | C87: =VLOOKUP($A87,'Реестр объектов'!$A:$I,6,0) -> 55.696783 | D87: =VLOOKUP($A87,'Реестр объектов'!$A:$I,7,0) -> 37.816855 | E87: Дрозд Александр Викторович | F87: МФР 26 | G87: 45975.451 | H87: 45975.503 | I87: 76 мин | J87: =VLOOKUP($A87,'Реестр объектов'!$A:$I,8,0) -> https://docs.google.com/spreadsheets/d/1rbCD10ySi4YZEkJW2_Slmn9z7AI1WEsGsZaIJmnnT18/edit?gid=607897783#gid=607897783 | K87: =VLOOKUP($A87,'Реестр объектов'!$A:$I,9,0) -> https://disk.yandex.ru/client/disk/Осмотры%20объектов%20АНО%20СМГ/761.%20Самаркандский%20б-р%2C%20уч.%2015-2
A88: 763 | B88: =VLOOKUP($A88,'Реестр объектов'!$A:$I,5,0) -> Жилой дом с приспособлением подземного гаража под защитное сооружение гражданской обороны – «укрытие» (ЗСГО) с инженерными сетями и благоустройством территории (со сносом жилого дома по адресу: Самаркандский б-р. д.15 к.4) по адресу: г. Москва, внутригородское муниципальное образование Выхино- Жулебино, Самаркандский бульвар, земельный участок 15/4 (участок 5.2) ЮВАО Самаркандский бульвар, земельный участок 15/4 (участок 5.2) | C88: =VLOOKUP($A88,'Реестр объектов'!$A:$I,6,0) -> 55.696051 | D88: =VLOOKUP($A88,'Реестр объектов'!$A:$I,7,0) -> 37.818209 | E88: Дрозд Александр Викторович | F88: МФР 26 | G88: 45975.518 | J88: =VLOOKUP($A88,'Реестр объектов'!$A:$I,8,0) -> https://docs.google.com/spreadsheets/d/1rbCD10ySi4YZEkJW2_Slmn9z7AI1WEsGsZaIJmnnT18/edit?gid=829089146#gid=829089146 | K88: =VLOOKUP($A88,'Реестр объектов'!$A:$I,9,0) -> https://disk.yandex.ru/client/disk/Осмотры%20объектов%20АНО%20СМГ/763.%20Самаркандский%2015-4%20(Фонд%20реновации)
A89: 920 | B89: =VLOOKUP($A89,'Реестр объектов'!$A:$I,5,0) -> Жилой дом с инженерными сетями и благоустройством территории, СЗАО, район Южное Тушино, Новопоселковая ул., вл.6 ул. Новопоселковая, вл. 6 | C89: =VLOOKUP($A89,'Реестр объектов'!$A:$I,6,0) -> 55.841008 | D89: =VLOOKUP($A89,'Реестр объектов'!$A:$I,7,0) -> 37.443541 | E89: Admin | F89: МФР 26 | J89: =VLOOKUP($A89,'Реестр объектов'!$A:$I,8,0) -> https://docs.google.com/spreadsheets/d/1rbCD10ySi4YZEkJW2_Slmn9z7AI1WEsGsZaIJmnnT18/edit?gid=402405412#gid=402405412 | K89: =VLOOKUP($A89,'Реестр объектов'!$A:$I,9,0) -> https://disk.yandex.ru/client/disk/Осмотры%20объектов%20АНО%20СМГ/920.%20Новопоселковая%20вл.%206
A90: 11113 | B90: Комплекс производственных объектов. Котельная | C90: 55.884267 | D90: 37.626924 | E90: Наволокин Андрей Александрович | F90: СПЕЦ. СКУД
A91: 11114 | B91: Комплекс производственных объектов. Проектируемое здание охраны (проходная) | C91: 55.884267 | D91: 37.626924 | E91: Наволокин Андрей Александрович | F91: СПЕЦ. СКУД
A92: 11116 | B92: Производственно-складское здание | C92: 55.834790 | D92: 37.512703 | E92: Поляков Сергей Алексеевич | F92: СПЕЦ. СКУД | G92: 45975.404 | H92: 45975.416 | I92: 19 мин
A93: 11117 | B93: Офисно-деловой центр. Строение 1 | C93: 55.893223 | D93: 37.522522 | E93: Наволокин Андрей Александрович | F93: СПЕЦ. СКУД | G93: 45975.456 | H93: 45975.518 | I93: 90 мин
A94: 11118 | B94: Производственно-складское здание, 1 этап | C94: 55.885292 | D94: 37.553433 | E94: Наволокин Андрей Александрович | F94: СПЕЦ. СКУД | L94: Поляков Сергей Алексеевич
A95: 11119 | B95: Многофункциональное здание | C95: 55.749972 | D95: 37.515111 | E95: Терехин Александр Андреевич | F95: СПЕЦ. СКУД
A96: 11120 | B96: Административно-офисное здание с общественной функцией | C96: 55.483520 | D96: 37.308732 | E96: Осипенко Юрий Владимирович | F96: СПЕЦ. СКУД
A97: 11121 | B97: Многоквартирные жилые дома со встроенными нежилыми помещениями и подземной автостоянкой, Блок 10-F | C97: 55.820420 | D97: 37.420877 | E97: Поляков Сергей Алексеевич | F97: СПЕЦ. СКУД | G97: 45975.45 | H97: 45975.462 | I97: 17 мин
A98: 11123 | B98: Многофункциональная комплексная жилая застройка, квартал 5. Торговый центр | C98: 55.748344 | D98: 37.455772 | E98: Терехин Александр Андреевич | F98: СПЕЦ. СКУД
A99: 11124 | B99: Офисное здание | C99: 55.788805 | D99: 37.666200 | E99: Лашин Александр Николаевич | F99: СПЕЦ. СКУД | L99: Джинджолия Леван Раульевич
A100: 11130 | B100: Творческая мастерская З.К. Церетели "Детская школа искусств" | C100: 55.741404 | D100: 37.627894 | E100: Гытлан Роман Валентинович | F100: СПЕЦ. СКУД | G100: 45975.511
A101: 11131 | B101: Производственное здание | C101: 55.492156 | D101: 37.560484 | E101: Данилов Семен Юрьевич | F101: СПЕЦ. СКУД | L101: Осипенко Юрий Владимирович
A102: 11132 | B102: Жилой комплекс с нежилыми помещениями, подземной автостоянкой и отдельно стоящим дошкольным образовательным учреждением. ДОУ | C102: 55.799593 | D102: 37.776973 | E102: Лашин Александр Николаевич | F102: СПЕЦ. СКУД | G102: 45975.371 | H102: 45975.402 | I102: 45 мин | L102: Джинджолия Леван Раульевич
A103: 11133 | B103: Многофункциональный комплекс апартаментов с подземной парковкой и коммерческими помещениями | C103: 55.723577 | D103: 37.635242 | E103: Гытлан Роман Валентинович | F103: СПЕЦ. СКУД | G103: 45975.482 | H103: 45975.502 | I103: 28 мин
A104: 11134 | B104: Многофункциональный жилой комплекс "Лучи-2". Этап 1. Многоквартирные жилые дома. Корпус № 3 | C104: 55.643642 | D104: 37.380678 | E104: Терехин Александр Андреевич | F104: СПЕЦ. СКУД | L104: Пулатов Алекс Шухратович
A105: 11135 | B105: Многофункциональный жилой комплекс «Лучи-2». Этап 1. Многоквартирные жилые дома. Корпуса № 3,4. Подземный гараж | C105: 55.643642 | D105: 37.380678 | E105: Терехин Александр Андреевич | F105: СПЕЦ. СКУД | L105: Пулатов Алекс Шухратович
A106: 11137 | B106: Многофункциональный административно-деловой центр с автомойкой | C106: 55.612070 | D106: 37.497261 | E106: Данилов Семен Юрьевич | F106: СПЕЦ. СКУД
A107: 11138 | B107: Развертывание RSP-платформы для внедрения технологии виртуализации СИМ-карт и локализация производства | C107: 56.015314 | D107: 37.157231 | E107: Наволокин Андрей Александрович | F107: СПЕЦ. СКУД
A108: 11139 | B108: Производственный комплекс | C108: 55.321461 | D108: 37.164446 | E108: Осипенко Юрий Владимирович | F108: СПЕЦ. СКУД | G108: 45975.482 | H108: 45975.517 | I108: 51 мин
...

Sheet map7 (копия)
A1: № точки | B1: Адрес | C1: Широта | D1: Долгота | E1: инспектор | F1: Список | G1: Время/дата входа | H1: Время/дата выхода | I1: Время на объекте | J1: Ссылка на чек | K1: Ссылка на яндекс | L1: Предыдущий инспектор | M1: Инспектор | N1: Время открытия рабочего дня | O1: Координаты открытия дня | P1: Время закрытия рабочего дня | Q1: Координаты закрытия дня
M2: Наволокин Андрей Александрович | N2: 45974.369 | O2: 55.891891891891895, 37.497629338494576 | P2: 45974.753 | Q2: 55.891891891891895, 37.56189262784932
M3: Поляков Сергей Алексеевич | N3: 45974.369 | O3: 55.8582975715919, 37.56338548850041 | P3: 45974.754 | Q3: 55.97331960752988, 37.43128846985928
M4: Лашин Александр Николаевич | N4: 45974.374 | O4: 55.8065928, 37.7505764 | P4: 45974.753 | Q4: 55.8762665, 37.6928165
M5: Джинджолия Леван Раульевич | N5: 45974.364 | O5: 55.729640671929225, 37.859889534424795 | P5: 45974.752 | Q5: 55.75591697791024, 37.81832386127772
M6: Гытлан Роман Валентинович | N6: 45974.359 | O6: 55.6343384, 37.6832811 | P6: 45974.743 | Q6: 55.6758392, 37.7484568
M7: Удалкин Иван Вячеславович | N7: 45974.369 | O7: 55.7088312, 37.7532142 | P7: 45974.752 | Q7: 55.61714181018449, 37.66326114535332
M8: Осипенко Юрий Владимирович | N8: 45974.37 | O8: 55.6627117, 37.5984287 | P8: 45974.752 | Q8: 55.680911033036686, 37.58400882928834
M9: Данилов Семен Юрьевич | N9: 45974.38 | O9: 55.6564175, 37.5908138 | P9: 45974.749 | Q9: 55.6481499, 37.5780129
M10: Терехин Александр Андреевич | N10: 45974.38 | O10: 55.6294717, 37.336493 | P10: 45974.764 | Q10: 55.6740797, 37.4610087
M11: Пулатов Алекс Шухратович | N11: 45974.403 | O11: 55.7907901, 37.5476043 | P11: 45974.758 | Q11: 55.6359029, 37.3045624
M12: Макаров Илья Алексеевич
M13: Куликов Илья Александрович
M14: Шурпаев Нажмутдин Гаджиатаевич | N14: 45973.372 | O14: 55.7004796, 37.8739557 | P14: 45973.751 | Q14: 55.7095883, 37.8667496
M15: Старостин Кирилл Владимирович
M16: Дрозд Александр Викторович | N16: 45974.36 | O16: 55.7206082, 37.7823076 | P16: 45974.75 | Q16: 55.699569, 37.7860144
M17: Иванов Иван Иванович
A18: 1178 | B18: Общеобразовательная школа №1 на 850 мест Волоколамское шоссе уч. 71/14 (город Москва, вн. тер.г. муниципальный округ Покровское-Стрешнево, улица Николая Озерова, земельный участок 8) | C18: 55.81402855891889 | D18: 37.428749835997806 | E18: Поляков Сергей Алексеевич | F18: МЭР | G18: 45974.427 | H18: 45974.494 | I18: 97 мин | J18: https://docs.google.com/spreadsheets/d/1EI7qusa674eJhuaw-nWWtWMEHVSYMQv7HLsInEZTWpE/edit?gid=623093467#gid=623093467 | K18: https://disk.yandex.ru/client/disk/Осмотры%20объектов%20АНО%20СМГ/1178%20Волоколамское%20шоссе%2C%20вл.%2071%2014%20Школа%20на%20850%20мест | L18: Куликов Илья Александрович
A19: 1338 | B19: Осмотр итогов строительства средней общеобразовательной школы на 1000 мест, корп. 8 ЗАО, ул. Озерная, вл. 42-44 | C19: 55.669999907394924 | D19: 37.43651406872443 | E19: Терехин Александр Андреевич | F19: МЭР | G19: 45973.385 | H19: 45973.472 | I19: 126 мин | J19: https://docs.google.com/spreadsheets/d/1EI7qusa674eJhuaw-nWWtWMEHVSYMQv7HLsInEZTWpE/edit?gid=1412429298#gid=1412429298 | K19: https://disk.yandex.ru/d/q3xDbj1lGRqG7w
A20: 542 | B20: 11-я Парковая улица, земельный участок 55/1 (вл. 55) (зона 72.2 (к. 38)) район Северное Измайлово, 11-я Парковая ул., земельный участок 55/1 (11-я Парковая ул., вл. 55) (зона 72.2 (к.38)) | C20: 55.808673 | D20: 37.802970 | E20: Лашин Александр Николаевич | F20: ОВА26 | G20: 45973.381 | H20: 45973.433 | I20: 75 мин | J20: https://docs.google.com/spreadsheets/d/1H1MjbG2y0oC0hhID4do1G0_gfyI1jag72lQd7nL3WDQ/edit?gid=1320846516#gid=1320846516 | K20: https://disk.yandex.ru/client/disk/Осмотры%20объектов%20АНО%20СМГ/542.%20Северное%20Измайлово%2C%2011-я%20Парковая%20ул.%2055 | L20: Лашин Александр Николаевич
A21: 603 | B21: Жилой дом с подземной автостоянкой, инженерными сетями и благоустройством территории (со сносом жилых зданий по адресам: ул. Бутлерова, д. 34, корп.1; ул. Бутлерова, д. 34, корп.2; ул. Бутлерова, д. 36, корп.1; ул. Бутлерова, д. 36, корп.2), район Коньково, микрорайон 6 района Коньково, зона № 1.2 район Коньково, микрорайон 6 района Коньково, зона № 1.2 (4 корпуса) | C21: 55.643709 | D21: 37.545808 | E21: Терехин Александр Андреевич | F21: ОВА26 | G21: 45973.582 | H21: 45973.657 | I21: 107 мин | J21: https://docs.google.com/spreadsheets/d/1H1MjbG2y0oC0hhID4do1G0_gfyI1jag72lQd7nL3WDQ/edit?gid=1000032786#gid=1000032786 | K21: https://disk.yandex.ru/client/disk/Осмотры%20объектов%20АНО%20СМГ/603.%20район%20Коньково%2C%20ул.%20Бутлерово%20зу%2034_2%20мкр.%206%20зона%201.2 | L21: Удалкин Иван Вячеславович
A22: 631 | B22: Ярославская ул., з/у 2/1 район Алексеевский, Ярославская ул., з/у 2/1 | C22: 55.813806 | D22: 37.647062 | E22: Поляков Сергей Алексеевич | F22: ОВА26 | G22: 45973.427 | H22: 45973.493 | I22: 95 мин | J22: https://docs.google.com/spreadsheets/d/1H1MjbG2y0oC0hhID4do1G0_gfyI1jag72lQd7nL3WDQ/edit?gid=1988948543#gid=1988948543 | K22: https://disk.yandex.ru/client/disk/Осмотры%20объектов%20АНО%20СМГ/631.%20Ярославская%20ул.%2C%20зу%202-1
A23: 650 | B23: Большая Черёмушкинская, з/у 26 ЮЗАО, район Академический, Большая Черемушкинская улица, земельный участок 26 (рефинансирование) | C23: 55.680673 | D23: 37.584110 | E23: Осипенко Юрий Владимирович | F23: ОВА26 | G23: 45974.492 | H23: 45974.751 | I23: 373 мин | J23: https://docs.google.com/spreadsheets/d/1rbCD10ySi4YZEkJW2_Slmn9z7AI1WEsGsZaIJmnnT18/edit?gid=1401788865#gid=1401788865 | K23: https://disk.yandex.ru/client/disk/%D0%9E%D1%81%D0%BC%D0%BE%D1%82%D1%80%D1%8B%20%D0%BE%D0%B1%D1%8A%D0%B5%D0%BA%D1%82%D0%BE%D0%B2%20%D0%90%D0%9D%D0%9E%20%D0%A1%D0%9C%D0%93/650.%20%D0%91%D0%BE%D0%BB%D1%8C%D1%88%D0%B0%D1%8F%20%D0%A7%D0%B5%D1%80%D1%91%D0%BC%D1%83%D1%88%D0%BA%D0%B8%D0%BD%D1%81%D0%BA%D0%B0%D1%8F%20%D0%B7!%D1%83%2026%20(%D1%80%D0%B5%D1%84%D0%B8%D0%BD%D0%B0%D0%BD%D1%81%D0%B8%D1%80%D0%BE%D0%B2%D0%B0%D0%BD%D0%B8%D0%B5) | L23: Дрозд Александр Викторович
A24: 962 | B24: ул. Годовикова, з/у 7 (Годовикова ул., вл.7) район Останкинский, Годовикова ул., вл. 7 | C24: 55.805922 | D24: 37.630109 | E24: Поляков Сергей Алексеевич | F24: ОВА26 | G24: 45973.373 | H24: 45973.42 | I24: 68 мин | J24: https://docs.google.com/spreadsheets/d/1rbCD10ySi4YZEkJW2_Slmn9z7AI1WEsGsZaIJmnnT18/edit?gid=1538306210#gid=1538306210 | K24: https://disk.yandex.ru/client/disk/Осмотры%20объектов%20АНО%20СМГ/962.%20ул.%20Годовикова%2C%20з.у.%207
A25: 1065 | B25: Технологическая часть ТПУ на станции метро "Рассказовка" ("Новопеределкино"). Этап 2.1 Станция метро "Рассказовка" | C25: 55.6329806404929 | D25: 37.3362958431244 | E25: Терехин Александр Андреевич | F25: ТПУ | G25: 45974.387 | H25: 45974.499 | I25: 161 мин | L25: Пулатов Алекс Шухратович
A26: 1134 | B26: Технологическая часть ТПУ на станции метро "Нижегородская". Этап 2 г. Москва , м . "Нижегородская" | C26: 55.73157328033123 | D26: 37.7306499021285 | E26: Шурпаев Нажмутдин Гаджиатаевич | F26: ТПУ | G26: 45973.474 | H26: 45973.515 | I26: 58 мин | L26: Гытлан Роман Валентинович
A27: 1121 | B27: Технологическая часть ТПУ на станции метро "Лианозово". Этап 1 "Устройство УДС улицы Псковская, Дубнинская и Лианозовского проезда, ОРП для электробусов на Дмитровском шоссе. Уширение плоскостной перехватывающей парковки." г. Москва, м. "Лианозово" | C27: 55.896590400864746 | D27: 37.5536087103118 | E27: Наволокин Андрей Александрович | F27: ТПУ | G27: 45973.546 | H27: 45973.638 | I27: 132 мин
A28: 1130 | B28: Технологическая часть ТПУ на станции метро "Лефортово". Этапы 1 г.Москва, м. "Лефортово" | C28: 55.76508268252738 | D28: 37.706975584338856 | E28: Шурпаев Нажмутдин Гаджиатаевич | F28: ТПУ | G28: 45973.587 | H28: 45973.643 | I28: 81 мин | L28: Лашин Александр Николаевич
A29: 1328 | B29: Технологическая часть ТПУ на станции метро "Ховрино" ("ул. Дыбенко"). Этап 4.1 "Технологическая часть транспортно-пересадочноо узла на станции метро "Ховрино" ("Улица Дыбенко"). Развитие транспортной и пешеходной инфраструктуры. Благоустройство Станция метро "Ховрино" | C29: 55.87969632155726 | D29: 37.48327681880147 | E29: Наволокин Андрей Александрович | F29: ТПУ | G29: 45973.367 | H29: 45973.436 | I29: 100 мин
A30: 1020 | B30: Теплоснабжение жилого комплекса с подземной автостоянкой, ул. 4-я Парковая, влд. 16 ВАО г. Москвы, район Измайлово, 4-я Парковая ул.,вл.16 | C30: 55.7948 | D30: 37.7882 | E30: Джинджолия Леван Раульевич | F30: ГС | G30: 45973.548 | H30: 45973.55 | I30: 3 мин | J30: https://docs.google.com/spreadsheets/d/19THEBTE9q0fhN2eApZr6BgenIvLGh0AckaYxHQfHk5w/edit?gid=901281284#gid=901281284 | K30: https://disk.yandex.ru/client/disk/%D0%9E%D1%81%D0%BC%D0%BE%D1%82%D1%80%D1%8B%20%D0%BE%D0%B1%D1%8A%D0%B5%D0%BA%D1%82%D0%BE%D0%B2%20%D0%90%D0%9D%D0%9E%20%D0%A1%D0%9C%D0%93/1020.%20%D1%83%D0%BB.%204-%D1%8F%20%D0%9F%D0%B0%D1%80%D0%BA%D0%BE%D0%B2%D0%B0%D1%8F%2C%20%D0%B2%D0%BB%D0%B4.%2016%20(%D0%A2%D0%B5%D0%BF%D0%BB%D0%BE%D1%81%D0%BD%D0%B0%D0%B1%D0%B6%D0%B5%D0%BD%D0%B8%D0%B5%20%D0%B6%D0%B8%D0%BB%D0%BE%D0%B3%D0%BE%20%D0%BA%D0%BE%D0%BC%D0%BF%D0%BB%D0%B5%D0%BA%D1%81%D0%B0%20%D1%81%20%D0%BF%D0%BE%D0%B4%D0%B7%D0%B5%D0%BC%D0%BD%D0%BE%D0%B9%20%D0%B0%D0%B2%D1%82%D0%BE%D1%81%D1%82%D0%BE%D1%8F%D0%BD%D0%BA%D0%BE%D0%B9) | L30: Лашин Александр Николаевич
A31: 115 | B31: Жилой комплекс «Академ Палас», проспект Вернадского, вл. 78 район Тропарево-Никулино, проспект Вернадского, вл. 78 | C31: 55.667261 | D31: 37.482381 | E31: Терехин Александр Андреевич | F31: ГС | G31: 45973.501 | H31: 45973.549 | I31: 69 мин | J31: https://docs.google.com/spreadsheets/d/19THEBTE9q0fhN2eApZr6BgenIvLGh0AckaYxHQfHk5w/edit?gid=809581458#gid=809581458 | K31: https://disk.yandex.ru/client/disk/Осмотры%20объектов%20АНО%20СМГ/115.%20Жилой%20комплекс%20«Академ%20Палас»%20проспект%20Вернадского%2C%20вл.78
A32: 188 | B32: Жилой дом с подземной автостоянкой(проектно-изыскательские и строительно-монтажные работы по сносу и строительству) район Бутырский, ул. Милашенкова, вл.6 | C32: 55.82384253354808 | D32: 37.58752899867056 | E32: Поляков Сергей Алексеевич | F32: ГС | G32: 45973.515 | H32: 45973.582 | I32: 97 мин | J32: https://docs.google.com/spreadsheets/d/19THEBTE9q0fhN2eApZr6BgenIvLGh0AckaYxHQfHk5w/edit?gid=1559792467#gid=1559792467 | K32: https://disk.yandex.ru/client/disk/Осмотры%20объектов%20АНО%20СМГ/188.%20СВАО%2C%20район%2C%20Бутырский%2C%20ул.%20Милашенкова%2C%20влд.6%09 | L32: Поляков Сергей Алексеевич
A33: 555 | B33: =VLOOKUP($A33,'Реестр объектов'!$A:$I,5,0) -> Севастопольский просп., з/у 46/7 (Севастопольский просп., вблизи д. 46, корп. 7) район Черемушки, Севастопольский пр-кт, вблизи д. 46, к. 7, квартал 32, 33-34, зона № 8.2 | C33: =VLOOKUP($A33,'Реестр объектов'!$A:$I,6,0) -> 55.656958 | D33: =VLOOKUP($A33,'Реестр объектов'!$A:$I,7,0) -> 37.565047 | E33: Осипенко Юрий Владимирович | F33: МФР ШТАБ | G33: 45973.548 | H33: 45973.625 | I33: 111 мин | J33: =VLOOKUP($A33,'Реестр объектов'!$A:$I,8,0) -> https://docs.google.com/spreadsheets/d/1H1MjbG2y0oC0hhID4do1G0_gfyI1jag72lQd7nL3WDQ/edit?gid=1298340576#gid=1298340576 | K33: =VLOOKUP($A33,'Реестр объектов'!$A:$I,9,0) -> https://disk.yandex.ru/client/disk/Осмотры%20объектов%20АНО%20СМГ/555.%20Район%20Черемушки%2C%20Севастопольский%20вблизи%20д46%20к7%2C%20кв%2032%2C33%20зона%208.2
A34: 710 | B34: =VLOOKUP($A34,'Реестр объектов'!$A:$I,5,0) -> Сиреневый бульвар, з/у 4/9, зона 6,1 Сиреневый бульвар, з/у 4/9, зона 6,1 | C34: =VLOOKUP($A34,'Реестр объектов'!$A:$I,6,0) -> 55.796229 | D34: =VLOOKUP($A34,'Реестр объектов'!$A:$I,7,0) -> 37.759937 | E34: Дрозд Александр Викторович | F34: МФР ШТАБ | G34: 45973.706 | H34: 45973.751 | I34: 65 мин | J34: =VLOOKUP($A34,'Реестр объектов'!$A:$I,8,0) -> https://docs.google.com/spreadsheets/d/1H1MjbG2y0oC0hhID4do1G0_gfyI1jag72lQd7nL3WDQ/edit?gid=84528393#gid=84528393 | K34: =VLOOKUP($A34,'Реестр объектов'!$A:$I,9,0) -> https://disk.yandex.ru/client/disk/Осмотры%20объектов%20АНО%20СМГ/710%20Сиреневый%20бульвар%2C%20зу%204%209%2C%20зона%206.1
A35: 532 | B35: =VLOOKUP($A35,'Реестр объектов'!$A:$I,5,0) -> Михайлова ул., з/у 15 (Михайлова ул., вл. 15, корп. 1 и 2) Михайлова ул., з/у 15 (Михайлова ул., вл. 15, корп. 1 и 2) | C35: =VLOOKUP($A35,'Реестр объектов'!$A:$I,6,0) -> 55.728195 | D35: =VLOOKUP($A35,'Реестр объектов'!$A:$I,7,0) -> 37.765938 | E35: Гытлан Роман Валентинович | F35: МФР ШТАБ | G35: 45973.352 | H35: 45973.435 | I35: 120 мин | J35: =VLOOKUP($A35,'Реестр объектов'!$A:$I,8,0) -> https://docs.google.com/spreadsheets/d/1H1MjbG2y0oC0hhID4do1G0_gfyI1jag72lQd7nL3WDQ/edit?gid=1217417878#gid=1217417878 | K35: =VLOOKUP($A35,'Реестр объектов'!$A:$I,9,0) -> https://disk.yandex.ru/client/disk/Осмотры%20объектов%20АНО%20СМГ/532%20район%20Рязанский%2C%20Михайлова%20ул.%2C%20зу%2015
A36: 616 | B36: =VLOOKUP($A36,'Реестр объектов'!$A:$I,5,0) -> Сиреневый б-р, з/у 4/9, зона 6,2 Сиреневый б-р, з/у 4/9, зона 6,2 | C36: =VLOOKUP($A36,'Реестр объектов'!$A:$I,6,0) -> 55.796435 | D36: =VLOOKUP($A36,'Реестр объектов'!$A:$I,7,0) -> 37.761761 | E36: Дрозд Александр Викторович | F36: МФР ШТАБ | G36: 45973.636 | H36: 45973.705 | I36: 100 мин | J36: =VLOOKUP($A36,'Реестр объектов'!$A:$I,8,0) -> https://docs.google.com/spreadsheets/d/1H1MjbG2y0oC0hhID4do1G0_gfyI1jag72lQd7nL3WDQ/edit?gid=632665949#gid=632665949 | K36: =VLOOKUP($A36,'Реестр объектов'!$A:$I,9,0) -> https://disk.yandex.ru/client/disk/Осмотры%20объектов%20АНО%20СМГ/616.%20Измайлово%2C%20Сиреневый%20бульв%20ар%2C%20зу%204.9%2C%20зона%206.2
A37: 566 | B37: =VLOOKUP($A37,'Реестр объектов'!$A:$I,5,0) -> Волгоградский пр-т, вл. 101, корп. 2 район Кузьминки, Волгоградский пр-т, вл. 101, корп. 2 | C37: =VLOOKUP($A37,'Реестр объектов'!$A:$I,6,0) -> 55.708765 | D37: =VLOOKUP($A37,'Реестр объектов'!$A:$I,7,0) -> 37.754512 | E37: Удалкин Иван Вячеславович | F37: МФР ШТАБ | G37: 45974.369 | H37: 45974.467 | I37: 141 мин | J37: =VLOOKUP($A37,'Реестр объектов'!$A:$I,8,0) -> https://docs.google.com/spreadsheets/d/1H1MjbG2y0oC0hhID4do1G0_gfyI1jag72lQd7nL3WDQ/edit?gid=947386880#gid=947386880 | K37: =VLOOKUP($A37,'Реестр объектов'!$A:$I,9,0) -> https://disk.yandex.ru/client/disk/Осмотры%20объектов%20АНО%20СМГ/566.%20район%20Кузьминки%2C%20Волгоградский%20пр-т%2C%20вл.%20101%2C%20корп.%202
A38: 447 | B38: =VLOOKUP($A38,'Реестр объектов'!$A:$I,5,0) -> Камова ул., вл. 24 район Косино-Ухтомский, Камова ул., вл. 24 | C38: =VLOOKUP($A38,'Реестр объектов'!$A:$I,6,0) -> 55.699665 | D38: =VLOOKUP($A38,'Реестр объектов'!$A:$I,7,0) -> 37.875188 | E38: Шурпаев Нажмутдин Гаджиатаевич | F38: МФР ШТАБ | G38: 45973.374 | H38: 45973.447 | I38: 105 мин | J38: =VLOOKUP($A38,'Реестр объектов'!$A:$I,8,0) -> https://docs.google.com/spreadsheets/d/1H1MjbG2y0oC0hhID4do1G0_gfyI1jag72lQd7nL3WDQ/edit?gid=747557076#gid=747557076 | K38: =VLOOKUP($A38,'Реестр объектов'!$A:$I,9,0) -> https://disk.yandex.ru/client/disk/Осмотры%20объектов%20АНО%20СМГ/447.%20район%20Косино-Ухтомский%2C%20ул.%20Камова%2C%20влд.%2024
A39: 588 | B39: =VLOOKUP($A39,'Реестр объектов'!$A:$I,5,0) -> Молодогвардейская ул., з/у 53 (вл. 51, вл. 53) район Кунцево, Молодогвардейская ул., з/у 53 | C39: =VLOOKUP($A39,'Реестр объектов'!$A:$I,6,0) -> 55.733307 | D39: =VLOOKUP($A39,'Реестр объектов'!$A:$I,7,0) -> 37.406168 | E39: Пулатов Алекс Шухратович | F39: МФР ШТАБ | G39: 45973.389 | H39: 45973.466 | I39: 112 мин | J39: =VLOOKUP($A39,'Реестр объектов'!$A:$I,8,0) -> https://docs.google.com/spreadsheets/d/1H1MjbG2y0oC0hhID4do1G0_gfyI1jag72lQd7nL3WDQ/edit?gid=788221100#gid=788221100 | K39: =VLOOKUP($A39,'Реестр объектов'!$A:$I,9,0) -> https://disk.yandex.ru/client/disk/Осмотры%20объектов%20АНО%20СМГ/588.%20жилой%20дом%20ул.%20Молодогвардейская%2053
A40: 556 | B40: =VLOOKUP($A40,'Реестр объектов'!$A:$I,5,0) -> Грайвороново, кв. 90А, корп. 12 район Текстильщики, кв-л Грайвороново 90А, з/у 1 (Грайвороново, квартал 90А) | C40: =VLOOKUP($A40,'Реестр объектов'!$A:$I,6,0) -> 55.721583 | D40: =VLOOKUP($A40,'Реестр объектов'!$A:$I,7,0) -> 37.738602 | E40: Гытлан Роман Валентинович | F40: МФР ШТАБ | G40: 45973.447 | H40: 45973.53 | I40: 119 мин | J40: =VLOOKUP($A40,'Реестр объектов'!$A:$I,8,0) -> https://docs.google.com/spreadsheets/d/1H1MjbG2y0oC0hhID4do1G0_gfyI1jag72lQd7nL3WDQ/edit?gid=1984564802#gid=1984564802 | K40: =VLOOKUP($A40,'Реестр объектов'!$A:$I,9,0) -> https://disk.yandex.ru/client/disk/Осмотры%20объектов%20АНО%20СМГ/556.%20Грайвороново%20кв.%2090.%20корп.%2012
A41: 453 | B41: =VLOOKUP($A41,'Реестр объектов'!$A:$I,5,0) -> 2-й квартал Капотня, з/у 21 район Капотня, Капотня, 2-й кв., з/у 21 | C41: =VLOOKUP($A41,'Реестр объектов'!$A:$I,6,0) -> 55.638790 | D41: =VLOOKUP($A41,'Реестр объектов'!$A:$I,7,0) -> 37.801064 | E41: Данилов Семен Юрьевич | F41: МФР ШТАБ | G41: 45973.743 | H41: 45973.743 | I41: 1 мин | J41: =VLOOKUP($A41,'Реестр объектов'!$A:$I,8,0) -> https://docs.google.com/spreadsheets/d/1H1MjbG2y0oC0hhID4do1G0_gfyI1jag72lQd7nL3WDQ/edit?gid=1879792750#gid=1879792750 | K41: =VLOOKUP($A41,'Реестр объектов'!$A:$I,9,0) -> https://disk.yandex.ru/client/disk/Осмотры%20объектов%20АНО%20СМГ/453.%20Капотня%20р-н%2C%20Капотня%2C%202-й%20кв.%2C%20зу%2021 | L41: Удалкин Иван Вячеславович
A42: 536 | B42: =VLOOKUP($A42,'Реестр объектов'!$A:$I,5,0) -> пр-д Нансена, з/у 8 (пр-д Нансена, вл.8) район Свиблово, проезд Нансена, з/у 8 | C42: =VLOOKUP($A42,'Реестр объектов'!$A:$I,6,0) -> 55.850828 | D42: =VLOOKUP($A42,'Реестр объектов'!$A:$I,7,0) -> 37.652804 | E42: Лашин Александр Николаевич | F42: МФР ШТАБ | G42: 45974.47 | H42: 45974.519 | I42: 69 мин | J42: =VLOOKUP($A42,'Реестр объектов'!$A:$I,8,0) -> https://docs.google.com/spreadsheets/d/1H1MjbG2y0oC0hhID4do1G0_gfyI1jag72lQd7nL3WDQ/edit?gid=1956651299#gid=1956651299 | K42: =VLOOKUP($A42,'Реестр объектов'!$A:$I,9,0) -> https://disk.yandex.ru/client/disk/%D0%9E%D1%81%D0%BC%D0%BE%D1%82%D1%80%D1%8B%20%D0%BE%D0%B1%D1%8A%D0%B5%D0%BA%D1%82%D0%BE%D0%B2%20%D0%90%D0%9D%D0%9E%20%D0%A1%D0%9C%D0%93/536.%20%D0%BF%D1%80%D0%BE%D0%B5%D0%B7%D0%B4%20%D0%9D%D0%B0%D0%BD%D1%81%D0%B5%D0%BD%D0%B0%2C%20%D0%B2%D0%BB%D0%B4.%208
A43: 568 | B43: =VLOOKUP($A43,'Реестр объектов'!$A:$I,5,0) -> Карельский бул-р, з/у 14/16 район Дмитровский, Карельский бульвар, з/у 14/16, К.6 (зона 12.1) (со сносом жилых зданий по адресам: Карельский бульвар, д. 14/6; Карельский бульвар, д. 18) | C43: =VLOOKUP($A43,'Реестр объектов'!$A:$I,6,0) -> 55.894674 | D43: =VLOOKUP($A43,'Реестр объектов'!$A:$I,7,0) -> 37.537043 | E43: Наволокин Андрей Александрович | F43: МФР ШТАБ | G43: 45974.583 | H43: 45974.662 | I43: 114 мин | J43: =VLOOKUP($A43,'Реестр объектов'!$A:$I,8,0) -> https://docs.google.com/spreadsheets/d/1H1MjbG2y0oC0hhID4do1G0_gfyI1jag72lQd7nL3WDQ/edit?gid=33336285#gid=33336285 | K43: =VLOOKUP($A43,'Реестр объектов'!$A:$I,9,0) -> https://disk.yandex.ru/client/disk/%D0%9E%D1%81%D0%BC%D0%BE%D1%82%D1%80%D1%8B%20%D0%BE%D0%B1%D1%8A%D0%B5%D0%BA%D1%82%D0%BE%D0%B2%20%D0%90%D0%9D%D0%9E%20%D0%A1%D0%9C%D0%93/568.%20%D0%9A%D0%B0%D1%80%D0%B5%D0%BB%D1%8C%D1%81%D0%BA%D0%B8%D0%B9%20%D0%B1%D1%83%D0%BB%D1%8C%D0%B2%D0%B0%D1%80%2C%20%D0%B7%D1%83%2014-16
A44: 551 | B44: =VLOOKUP($A44,'Реестр объектов'!$A:$I,5,0) -> ул. Лобненская, з/у 9А (Лобненская ул., вл. 9А) район Дмитровский, ул. Лобненская, з/у 9А, к. 23 микрорайон 15, 16, 17, 18 зона № 14.1 | C44: =VLOOKUP($A44,'Реестр объектов'!$A:$I,6,0) -> 55.887585 | D44: =VLOOKUP($A44,'Реестр объектов'!$A:$I,7,0) -> 37.538869 | E44: Наволокин Андрей Александрович | F44: МФР ШТАБ | G44: 45974.675 | H44: 45974.753 | I44: 112 мин | J44: =VLOOKUP($A44,'Реестр объектов'!$A:$I,8,0) -> https://docs.google.com/spreadsheets/d/1H1MjbG2y0oC0hhID4do1G0_gfyI1jag72lQd7nL3WDQ/edit?gid=1791563527#gid=1791563527 | K44: =VLOOKUP($A44,'Реестр объектов'!$A:$I,9,0) -> https://disk.yandex.ru/client/disk/Осмотры%20объектов%20АНО%20СМГ/551.%20Дмитровский%2C%20Лобненская%20ул.%2C%20з.у%209А%2C%20К.23%20мкр.%2015%2C%2016%2C%2017%2C%2018%2C%20зона%20№%20%2014.1
A45: 591 | B45: =VLOOKUP($A45,'Реестр объектов'!$A:$I,5,0) -> ул. Долгопрудная, з/у 3/5 (зона 13.1) район Дмитровский, ул. Долгопрудная, з/у 3/5, микрорайон 15,16,17,18; Дмитровское шосс, к. 10, (зона 13.1) (со сносом жилых зданий по адресам: ул. Долгопрудная, д. 5; ул. Долгопрудная, д. 3; Дмитровское шоссе, д. 141, к. 1) | C45: =VLOOKUP($A45,'Реестр объектов'!$A:$I,6,0) -> 55.893395 | D45: =VLOOKUP($A45,'Реестр объектов'!$A:$I,7,0) -> 37.540047 | E45: Наволокин Андрей Александрович | F45: МФР ШТАБ | G45: 45974.37 | H45: 45974.46 | I45: 131 мин | J45: =VLOOKUP($A45,'Реестр объектов'!$A:$I,8,0) -> https://docs.google.com/spreadsheets/d/1H1MjbG2y0oC0hhID4do1G0_gfyI1jag72lQd7nL3WDQ/edit?gid=683523839#gid=683523839 | K45: =VLOOKUP($A45,'Реестр объектов'!$A:$I,9,0) -> https://disk.yandex.ru/client/disk/%D0%9E%D1%81%D0%BC%D0%BE%D1%82%D1%80%D1%8B%20%D0%BE%D0%B1%D1%8A%D0%B5%D0%BA%D1%82%D0%BE%D0%B2%20%D0%90%D0%9D%D0%9E%20%D0%A1%D0%9C%D0%93/591.%20%D0%94%D0%BE%D0%BB%D0%B3%D0%BE%D0%BF%D1%80%D1%83%D0%B4%D0%BD%D0%B0%D1%8F%20%D1%83%D0%BB.%2C%20%D0%B7%D1%83%203-5
A46: 584 | B46: =VLOOKUP($A46,'Реестр объектов'!$A:$I,5,0) -> Изумрудная зу 44/1 (мкр 2, зона 12.4) район Лосиноостровский, ул. Изумрудная, з/у 44/1, микрорайон 2, зона 12.4 (со сносом жилого здания по адресу: ул. Изумрудная, д. 44) | C46: =VLOOKUP($A46,'Реестр объектов'!$A:$I,6,0) -> 55.877273 | D46: =VLOOKUP($A46,'Реестр объектов'!$A:$I,7,0) -> 37.692177 | E46: Лашин Александр Николаевич | F46: МФР ШТАБ | G46: 45974.673 | H46: 45974.753 | I46: 116 мин | J46: =VLOOKUP($A46,'Реестр объектов'!$A:$I,8,0) -> https://docs.google.com/spreadsheets/d/1H1MjbG2y0oC0hhID4do1G0_gfyI1jag72lQd7nL3WDQ/edit?gid=1900542966#gid=1900542966 | K46: =VLOOKUP($A46,'Реестр объектов'!$A:$I,9,0) -> https://disk.yandex.ru/client/disk/Осмотры%20объектов%20АНО%20СМГ/584.%20ул.%20Изумрудная%2044.1
A47: 632 | B47: =VLOOKUP($A47,'Реестр объектов'!$A:$I,5,0) -> Строительный проезд, земельный участок 9/13 (Строительный проезд, вл.9) Строительный проезд, земельный участок 9/13 (Строительный проезд, вл.9) | C47: =VLOOKUP($A47,'Реестр объектов'!$A:$I,6,0) -> 55.833154 | D47: =VLOOKUP($A47,'Реестр объектов'!$A:$I,7,0) -> 37.423872 | E47: Терехин Александр Андреевич | F47: МФР ШТАБ | G47: 45974.593 | H47: 45974.674 | I47: 117 мин | J47: =VLOOKUP($A47,'Реестр объектов'!$A:$I,8,0) -> https://docs.google.com/spreadsheets/d/1H1MjbG2y0oC0hhID4do1G0_gfyI1jag72lQd7nL3WDQ/edit?gid=1181793870#gid=1181793870 | K47: =VLOOKUP($A47,'Реестр объектов'!$A:$I,9,0) -> https://disk.yandex.ru/client/disk/Осмотры%20объектов%20АНО%20СМГ/632%20Строительный%20проезд%209%5C13 | L47: Поляков Сергей Алексеевич
A48: 604 | B48: =VLOOKUP($A48,'Реестр объектов'!$A:$I,5,0) -> улица Совхозная, земельный участок 55/2 (участок 21.1) улица Совхозная, земельный участок 55/2 (участок 21.1) | C48: =VLOOKUP($A48,'Реестр объектов'!$A:$I,6,0) -> 55.681186 | D48: =VLOOKUP($A48,'Реестр объектов'!$A:$I,7,0) -> 37.762729 | E48: Данилов Семен Юрьевич | F48: МФР ШТАБ | G48: 45973.455 | H48: 45973.566 | I48: 160 мин | J48: =VLOOKUP($A48,'Реестр объектов'!$A:$I,8,0) -> https://docs.google.com/spreadsheets/d/1H1MjbG2y0oC0hhID4do1G0_gfyI1jag72lQd7nL3WDQ/edit?gid=1407301391#gid=1407301391 | K48: =VLOOKUP($A48,'Реестр объектов'!$A:$I,9,0) -> https://disk.yandex.ru/client/disk/Осмотры%20объектов%20АНО%20СМГ/604.%20Совхозная%20ул.%2C%20зу%2055-2%20(участок%2021.1) | L48: Удалкин Иван Вячеславович
A49: 629 | B49: =VLOOKUP($A49,'Реестр объектов'!$A:$I,5,0) -> улица Юных Ленинцев, земельный участок 44/3 (зоны 2.5 и 2.7) улица Юных Ленинцев, земельный участок 44/3 (зоны 2.5 и 2.7) | C49: =VLOOKUP($A49,'Реестр объектов'!$A:$I,6,0) -> 55.699296 | D49: =VLOOKUP($A49,'Реестр объектов'!$A:$I,7,0) -> 37.759386 | E49: Удалкин Иван Вячеславович | F49: МФР ШТАБ | G49: 45973.538 | H49: 45973.608 | I49: 101 мин | J49: =VLOOKUP($A49,'Реестр объектов'!$A:$I,8,0) -> https://docs.google.com/spreadsheets/d/1H1MjbG2y0oC0hhID4do1G0_gfyI1jag72lQd7nL3WDQ/edit?gid=139795987#gid=139795987 | K49: =VLOOKUP($A49,'Реестр объектов'!$A:$I,9,0) -> https://disk.yandex.ru/client/disk/Осмотры%20объектов%20АНО%20СМГ/629.%20район%20Кузьминки%2C%20ул.%20Юных%20Ленинцев%2C%20зу%2044.3%2C%20мкр.%20113%2C113а%2C%20зона%20№2.5%20(со%20сносом%20жилых%20домов%20по%20адресам%3A%20ул.%20Юных%20Ленинцев%2C%20д.%2044%2C%20корп.3%2C%20ул.%20Юных%20Ленинцев%2C%20д.%2044%2C%20корп.2%20)
A50: 543 | B50: =VLOOKUP($A50,'Реестр объектов'!$A:$I,5,0) -> 11-я Парковая улица, земельный участок 53 (вл. 53) (зона 72.3 (к. 39)) 11-я Парковая улица, земельный участок 53 (вл. 53) (зона 72.3 (к. 39)) | C50: =VLOOKUP($A50,'Реестр объектов'!$A:$I,6,0) -> 55.808251 | D50: =VLOOKUP($A50,'Реестр объектов'!$A:$I,7,0) -> 37.804211 | E50: Джинджолия Леван Раульевич | F50: МФР ШТАБ | G50: 45973.598 | H50: 45973.677 | I50: 115 мин | J50: =VLOOKUP($A50,'Реестр объектов'!$A:$I,8,0) -> https://docs.google.com/spreadsheets/d/1H1MjbG2y0oC0hhID4do1G0_gfyI1jag72lQd7nL3WDQ/edit?gid=432585965#gid=432585965 | K50: =VLOOKUP($A50,'Реестр объектов'!$A:$I,9,0) -> https://disk.yandex.ru/client/disk/Осмотры%20объектов%20АНО%20СМГ/543.%2011я%20Парковая%20зу%2053%20%2C%20зона%20№72.3%20Фонд%20реновации
A51: 613 | B51: =VLOOKUP($A51,'Реестр объектов'!$A:$I,5,0) -> Жилой дом с подземным одноуровневым гаражом с инженерными сетями и благоустройством территории (со сносом жилых зданий по адресам: ул. Одесская, д 27/14, ул. Малая Юшуньская, д.12, корп. 1, ул. Малая Юшуньская, д.10, корп. 1) по адресу: г. Москва, район Зюзино, улица Малая Юшуньская, земельный участок 12/1 (участок 7.5) улица Малая Юшуньская, земельный участок 12/1 (участок 7.5) | C51: =VLOOKUP($A51,'Реестр объектов'!$A:$I,6,0) -> 55.651939 | D51: =VLOOKUP($A51,'Реестр объектов'!$A:$I,7,0) -> 37.588976 | E51: Данилов Семен Юрьевич | F51: МФР ШТАБ | G51: 45974.38 | H51: 45974.475 | I51: 138 мин | J51: =VLOOKUP($A51,'Реестр объектов'!$A:$I,8,0) -> https://docs.google.com/spreadsheets/d/1H1MjbG2y0oC0hhID4do1G0_gfyI1jag72lQd7nL3WDQ/edit?gid=1835376342#gid=1835376342 | K51: =VLOOKUP($A51,'Реестр объектов'!$A:$I,9,0) -> https://disk.yandex.ru/client/disk/Осмотры%20объектов%20АНО%20СМГ/613.%20Район%20Зюзино%2C%20ул.%20Малая%20Юшуньская%2012_1%20(зона%207.5) | L51: Осипенко Юрий Владимирович
A52: 563 | B52: =VLOOKUP($A52,'Реестр объектов'!$A:$I,5,0) -> улица Маршала Чуйкова, земельный участок 9/5/2 (зоны 4.1, 4.7) улица Маршала Чуйкова, земельный участок 9/5/2 (зоны 4.1, 4.7) | C52: =VLOOKUP($A52,'Реестр объектов'!$A:$I,6,0) -> 55.696299 | D52: =VLOOKUP($A52,'Реестр объектов'!$A:$I,7,0) -> 37.761476 | E52: Удалкин Иван Вячеславович | F52: МФР ШТАБ | G52: 45973.373 | H52: 45973.448 | I52: 108 мин | J52: =VLOOKUP($A52,'Реестр объектов'!$A:$I,8,0) -> https://docs.google.com/spreadsheets/d/1H1MjbG2y0oC0hhID4do1G0_gfyI1jag72lQd7nL3WDQ/edit?gid=640523369#gid=640523369 | K52: =VLOOKUP($A52,'Реестр объектов'!$A:$I,9,0) -> https://disk.yandex.ru/client/disk/Осмотры%20объектов%20АНО%20СМГ/563.%20район%20Кузьминки%2C%20ул.%20Маршала%20Чуйкова%2C%20зу%209.5.2%2C%20мкр.%20113%2C113а%2C%20зона%20№4.1%2C%204.7%20(со%20сносом%20нежилого%20здания%20по%20адресу%3A%20ул.%20Маршала%20Чуйкова%2C%20д.%209%2C%20корп.5)%209.5.2
A53: 684 | B53: =VLOOKUP($A53,'Реестр объектов'!$A:$I,5,0) -> улица Юных Ленинцев, земельный участок 40/В (зоны 2.4 и 2.7) улица Юных Ленинцев, земельный участок 40/В (зоны 2.4 и 2.7) | C53: =VLOOKUP($A53,'Реестр объектов'!$A:$I,6,0) -> 55.699429 | D53: =VLOOKUP($A53,'Реестр объектов'!$A:$I,7,0) -> 37.757826 | E53: Удалкин Иван Вячеславович | F53: МФР ШТАБ | G53: 45973.47 | H53: 45973.538 | I53: 98 мин | J53: =VLOOKUP($A53,'Реестр объектов'!$A:$I,8,0) -> https://docs.google.com/spreadsheets/d/1H1MjbG2y0oC0hhID4do1G0_gfyI1jag72lQd7nL3WDQ/edit?gid=2107770933#gid=2107770933 | K53: =VLOOKUP($A53,'Реестр объектов'!$A:$I,9,0) -> https://disk.yandex.ru/client/disk/Осмотры%20объектов%20АНО%20СМГ/684.%20район%20Кузьминки%2C%20улица%20Юных%20Ленинцев%2C%20земельный%20участок%2040.3%20(зоны%202.4%20и%202.7)%20(со%20сносом%20жилых%20домов%20по%20адресу%3A%20ул.%20Юных%20Ленинцев%2C%20д.%2040%2C%20корп.%202%2C%20ул.%20Юных%20Ленинцев%2C%20д.%2040%2C%20корп.%203)
A54: 707 | B54: =VLOOKUP($A54,'Реестр объектов'!$A:$I,5,0) -> Жилой дом с инженерными сетями и благоустройством территории (со сносом жилых домов по адресам: ул.Паперника, д.1, ул. Паперника, д.3, ул. Паперника, д.5) по адресу: г. Москва, район Рязанский, 3-я Институтская улица, земельный участок 4/1 (3-я Институтская ул., рядом с д. 4) 3-я Институтская улица, земельный участок 4/1 | C54: =VLOOKUP($A54,'Реестр объектов'!$A:$I,6,0) -> 55.720079 | D54: =VLOOKUP($A54,'Реестр объектов'!$A:$I,7,0) -> 37.783518 | E54: Дрозд Александр Викторович | F54: МФР ШТАБ | G54: 45974.36 | H54: 45974.364 | I54: 6 мин | J54: =VLOOKUP($A54,'Реестр объектов'!$A:$I,8,0) -> https://docs.google.com/spreadsheets/d/1H1MjbG2y0oC0hhID4do1G0_gfyI1jag72lQd7nL3WDQ/edit?gid=864081677#gid=864081677 | K54: =VLOOKUP($A54,'Реестр объектов'!$A:$I,9,0) -> https://disk.yandex.ru/client/disk/Осмотры%20объектов%20АНО%20СМГ/707%20Ул%203-я%20Институтская%20ЗУ%204.1 | L54: Джинджолия Леван Раульевич
A55: 574 | B55: =VLOOKUP($A55,'Реестр объектов'!$A:$I,5,0) -> Амурская ул., земельный участок 1/18 (зоны 3.4, 3.6, 3.7) Амурская ул., емельный участок 1/18 (зоны 3.4, 3.6, 3.7) | C55: =VLOOKUP($A55,'Реестр объектов'!$A:$I,6,0) -> 55.807256 | D55: =VLOOKUP($A55,'Реестр объектов'!$A:$I,7,0) -> 37.751308 | E55: Лашин Александр Николаевич | F55: МФР ШТАБ | G55: 45974.374 | H55: 45974.441 | I55: 96 мин | J55: =VLOOKUP($A55,'Реестр объектов'!$A:$I,8,0) -> https://docs.google.com/spreadsheets/d/1H1MjbG2y0oC0hhID4do1G0_gfyI1jag72lQd7nL3WDQ/edit?gid=1599124365#gid=1599124365 | K55: =VLOOKUP($A55,'Реестр объектов'!$A:$I,9,0) -> https://disk.yandex.ru/client/disk/Осмотры%20объектов%20АНО%20СМГ/574.%20Район%20Гольяново%2C%20Амурская%20ул.%20вл.%201%20зона%20N3.4%20(зу%201_18)
A56: 716 | B56: =VLOOKUP($A56,'Реестр объектов'!$A:$I,5,0) -> Сходненская ул., вл. 42 Сходненская ул., вл. 42 | C56: =VLOOKUP($A56,'Реестр объектов'!$A:$I,6,0) -> 55.844727 | D56: =VLOOKUP($A56,'Реестр объектов'!$A:$I,7,0) -> 37.439962 | E56: Поляков Сергей Алексеевич | F56: МФР ШТАБ | G56: 45974.665 | H56: 45974.754 | I56: 128 мин | J56: =VLOOKUP($A56,'Реестр объектов'!$A:$I,8,0) -> https://docs.google.com/spreadsheets/d/1H1MjbG2y0oC0hhID4do1G0_gfyI1jag72lQd7nL3WDQ/edit?gid=1587877211#gid=1587877211 | K56: =VLOOKUP($A56,'Реестр объектов'!$A:$I,9,0) -> https://disk.yandex.ru/client/disk/Осмотры%20объектов%20АНО%20СМГ/716%20Сходненская%20%20вл%2042
A57: 641 | B57: =VLOOKUP($A57,'Реестр объектов'!$A:$I,5,0) -> Никитинская улица, земельный участок 21/1/3 (Никитинская ул., вл. 21, корп. 1, 3) Никитинская улица, земельный участок 21/1/3 (Никитинская ул., вл. 21, корп. 1, 3) | C57: =VLOOKUP($A57,'Реестр объектов'!$A:$I,6,0) -> 55.801708 | D57: =VLOOKUP($A57,'Реестр объектов'!$A:$I,7,0) -> 37.773139 | E57: Дрозд Александр Викторович | F57: МФР ШТАБ | G57: 45973.46 | H57: 45973.548 | I57: 128 мин | J57: =VLOOKUP($A57,'Реестр объектов'!$A:$I,8,0) -> https://docs.google.com/spreadsheets/d/1H1MjbG2y0oC0hhID4do1G0_gfyI1jag72lQd7nL3WDQ/edit?gid=833062955#gid=833062955 | K57: =VLOOKUP($A57,'Реестр объектов'!$A:$I,9,0) -> https://disk.yandex.ru/client/disk/Осмотры%20объектов%20АНО%20СМГ/641.%20Никитинская%20ул.%2C%20зу%2021.1.3%20%20(рефинансирование)
A58: 607 | B58: =VLOOKUP($A58,'Реестр объектов'!$A:$I,5,0) -> Херсонская ул. 8 (зона 6.5) Херсонская ул. 8 (зона 6.5) | C58: =VLOOKUP($A58,'Реестр объектов'!$A:$I,6,0) -> 55.650516 | D58: =VLOOKUP($A58,'Реестр объектов'!$A:$I,7,0) -> 37.575543 | E58: Осипенко Юрий Владимирович | F58: МФР ШТАБ | G58: 45973.436 | H58: 45973.527 | I58: 132 мин | J58: =VLOOKUP($A58,'Реестр объектов'!$A:$I,8,0) -> https://docs.google.com/spreadsheets/d/1H1MjbG2y0oC0hhID4do1G0_gfyI1jag72lQd7nL3WDQ/edit?gid=471133046#gid=471133046 | K58: =VLOOKUP($A58,'Реестр объектов'!$A:$I,9,0) -> https://disk.yandex.ru/client/disk/%D0%9E%D1%81%D0%BC%D0%BE%D1%82%D1%80%D1%8B%20%D0%BE%D0%B1%D1%8A%D0%B5%D0%BA%D1%82%D0%BE%D0%B2%20%D0%90%D0%9D%D0%9E%20%D0%A1%D0%9C%D0%93/607.%20%D1%80%D0%B0%D0%B9%D0%BE%D0%BD%20%D0%97%D1%8E%D0%B7%D0%B8%D0%BD%D0%BE%20%D1%83%D0%BB.%D0%A5%D0%B5%D1%80%D1%81%D0%BE%D0%BD%D1%81%D0%BA%D0%B0%D1%8F%20%D0%B7%D1%83%208%20%D0%BA%D0%B2%2040%20%D0%B7%D0%BE%D0%BD%D0%B0%206.5_%D1%83%D0%BB.%D0%A5%D0%B5%D1%80%D1%81%D0%BE%D0%BD%D1%81%D0%BA%D0%B0%D1%8F%20%D0%B48
A59: 759 | B59: =VLOOKUP($A59,'Реестр объектов'!$A:$I,5,0) -> ул. Оренбургская, вл. 30 район Косино-Ухтомский, ул. Оренбургская, вл. 30 | C59: =VLOOKUP($A59,'Реестр объектов'!$A:$I,6,0) -> 55.711431 | D59: =VLOOKUP($A59,'Реестр объектов'!$A:$I,7,0) -> 37.866175 | E59: Шурпаев Нажмутдин Гаджиатаевич | F59: МФР ШТАБ | G59: 45973.668 | H59: 45973.75 | I59: 119 мин | J59: =VLOOKUP($A59,'Реестр объектов'!$A:$I,8,0) -> https://docs.google.com/spreadsheets/d/1H1MjbG2y0oC0hhID4do1G0_gfyI1jag72lQd7nL3WDQ/edit?gid=1180712542#gid=1180712542 | K59: =VLOOKUP($A59,'Реестр объектов'!$A:$I,9,0) -> https://disk.yandex.ru/client/disk/Осмотры%20объектов%20АНО%20СМГ/759%20ВАО%2C%20ул.%20Оренбургская%2C%20вл.%2030
A60: 670 | B60: =VLOOKUP($A60,'Реестр объектов'!$A:$I,5,0) -> ул. Мироновская, земельный участок 32 (Мироновская ул., вл. 32) Соколиная гора, улица Мироновская, земельный участок 32 (Мироновская ул., вл. 32) | C60: =VLOOKUP($A60,'Реестр объектов'!$A:$I,6,0) -> 55.788936 | D60: =VLOOKUP($A60,'Реестр объектов'!$A:$I,7,0) -> 37.734289 | E60: Джинджолия Леван Раульевич | F60: МФР ШТАБ | G60: 45974.462 | H60: 45974.533 | I60: 103 мин | J60: =VLOOKUP($A60,'Реестр объектов'!$A:$I,8,0) -> https://docs.google.com/spreadsheets/d/1H1MjbG2y0oC0hhID4do1G0_gfyI1jag72lQd7nL3WDQ/edit?gid=1252296860#gid=1252296860 | K60: =VLOOKUP($A60,'Реестр объектов'!$A:$I,9,0) -> https://disk.yandex.ru/client/disk/Осмотры%20объектов%20АНО%20СМГ/670.%20Ул%20Мироновская%20зу%2032 | L60: Дрозд Александр Викторович
A61: 844 | B61: =VLOOKUP($A61,'Реестр объектов'!$A:$I,5,0) -> улица Перекопская, земельный участок 4 внутригородское муниципальное образование Зюзино, улица Перекопская, земельный участок 4 | C61: =VLOOKUP($A61,'Реестр объектов'!$A:$I,6,0) -> 55.659190 | D61: =VLOOKUP($A61,'Реестр объектов'!$A:$I,7,0) -> 37.585503 | E61: Данилов Семен Юрьевич | F61: МФР ШТАБ | G61: 45974.482 | H61: 45974.547 | I61: 94 мин | J61: =VLOOKUP($A61,'Реестр объектов'!$A:$I,8,0) -> https://docs.google.com/spreadsheets/d/1rbCD10ySi4YZEkJW2_Slmn9z7AI1WEsGsZaIJmnnT18/edit?gid=932084254#gid=932084254 | K61: =VLOOKUP($A61,'Реестр объектов'!$A:$I,9,0) -> https://disk.yandex.ru/client/disk/Осмотры%20объектов%20АНО%20СМГ/844.%20Перекопская%20улица%2C%20зу%204 | L61: Осипенко Юрий Владимирович
A62: 589 | B62: =VLOOKUP($A62,'Реестр объектов'!$A:$I,5,0) -> Всеволода Вишневского ул., земельный участок 11 район Тимирязевский, Всеволода Вишневского ул., вл. 11 | C62: =VLOOKUP($A62,'Реестр объектов'!$A:$I,6,0) -> 55.811372 | D62: =VLOOKUP($A62,'Реестр объектов'!$A:$I,7,0) -> 37.569402 | E62: Поляков Сергей Алексеевич | F62: МФР ШТАБ | G62: 45973.611 | H62: 45973.665 | I62: 79 мин | J62: =VLOOKUP($A62,'Реестр объектов'!$A:$I,8,0) -> https://docs.google.com/spreadsheets/d/1rbCD10ySi4YZEkJW2_Slmn9z7AI1WEsGsZaIJmnnT18/edit?gid=2092914415#gid=2092914415 | K62: =VLOOKUP($A62,'Реестр объектов'!$A:$I,9,0) -> https://disk.yandex.ru/client/disk/Осмотры%20объектов%20АНО%20СМГ/589.%20Всеволода%20Вишневского%20ул.%2C%20вл.%2011
A63: 612 | B63: =VLOOKUP($A63,'Реестр объектов'!$A:$I,5,0) -> Сиреневый бульвар, земельный участок 4/4 зона 5.1 район Измайлово, Сиреневый бульвар, вл. 4, участок 4 зона 5.1 | C63: =VLOOKUP($A63,'Реестр объектов'!$A:$I,6,0) -> 55.796007 | D63: =VLOOKUP($A63,'Реестр объектов'!$A:$I,7,0) -> 37.758178 | E63: Дрозд Александр Викторович | F63: МФР ШТАБ | G63: 45973.751 | H63: 45973.794 | I63: 62 мин | J63: =VLOOKUP($A63,'Реестр объектов'!$A:$I,8,0) -> https://docs.google.com/spreadsheets/d/1rbCD10ySi4YZEkJW2_Slmn9z7AI1WEsGsZaIJmnnT18/edit?gid=1553204611#gid=1553204611 | K63: =VLOOKUP($A63,'Реестр объектов'!$A:$I,9,0) -> https://disk.yandex.ru/client/disk/Осмотры%20объектов%20АНО%20СМГ/612.%20Измайлово%2C%20Сиреневый%20бульвар%2C%20зу%204.4%2C%20зона%205.1 | L63: Поляков Сергей Алексеевич
A64: 693 | B64: =VLOOKUP($A64,'Реестр объектов'!$A:$I,5,0) -> 7-я Парковая улица, земельный участок 19 ВАО, район Измайлово, 7-я Парковая ул., зу 19 | C64: =VLOOKUP($A64,'Реестр объектов'!$A:$I,6,0) -> 55.800022 | D64: =VLOOKUP($A64,'Реестр объектов'!$A:$I,7,0) -> 37.792436 | E64: Джинджолия Леван Раульевич | F64: МФР ШТАБ | G64: 45973.426 | H64: 45973.461 | I64: 50 мин | J64: =VLOOKUP($A64,'Реестр объектов'!$A:$I,8,0) -> https://docs.google.com/spreadsheets/d/1rbCD10ySi4YZEkJW2_Slmn9z7AI1WEsGsZaIJmnnT18/edit?gid=511980375#gid=511980375 | K64: =VLOOKUP($A64,'Реестр объектов'!$A:$I,9,0) -> https://disk.yandex.ru/client/disk/Осмотры%20объектов%20АНО%20СМГ/693%207-я%20Парковая%20зу%2019
A65: 683 | B65: =VLOOKUP($A65,'Реестр объектов'!$A:$I,5,0) -> 3-я Прядильная улица, земельный участок 10 ВАО, район Измайлово, 3-я Прядильная ул., зу 10 (рефинансирование) | C65: =VLOOKUP($A65,'Реестр объектов'!$A:$I,6,0) -> 55.797856 | D65: =VLOOKUP($A65,'Реестр объектов'!$A:$I,7,0) -> 37.773705 | E65: Дрозд Александр Викторович | F65: МФР ШТАБ | G65: 45973.594 | H65: 45973.626 | I65: 45 мин | J65: =VLOOKUP($A65,'Реестр объектов'!$A:$I,8,0) -> https://docs.google.com/spreadsheets/d/1rbCD10ySi4YZEkJW2_Slmn9z7AI1WEsGsZaIJmnnT18/edit?gid=152190080#gid=152190080 | K65: =VLOOKUP($A65,'Реестр объектов'!$A:$I,9,0) -> https://disk.yandex.ru/client/disk/Осмотры%20объектов%20АНО%20СМГ/683%203-я%20Прядильная%20ул.%2C%20зу%2010
A66: 845 | B66: =VLOOKUP($A66,'Реестр объектов'!$A:$I,5,0) -> Кусковская ул., вл. 21 район Новогиреево, Кусковская ул., вл. 21 | C66: =VLOOKUP($A66,'Реестр объектов'!$A:$I,6,0) -> 55.739422 | D66: =VLOOKUP($A66,'Реестр объектов'!$A:$I,7,0) -> 37.778923 | E66: Гытлан Роман Валентинович | F66: МФР ШТАБ | G66: 45973.705 | H66: 45973.72 | I66: 21 мин | J66: =VLOOKUP($A66,'Реестр объектов'!$A:$I,8,0) -> https://docs.google.com/spreadsheets/d/1rbCD10ySi4YZEkJW2_Slmn9z7AI1WEsGsZaIJmnnT18/edit?gid=1340012708#gid=1340012708 | K66: =VLOOKUP($A66,'Реестр объектов'!$A:$I,9,0) -> https://disk.yandex.ru/client/disk/Осмотры%20объектов%20АНО%20СМГ/845%20ВАО%20ул.%20Кусковская%20вл.%2021
A67: 846 | B67: =VLOOKUP($A67,'Реестр объектов'!$A:$I,5,0) -> Кусковская ул., вл. 23 район Новогиреево, Кусковская ул., вл. 23 | C67: =VLOOKUP($A67,'Реестр объектов'!$A:$I,6,0) -> 55.739990 | D67: =VLOOKUP($A67,'Реестр объектов'!$A:$I,7,0) -> 37.780264 | E67: Гытлан Роман Валентинович | F67: МФР ШТАБ | G67: 45973.72 | H67: 45973.739 | I67: 28 мин | J67: =VLOOKUP($A67,'Реестр объектов'!$A:$I,8,0) -> https://docs.google.com/spreadsheets/d/1rbCD10ySi4YZEkJW2_Slmn9z7AI1WEsGsZaIJmnnT18/edit?gid=771281495#gid=771281495 | K67: =VLOOKUP($A67,'Реестр объектов'!$A:$I,9,0) -> https://disk.yandex.ru/client/disk/Осмотры%20объектов%20АНО%20СМГ/846%20ВАО%09%20Кусковская%20ул.%2C%20вл.%2023
A68: 727 | B68: =VLOOKUP($A68,'Реестр объектов'!$A:$I,5,0) -> 3-я Парковая улица, земельный участок 39 (3-я Парковая улица, вл. 39) ВАО, район Измайлово, 3-я Парковая ул., вл.39 | C68: =VLOOKUP($A68,'Реестр объектов'!$A:$I,6,0) -> 55.798756 | D68: =VLOOKUP($A68,'Реестр объектов'!$A:$I,7,0) -> 37.780507 | E68: Дрозд Александр Викторович | F68: МФР ШТАБ | G68: 45973.415 | H68: 45973.441 | I68: 37 мин | J68: =VLOOKUP($A68,'Реестр объектов'!$A:$I,8,0) -> https://docs.google.com/spreadsheets/d/1rbCD10ySi4YZEkJW2_Slmn9z7AI1WEsGsZaIJmnnT18/edit?gid=1493713747#gid=1493713747 | K68: =VLOOKUP($A68,'Реестр объектов'!$A:$I,9,0) -> https://disk.yandex.ru/client/disk/Осмотры%20объектов%20АНО%20СМГ/727%203-я%20Парковая%20ул.%2C%20вл.%2039
A69: 667 | B69: =VLOOKUP($A69,'Реестр объектов'!$A:$I,5,0) -> 16-я Парковая улица, земельный участок 29А (16-я Парковая ул., вл. 29, корп. 1, 2) ВАО, район Восточное Измайлово, 16-я Парковая улица, земельный участок 29А (16-я Парковая ул., вл. 29, корп. 1, 2) (со сносом жилых зданий по адресам: 16-я Парковая, д. 29 корпуса 1, 2) | C69: =VLOOKUP($A69,'Реестр объектов'!$A:$I,6,0) -> 55.802208 | D69: =VLOOKUP($A69,'Реестр объектов'!$A:$I,7,0) -> 37.828432 | E69: Джинджолия Леван Раульевич | F69: МФР ШТАБ | G69: 45973.686 | H69: 45973.723 | I69: 53 мин | J69: =VLOOKUP($A69,'Реестр объектов'!$A:$I,8,0) -> https://docs.google.com/spreadsheets/d/1rbCD10ySi4YZEkJW2_Slmn9z7AI1WEsGsZaIJmnnT18/edit?gid=1285905712#gid=1285905712 | K69: =VLOOKUP($A69,'Реестр объектов'!$A:$I,9,0) -> https://disk.yandex.ru/client/disk/%D0%9E%D1%81%D0%BC%D0%BE%D1%82%D1%80%D1%8B%20%D0%BE%D0%B1%D1%8A%D0%B5%D0%BA%D1%82%D0%BE%D0%B2%20%D0%90%D0%9D%D0%9E%20%D0%A1%D0%9C%D0%93/667%2016-%D1%8F%20%D0%9F%D0%B0%D1%80%D0%BA%D0%BE%D0%B2%D0%B0%D1%8F%20%D0%B7%D1%83%2029%20%D0%90%20%D0%BA1%2C2%20
A70: 874 | B70: =VLOOKUP($A70,'Реестр объектов'!$A:$I,5,0) -> 5-я Парковая улица, земельный участок 39/3 (5-я Парковая ул., вл. 39, корп. 3 район Измайлово, 5-я Парковая ул., вл. 39, корп. 3 | C70: =VLOOKUP($A70,'Реестр объектов'!$A:$I,6,0) -> 55.800869 | D70: =VLOOKUP($A70,'Реестр объектов'!$A:$I,7,0) -> 37.786025 | E70: Джинджолия Леван Раульевич | F70: МФР ШТАБ | G70: 45973.368 | H70: 45973.389 | I70: 30 мин | J70: =VLOOKUP($A70,'Реестр объектов'!$A:$I,8,0) -> https://docs.google.com/spreadsheets/d/1rbCD10ySi4YZEkJW2_Slmn9z7AI1WEsGsZaIJmnnT18/edit?gid=1439077148#gid=1439077148 | K70: =VLOOKUP($A70,'Реестр объектов'!$A:$I,9,0) -> https://disk.yandex.ru/client/disk/%D0%9E%D1%81%D0%BC%D0%BE%D1%82%D1%80%D1%8B%20%D0%BE%D0%B1%D1%8A%D0%B5%D0%BA%D1%82%D0%BE%D0%B2%20%D0%90%D0%9D%D0%9E%20%D0%A1%D0%9C%D0%93/874%20%D1%83%D0%BB%205-%D1%8F%20%D0%BF%D0%B0%D1%80%D0%BA%D0%BE%D0%B2%D0%B0%D1%8F%2039.3%20
A71: 875 | B71: =VLOOKUP($A71,'Реестр объектов'!$A:$I,5,0) -> 9-я Парковая улица, земельный участок 50/2 (9-я Парковая ул., вл. 50, корп. 2) ВАО 9-я Парковая улица, з/у 50/2 (9-я Парковая ул., вл. 50, корп. 2) | C71: =VLOOKUP($A71,'Реестр объектов'!$A:$I,6,0) -> 55.800494 | D71: =VLOOKUP($A71,'Реестр объектов'!$A:$I,7,0) -> 37.800640 | E71: Джинджолия Леван Раульевич | F71: МФР ШТАБ | G71: 45973.493 | H71: 45973.506 | I71: 20 мин | J71: =VLOOKUP($A71,'Реестр объектов'!$A:$I,8,0) -> https://docs.google.com/spreadsheets/d/1rbCD10ySi4YZEkJW2_Slmn9z7AI1WEsGsZaIJmnnT18/edit?gid=1846163124#gid=1846163124 | K71: =VLOOKUP($A71,'Реестр объектов'!$A:$I,9,0) -> https://disk.yandex.ru/client/disk/Осмотры%20объектов%20АНО%20СМГ/875%209-я%20Парковая%20ул.%2C%20вл.%2050%2C%20корп.%202
A72: 876 | B72: =VLOOKUP($A72,'Реестр объектов'!$A:$I,5,0) -> 9-я Парковая улица, земельный участок 52/1 (9-я Парковая ул., вл. 52, корп. 1) ВАО 9-я Парковая улица, з/у 52/1 (9-я Парковая ул., вл. 52, корп. 1) | C72: =VLOOKUP($A72,'Реестр объектов'!$A:$I,6,0) -> 55.801268 | D72: =VLOOKUP($A72,'Реестр объектов'!$A:$I,7,0) -> 37.799688 | E72: Джинджолия Леван Раульевич | F72: МФР ШТАБ | G72: 45973.47 | H72: 45973.492 | I72: 32 мин | J72: =VLOOKUP($A72,'Реестр объектов'!$A:$I,8,0) -> https://docs.google.com/spreadsheets/d/1rbCD10ySi4YZEkJW2_Slmn9z7AI1WEsGsZaIJmnnT18/edit?gid=1451563730#gid=1451563730 | K72: =VLOOKUP($A72,'Реестр объектов'!$A:$I,9,0) -> https://disk.yandex.ru/client/disk/Осмотры%20объектов%20АНО%20СМГ/876%209-я%20Парковая%20ул.%2C%20вл.%2052%2C%20корп.%201
A73: 878 | B73: =VLOOKUP($A73,'Реестр объектов'!$A:$I,5,0) -> улица Азовская, земельный участок 39 ЮЗАО улица Азовская, земельный участок 39 | C73: =VLOOKUP($A73,'Реестр объектов'!$A:$I,6,0) -> 55.644814 | D73: =VLOOKUP($A73,'Реестр объектов'!$A:$I,7,0) -> 37.595841 | E73: Осипенко Юрий Владимирович | F73: МФР ШТАБ | G73: 45973.374 | H73: 45973.413 | I73: 55 мин | J73: =VLOOKUP($A73,'Реестр объектов'!$A:$I,8,0) -> https://docs.google.com/spreadsheets/d/1rbCD10ySi4YZEkJW2_Slmn9z7AI1WEsGsZaIJmnnT18/edit?gid=672785947#gid=672785947 | K73: =VLOOKUP($A73,'Реестр объектов'!$A:$I,9,0) -> https://disk.yandex.ru/client/disk/Осмотры%20объектов%20АНО%20СМГ/878.%20Азовская%20улица%2C%20зу%2039
A74: 806 | B74: =VLOOKUP($A74,'Реестр объектов'!$A:$I,5,0) -> Нижегородская ул., з/у 92А (зона №2.3) ЮВАО Нижегородская ул., з/у 92А (зона № 2.3) | C74: =VLOOKUP($A74,'Реестр объектов'!$A:$I,6,0) -> 55.730676 | D74: =VLOOKUP($A74,'Реестр объектов'!$A:$I,7,0) -> 37.721182 | E74: Шурпаев Нажмутдин Гаджиатаевич | F74: МФР ШТАБ | G74: 45973.518 | H74: 45973.568 | I74: 72 мин | J74: =VLOOKUP($A74,'Реестр объектов'!$A:$I,8,0) -> https://docs.google.com/spreadsheets/d/1rbCD10ySi4YZEkJW2_Slmn9z7AI1WEsGsZaIJmnnT18/edit?gid=1611612481#gid=1611612481 | K74: =VLOOKUP($A74,'Реестр объектов'!$A:$I,9,0) -> https://disk.yandex.ru/client/disk/Осмотры%20объектов%20АНО%20СМГ/806.%20Нижегородская%20ул.%2C%20з-у%2092А%2C%20зона%202.3
A75: 708 | B75: =VLOOKUP($A75,'Реестр объектов'!$A:$I,5,0) -> улица Байкальская, земельный участок 16/11 (зона 10.1) ВАО, район Гольяново, улица Байкальская, земельный участок 16/11 (участки 10.1, 10.2 и 10.3) (со сносом жилых домов по адресам: ул. Байкальская, д. 14, к. 1; д. 16, к. 1; д. 16, к. 2; д. 16, к. 4) | C75: =VLOOKUP($A75,'Реестр объектов'!$A:$I,6,0) -> 55.816341 | D75: =VLOOKUP($A75,'Реестр объектов'!$A:$I,7,0) -> 37.792496 | E75: Дрозд Александр Викторович | F75: МФР ШТАБ | G75: 45974.391 | H75: 45974.454 | I75: 91 мин | J75: =VLOOKUP($A75,'Реестр объектов'!$A:$I,8,0) -> https://docs.google.com/spreadsheets/d/1rbCD10ySi4YZEkJW2_Slmn9z7AI1WEsGsZaIJmnnT18/edit?gid=1294085884#gid=1294085884 | K75: =VLOOKUP($A75,'Реестр объектов'!$A:$I,9,0) -> https://disk.yandex.ru/client/disk/%D0%9E%D1%81%D0%BC%D0%BE%D1%82%D1%80%D1%8B%20%D0%BE%D0%B1%D1%8A%D0%B5%D0%BA%D1%82%D0%BE%D0%B2%20%D0%90%D0%9D%D0%9E%20%D0%A1%D0%9C%D0%93/708%20%D0%93%D0%BE%D0%BB%D1%8C%D1%8F%D0%BD%D0%BE%D0%B2%D0%BE%2C%20%D1%83%D0%BB%20%D0%91%D0%B0%D0%B9%D0%BA%D0%B0%D0%BB%D1%8C%D1%81%D0%BA%D0%B0%D1%8F%20%D0%B7%D1%83%2016.11%20%D1%83%D1%87%D0%B0%D1%81%D1%82%D0%BA%D0%B8%2010.1%2C%2010.2%20%2C%2010.3%20 | L75: Лашин Александр Николаевич
A76: 837 | B76: =VLOOKUP($A76,'Реестр объектов'!$A:$I,5,0) -> улица Жигулевская, земельный участок 3/3/1 ЮВАО улица Жигулёвская, земельный участок 3/3/1 | C76: =VLOOKUP($A76,'Реестр объектов'!$A:$I,6,0) -> 55.712834 | D76: =VLOOKUP($A76,'Реестр объектов'!$A:$I,7,0) -> 37.762931 | E76: Удалкин Иван Вячеславович | F76: МФР ШТАБ | G76: 45973.627 | H76: 45973.75 | I76: 177 мин | J76: =VLOOKUP($A76,'Реестр объектов'!$A:$I,8,0) -> https://docs.google.com/spreadsheets/d/1rbCD10ySi4YZEkJW2_Slmn9z7AI1WEsGsZaIJmnnT18/edit?gid=858056712#gid=858056712 | K76: =VLOOKUP($A76,'Реестр объектов'!$A:$I,9,0) -> https://disk.yandex.ru/client/disk/Осмотры%20объектов%20АНО%20СМГ/837.%20Жигулевская%20ул.%2C%20з-у%203-3-1.%20Жилой%20дом
A77: 850 | B77: =VLOOKUP($A77,'Реестр объектов'!$A:$I,5,0) -> Жилой дом с инженерными сетями и благоустройством территории (со сносом жилого здания по адресу: Сосновая аллея, д.4) по адресу: район Покровское-Стрешнево, мкр. 2 (Северо-Западный административный округ) Сосновая аллея, мкр. 2 | C77: =VLOOKUP($A77,'Реестр объектов'!$A:$I,6,0) -> 55.818731 | D77: =VLOOKUP($A77,'Реестр объектов'!$A:$I,7,0) -> 37.463457 | E77: Поляков Сергей Алексеевич | F77: МФР ШТАБ | G77: 45974.598 | H77: 45974.638 | I77: 58 мин | J77: =VLOOKUP($A77,'Реестр объектов'!$A:$I,8,0) -> https://docs.google.com/spreadsheets/d/1rbCD10ySi4YZEkJW2_Slmn9z7AI1WEsGsZaIJmnnT18/edit?gid=625147630#gid=625147630 | K77: =VLOOKUP($A77,'Реестр объектов'!$A:$I,9,0) -> https://disk.yandex.ru/client/disk/Осмотры%20объектов%20АНО%20СМГ/850.%20Сосновая%20аллея.%2C%20влд.%204
A78: 851 | B78: =VLOOKUP($A78,'Реестр объектов'!$A:$I,5,0) -> улица Верхние Поля, земельный участок 17 (зоны 4.1 и 4.3) улица Верхние Поля, земельный участок 17 (зоны 4.1 и 4.3) | C78: =VLOOKUP($A78,'Реестр объектов'!$A:$I,6,0) -> 55.666430 | D78: =VLOOKUP($A78,'Реестр объектов'!$A:$I,7,0) -> 37.749082 | E78: Данилов Семен Юрьевич | F78: МФР ШТАБ | G78: 45973.585 | H78: 45973.642 | I78: 82 мин | J78: =VLOOKUP($A78,'Реестр объектов'!$A:$I,8,0) -> https://docs.google.com/spreadsheets/d/1rbCD10ySi4YZEkJW2_Slmn9z7AI1WEsGsZaIJmnnT18/edit?gid=632308495#gid=632308495 | K78: =VLOOKUP($A78,'Реестр объектов'!$A:$I,9,0) -> https://disk.yandex.ru/client/disk/Осмотры%20объектов%20АНО%20СМГ/851.%20жилой%20дом%20Верхние%20поля%20зу17 | L78: Удалкин Иван Вячеславович
A79: 852 | B79: =VLOOKUP($A79,'Реестр объектов'!$A:$I,5,0) -> улица Таганрогская, земельный участок 8 улица Таганрогская, земельный участок 8 | C79: =VLOOKUP($A79,'Реестр объектов'!$A:$I,6,0) -> 55.683838 | D79: =VLOOKUP($A79,'Реестр объектов'!$A:$I,7,0) -> 37.755823 | E79: Данилов Семен Юрьевич | F79: МФР ШТАБ | G79: 45973.369 | H79: 45973.421 | I79: 74 мин | J79: =VLOOKUP($A79,'Реестр объектов'!$A:$I,8,0) -> https://docs.google.com/spreadsheets/d/1rbCD10ySi4YZEkJW2_Slmn9z7AI1WEsGsZaIJmnnT18/edit?gid=918222638#gid=918222638 | K79: =VLOOKUP($A79,'Реестр объектов'!$A:$I,9,0) -> https://disk.yandex.ru/client/disk/Осмотры%20объектов%20АНО%20СМГ/852.%20Таганрогская%20ул.%2C%20з!у%208 | L79: Удалкин Иван Вячеславович
A80: 854 | B80: =VLOOKUP($A80,'Реестр объектов'!$A:$I,5,0) -> 2-я Прядильная ул., вл.9 (Приобретение объектов недвижимости) ВАО 2-я Прядильная ул., вл.9 (Приобретение объектов недвижимости) | C80: =VLOOKUP($A80,'Реестр объектов'!$A:$I,6,0) -> 55.796355 | D80: =VLOOKUP($A80,'Реестр объектов'!$A:$I,7,0) -> 37.780896 | E80: Дрозд Александр Викторович | F80: МФР ШТАБ | G80: 45973.376 | H80: 45973.406 | I80: 44 мин | J80: =VLOOKUP($A80,'Реестр объектов'!$A:$I,8,0) -> https://docs.google.com/spreadsheets/d/1rbCD10ySi4YZEkJW2_Slmn9z7AI1WEsGsZaIJmnnT18/edit?gid=1108501275#gid=1108501275 | K80: =VLOOKUP($A80,'Реестр объектов'!$A:$I,9,0) -> https://disk.yandex.ru/client/disk/Осмотры%20объектов%20АНО%20СМГ/854%202-я%20Прядильная%20ул%2C%20зу%209
A81: 863 | B81: =VLOOKUP($A81,'Реестр объектов'!$A:$I,5,0) -> ул. Каховка, земельный участок 14/2 ул. Каховка, земельный участок 14/2 | C81: =VLOOKUP($A81,'Реестр объектов'!$A:$I,6,0) -> 55.655884 | D81: =VLOOKUP($A81,'Реестр объектов'!$A:$I,7,0) -> 37.576879 | E81: Осипенко Юрий Владимирович | F81: МФР ШТАБ | G81: 45973.663 | H81: 45973.751 | I81: 127 мин | J81: =VLOOKUP($A81,'Реестр объектов'!$A:$I,8,0) -> https://docs.google.com/spreadsheets/d/1rbCD10ySi4YZEkJW2_Slmn9z7AI1WEsGsZaIJmnnT18/edit?gid=900983135#gid=900983135 | K81: =VLOOKUP($A81,'Реестр объектов'!$A:$I,9,0) -> https://disk.yandex.ru/client/disk/Осмотры%20объектов%20АНО%20СМГ/863.%20ул.%20Каховка%2C%20земельный%20участок%2014-2 | L81: Осипенко Юрий Владимирович
A82: 1158 | B82: =VLOOKUP($A82,'Реестр объектов'!$A:$I,5,0) -> Волоколамское шоссе, мкр.16, зона №1.2 (2 очередь) район Покровское-Стрешнево, мкр.16, зона №1.2 (2 очередь) зу 108 | C82: =VLOOKUP($A82,'Реестр объектов'!$A:$I,6,0) -> 55.827311 | D82: =VLOOKUP($A82,'Реестр объектов'!$A:$I,7,0) -> 37.427854 | E82: Терехин Александр Андреевич | F82: МФР ШТАБ | G82: 45974.548 | H82: 45974.562 | I82: 20 мин | J82: =VLOOKUP($A82,'Реестр объектов'!$A:$I,8,0) -> https://docs.google.com/spreadsheets/d/1rbCD10ySi4YZEkJW2_Slmn9z7AI1WEsGsZaIJmnnT18/edit?gid=679741287#gid=679741287 | K82: =VLOOKUP($A82,'Реестр объектов'!$A:$I,9,0) -> https://disk.yandex.ru/client/disk/Осмотры%20объектов%20АНО%20СМГ/1158%20Волоколамское%20шоссе%2Cмкр.%2016%20зона%201.2%20(2я%20очередь) | L82: Поляков Сергей Алексеевич
A83: 864 | B83: =VLOOKUP($A83,'Реестр объектов'!$A:$I,5,0) -> ул. Свободы, мкр. 14 ул. Свободы, мкр. 14 | C83: =VLOOKUP($A83,'Реестр объектов'!$A:$I,6,0) -> 55.824283 | D83: =VLOOKUP($A83,'Реестр объектов'!$A:$I,7,0) -> 37.449138 | E83: Поляков Сергей Алексеевич | F83: МФР ШТАБ | G83: 45974.531 | H83: 45974.565 | I83: 49 мин | J83: =VLOOKUP($A83,'Реестр объектов'!$A:$I,8,0) -> https://docs.google.com/spreadsheets/d/1rbCD10ySi4YZEkJW2_Slmn9z7AI1WEsGsZaIJmnnT18/edit?gid=1315766169#gid=1315766169 | K83: =VLOOKUP($A83,'Реестр объектов'!$A:$I,9,0) -> https://disk.yandex.ru/client/disk/Осмотры%20объектов%20АНО%20СМГ/864.%20Москва%2C%20улица%20Свободы%2C%20(мкр%2014)%20д.1%20к.4
A84: 865 | B84: =VLOOKUP($A84,'Реестр объектов'!$A:$I,5,0) -> Путевой проезд, микрорайон 3, зона №1.1 микрорайон 3 района Алтуфьевский, зона №1.1 ЗУ 34/2 | C84: =VLOOKUP($A84,'Реестр объектов'!$A:$I,6,0) -> 55.876438 | D84: =VLOOKUP($A84,'Реестр объектов'!$A:$I,7,0) -> 37.572267 | E84: Наволокин Андрей Александрович | F84: МФР ШТАБ | G84: 45973.677 | H84: 45973.711 | I84: 49 мин | J84: =VLOOKUP($A84,'Реестр объектов'!$A:$I,8,0) -> https://docs.google.com/spreadsheets/d/1rbCD10ySi4YZEkJW2_Slmn9z7AI1WEsGsZaIJmnnT18/edit?gid=667094303#gid=667094303 | K84: =VLOOKUP($A84,'Реестр объектов'!$A:$I,9,0) -> https://disk.yandex.ru/client/disk/Осмотры%20объектов%20АНО%20СМГ/865%20Путевой%20проезд%20микрорайон%203%2C%20(зоны%201.1%2C%201.2%2C%201.3) | L84: Наволокин Андрей Александрович
A85: 867 | B85: =VLOOKUP($A85,'Реестр объектов'!$A:$I,5,0) -> Алтуфьевский район, микрорайон 1-2, зона №24.1 Алтуфьевский район, микрорайон 1-2, зона №24.1 (Инженерная улица, д.10. корп. 2) | C85: =VLOOKUP($A85,'Реестр объектов'!$A:$I,6,0) -> 55.880778 | D85: =VLOOKUP($A85,'Реестр объектов'!$A:$I,7,0) -> 37.581837 | E85: Наволокин Андрей Александрович | F85: МФР ШТАБ | G85: 45973.719 | H85: 45973.757 | I85: 55 мин | J85: =VLOOKUP($A85,'Реестр объектов'!$A:$I,8,0) -> https://docs.google.com/spreadsheets/d/1rbCD10ySi4YZEkJW2_Slmn9z7AI1WEsGsZaIJmnnT18/edit?gid=151666570#gid=151666570 | K85: =VLOOKUP($A85,'Реестр объектов'!$A:$I,9,0) -> https://disk.yandex.ru/client/disk/Осмотры%20объектов%20АНО%20СМГ/867%20Алтуфьевский%20район%20микрорайон%201-2%2C%20зона%20№24.1
A86: 868 | B86: =VLOOKUP($A86,'Реестр объектов'!$A:$I,5,0) -> 3-я Парковая ул., зона 4.2 (к.4) 3-я Парковая ул., зона 4.2 (к.4) ЗУ 46/1 | C86: =VLOOKUP($A86,'Реестр объектов'!$A:$I,6,0) -> 55.805665 | D86: =VLOOKUP($A86,'Реестр объектов'!$A:$I,7,0) -> 37.783050 | E86: Джинджолия Леван Раульевич | F86: МФР ШТАБ | G86: 45973.395 | H86: 45973.418 | I86: 34 мин | J86: =VLOOKUP($A86,'Реестр объектов'!$A:$I,8,0) -> https://docs.google.com/spreadsheets/d/1rbCD10ySi4YZEkJW2_Slmn9z7AI1WEsGsZaIJmnnT18/edit?gid=1853936778#gid=1853936778 | K86: =VLOOKUP($A86,'Реестр объектов'!$A:$I,9,0) -> https://disk.yandex.ru/client/disk/Осмотры%20объектов%20АНО%20СМГ/868%203-я%20Парковая%20зона%204.2
A87: 872 | B87: =VLOOKUP($A87,'Реестр объектов'!$A:$I,5,0) -> улица Перовская, земельный участок 46/48 (Перовская ул., вл. 46/48) улица Перовская, земельный участок 46/48(Перовская ул., вл. 46) | C87: =VLOOKUP($A87,'Реестр объектов'!$A:$I,6,0) -> 55.745179 | D87: =VLOOKUP($A87,'Реестр объектов'!$A:$I,7,0) -> 37.783815 | E87: Гытлан Роман Валентинович | F87: МФР ШТАБ | G87: 45973.693 | H87: 45973.702 | I87: 13 мин | J87: =VLOOKUP($A87,'Реестр объектов'!$A:$I,8,0) -> https://docs.google.com/spreadsheets/d/1rbCD10ySi4YZEkJW2_Slmn9z7AI1WEsGsZaIJmnnT18/edit?gid=590835051#gid=590835051 | K87: =VLOOKUP($A87,'Реестр объектов'!$A:$I,9,0) -> https://disk.yandex.ru/client/disk/Осмотры%20объектов%20АНО%20СМГ/872%20ул.%20Перовская%20зем.%20уч.%2046-48
A88: 948 | B88: =VLOOKUP($A88,'Реестр объектов'!$A:$I,5,0) -> улица Братская, земельный участок 23 (Братская ул., вл. 23) Братская ул., вл. 23 | C88: =VLOOKUP($A88,'Реестр объектов'!$A:$I,6,0) -> 55.749281 | D88: =VLOOKUP($A88,'Реестр объектов'!$A:$I,7,0) -> 37.795311 | E88: Гытлан Роман Валентинович | F88: МФР ШТАБ | G88: 45973.675 | H88: 45973.685 | I88: 14 мин | J88: =VLOOKUP($A88,'Реестр объектов'!$A:$I,8,0) -> https://docs.google.com/spreadsheets/d/1rbCD10ySi4YZEkJW2_Slmn9z7AI1WEsGsZaIJmnnT18/edit?gid=238290316#gid=238290316 | K88: =VLOOKUP($A88,'Реестр объектов'!$A:$I,9,0) -> https://disk.yandex.ru/client/disk/Осмотры%20объектов%20АНО%20СМГ/948%20ул.%20Братская%2C%20вл.23
A89: 657 | B89: =VLOOKUP($A89,'Реестр объектов'!$A:$I,5,0) -> Кольская ул., з/у 7 СВАО, Кольская ул. земельный участок 7 (Кольская вл. 7), район Свиблово | C89: =VLOOKUP($A89,'Реестр объектов'!$A:$I,6,0) -> 55.859232 | D89: =VLOOKUP($A89,'Реестр объектов'!$A:$I,7,0) -> 37.649228 | E89: Лашин Александр Николаевич | F89: МФР ШТАБ | G89: 45974.584 | H89: 45974.638 | I89: 77 мин | J89: =VLOOKUP($A89,'Реестр объектов'!$A:$I,8,0) -> https://docs.google.com/spreadsheets/d/1rbCD10ySi4YZEkJW2_Slmn9z7AI1WEsGsZaIJmnnT18/edit?gid=1068599727#gid=1068599727 | K89: =VLOOKUP($A89,'Реестр объектов'!$A:$I,9,0) -> https://disk.yandex.ru/client/disk/Осмотры%20объектов%20АНО%20СМГ/657%20Кольская%20ул.%2C%20зу%207
A90: 723 | B90: =VLOOKUP($A90,'Реестр объектов'!$A:$I,5,0) -> ул. Кременчугская, вл. 11-17 ЗАО, район Фили-Давыдково, внутригородское муниципальное образование ул. Кременчугская, вл. 11-17 (со сносом нежилого здания по адресу: б-р Славянский, д. 7, корп.2) | C90: =VLOOKUP($A90,'Реестр объектов'!$A:$I,6,0) -> 55.725574 | D90: =VLOOKUP($A90,'Реестр объектов'!$A:$I,7,0) -> 37.471004 | E90: Пулатов Алекс Шухратович | F90: МФР ШТАБ | G90: 45973.487 | H90: 45973.559 | I90: 103 мин | J90: =VLOOKUP($A90,'Реестр объектов'!$A:$I,8,0) -> https://docs.google.com/spreadsheets/d/1rbCD10ySi4YZEkJW2_Slmn9z7AI1WEsGsZaIJmnnT18/edit?gid=1407510683#gid=1407510683 | K90: =VLOOKUP($A90,'Реестр объектов'!$A:$I,9,0) -> https://disk.yandex.ru/client/disk/Осмотры%20объектов%20АНО%20СМГ/723.%20дом%20Ул.%20Кремчугская%2011-17
A91: 685 | B91: =VLOOKUP($A91,'Реестр объектов'!$A:$I,5,0) -> Вагоноремонтная ул., з/у 9/11 (Зона 5.1) САО, район Дмитровский, Вагоноремонтная ул., зу 9/11, мкр. 15, 16, 17, 18 (зона 5.1) (со сносом жилых зданий по адресам: Вагоноремонтная улица, д.11; Вагоноремонтная ул., д.9/25) | C91: =VLOOKUP($A91,'Реестр объектов'!$A:$I,6,0) -> 55.897462 | D91: =VLOOKUP($A91,'Реестр объектов'!$A:$I,7,0) -> 37.534452 | E91: Наволокин Андрей Александрович | F91: МФР ШТАБ | G91: 45973.454 | H91: 45973.512 | I91: 83 мин | J91: =VLOOKUP($A91,'Реестр объектов'!$A:$I,8,0) -> https://docs.google.com/spreadsheets/d/1rbCD10ySi4YZEkJW2_Slmn9z7AI1WEsGsZaIJmnnT18/edit?gid=1084360480#gid=1084360480 | K91: =VLOOKUP($A91,'Реестр объектов'!$A:$I,9,0) -> https://disk.yandex.ru/client/disk/Осмотры%20объектов%20АНО%20СМГ/946.%20ФОК%20ул.%20Истринская%202-8
A92: 663 | B92: =VLOOKUP($A92,'Реестр объектов'!$A:$I,5,0) -> ул. Долгопрудная, з/у 8 р-н Дмитровский мкр. 15, 16, 17, 18. улица Долгопрудная, з/у 8 (Зона 10.4) (со сносом жилых домов по адресу: ул. Долгопрудная, д.8, к.2 и ул. Долгопрудная, д.8, к.1) | C92: =VLOOKUP($A92,'Реестр объектов'!$A:$I,6,0) -> 55.894542 | D92: =VLOOKUP($A92,'Реестр объектов'!$A:$I,7,0) -> 37.539888 | E92: Наволокин Андрей Александрович | F92: МФР ШТАБ | G92: 45974.461 | H92: 45974.537 | I92: 110 мин | J92: =VLOOKUP($A92,'Реестр объектов'!$A:$I,8,0) -> https://docs.google.com/spreadsheets/d/1rbCD10ySi4YZEkJW2_Slmn9z7AI1WEsGsZaIJmnnT18/edit?gid=43981398#gid=43981398 | K92: =VLOOKUP($A92,'Реестр объектов'!$A:$I,9,0) -> https://disk.yandex.ru/client/disk/Осмотры%20объектов%20АНО%20СМГ/663.%20ул.%20Долгопрудная%20з.у.%208
A93: 931 | B93: =VLOOKUP($A93,'Реестр объектов'!$A:$I,5,0) -> ул. Уткина, з/у 44 ул. Уткина, з/у 44 | C93: =VLOOKUP($A93,'Реестр объектов'!$A:$I,6,0) -> 55.761811 | D93: =VLOOKUP($A93,'Реестр объектов'!$A:$I,7,0) -> 37.744226 | E93: Дрозд Александр Викторович | F93: МФР ШТАБ | G93: 45973.347 | H93: 45973.364 | I93: 25 мин | J93: =VLOOKUP($A93,'Реестр объектов'!$A:$I,8,0) -> https://docs.google.com/spreadsheets/d/1rbCD10ySi4YZEkJW2_Slmn9z7AI1WEsGsZaIJmnnT18/edit?gid=1877394014#gid=1877394014 | K93: =VLOOKUP($A93,'Реестр объектов'!$A:$I,9,0) -> https://disk.yandex.ru/client/disk/Осмотры%20объектов%20АНО%20СМГ/931.%20ул.%20Уткина%2C%20з.у%2044
A94: 123 | B94: =VLOOKUP($A94,'Реестр объектов'!$A:$I,5,0) -> Жилой комплекс «Терлецкий парк» Новогиреевская ул., вл.5, корп.1, корп.2 район Новогиреево, Новогиреевская ул., вл. 5, корп. 1, корп. 2 | C94: =VLOOKUP($A94,'Реестр объектов'!$A:$I,6,0) -> 55.761429 | D94: =VLOOKUP($A94,'Реестр объектов'!$A:$I,7,0) -> 37.796085 | E94: Гытлан Роман Валентинович | F94: МСУ-1 | G94: 45974.455 | H94: 45974.509 | I94: 78 мин | J94: =VLOOKUP($A94,'Реестр объектов'!$A:$I,8,0) -> https://docs.google.com/spreadsheets/d/19THEBTE9q0fhN2eApZr6BgenIvLGh0AckaYxHQfHk5w/edit?gid=326698304#gid=326698304 | K94: =VLOOKUP($A94,'Реестр объектов'!$A:$I,9,0) -> https://disk.yandex.ru/client/disk/Осмотры%20объектов%20АНО%20СМГ/123.%20ЖК%20«Терлецкий%20Парк»%20Новогиреевская%20ул.%2C%20вл.5%2C%20корп.1%2C%20корп.2
A95: 181 | B95: =VLOOKUP($A95,'Реестр объектов'!$A:$I,5,0) -> Осмотр хода строительства учебного корпуса на 400 мест (на месте сноса здания школы), ЦАО, район Пресненский, Причальный пр., вл. 7, стр. 1, стр. 1/1 Пресненского района, Причальный проезд, вл. 7, стр. 1, стр. 1/1 | C95: =VLOOKUP($A95,'Реестр объектов'!$A:$I,6,0) -> 55.759260 | D95: =VLOOKUP($A95,'Реестр объектов'!$A:$I,7,0) -> 37.518414 | E95: Пулатов Алекс Шухратович | F95: МСУ-1 | G95: 45973.575 | H95: 45973.625 | I95: 72 мин | J95: =VLOOKUP($A95,'Реестр объектов'!$A:$I,8,0) -> https://docs.google.com/spreadsheets/d/19THEBTE9q0fhN2eApZr6BgenIvLGh0AckaYxHQfHk5w/edit?gid=2057787589#gid=2057787589 | K95: =VLOOKUP($A95,'Реестр объектов'!$A:$I,9,0) -> https://disk.yandex.ru/client/disk/Осмотры%20объектов%20АНО%20СМГ/181.Причальный%20проезд%20школа%20на%20400%20мест
A96: 257 | B96: =VLOOKUP($A96,'Реестр объектов'!$A:$I,5,0) -> Участок проектируемого проезда №894 с инженерными коммуникациями для жилых домов по адресу: ул. Николая Старостина, напротив вл. 8 район Косино-Ухтомский, ул. Николая Старостина, напротив вл. 8 | C96: =VLOOKUP($A96,'Реестр объектов'!$A:$I,6,0) -> 55.730687 | D96: =VLOOKUP($A96,'Реестр объектов'!$A:$I,7,0) -> 37.857446 | E96: Джинджолия Леван Раульевич | F96: МСУ-1 | G96: 45974.364 | H96: 45974.43 | I96: 95 мин | J96: =VLOOKUP($A96,'Реестр объектов'!$A:$I,8,0) -> https://docs.google.com/spreadsheets/d/19THEBTE9q0fhN2eApZr6BgenIvLGh0AckaYxHQfHk5w/edit?gid=1460101979#gid=1460101979 | K96: =VLOOKUP($A96,'Реестр объектов'!$A:$I,9,0) -> https://disk.yandex.ru/client/disk/Осмотры%20объектов%20АНО%20СМГ/257.%20Проезд%20№%20894%20для%20жилых%20зданий%2C%20ул.%20Николая%20Старостина%2C%20напротив%20вл.%208 | L96: Шурпаев Нажмутдин Гаджиатаевич
A97: 344 | B97: =VLOOKUP($A97,'Реестр объектов'!$A:$I,5,0) -> Школа 775 мест, СЗАО, р-н Хорошево-Мневники район Хорошёво-Мнёвники, Шелепихинская набережная, д. 36А, стр.1 | C97: =VLOOKUP($A97,'Реестр объектов'!$A:$I,6,0) -> 55.765579 | D97: =VLOOKUP($A97,'Реестр объектов'!$A:$I,7,0) -> 37.506354 | E97: Пулатов Алекс Шухратович | F97: МСУ-1 | G97: 45973.651 | H97: 45973.668 | I97: 24 мин | J97: =VLOOKUP($A97,'Реестр объектов'!$A:$I,8,0) -> https://docs.google.com/spreadsheets/d/1EI7qusa674eJhuaw-nWWtWMEHVSYMQv7HLsInEZTWpE/edit?gid=376178489#gid=376178489 | K97: =VLOOKUP($A97,'Реестр объектов'!$A:$I,9,0) -> https://disk.yandex.ru/client/disk/Осмотры%20объектов%20АНО%20СМГ/344.%20СОШ%20775%2C%20ул.%20Шеногина%20д.%202%2C%20стр.%202
A98: 1246 | B98: =VLOOKUP($A98,'Реестр объектов'!$A:$I,5,0) -> Здание дошкольной образовательной организации на 350 мест с бассейном (Шелепихинская наб., д. 38А) г. Москва, внутригородское муниципальное образование Хорошёво-Мнёвники, улица Шеногина, земельный участок 2/21 с кадастровым номером 77:08:0012003:2846 | C98: =VLOOKUP($A98,'Реестр объектов'!$A:$I,6,0) -> 55.766754 | D98: =VLOOKUP($A98,'Реестр объектов'!$A:$I,7,0) -> 37.503549 | E98: Пулатов Алекс Шухратович | F98: МСУ-1 | G98: 45973.669 | H98: 45973.688 | I98: 27 мин | J98: =VLOOKUP($A98,'Реестр объектов'!$A:$I,8,0) -> https://docs.google.com/spreadsheets/d/1EI7qusa674eJhuaw-nWWtWMEHVSYMQv7HLsInEZTWpE/edit?gid=1839942165#gid=1839942165 | K98: =VLOOKUP($A98,'Реестр объектов'!$A:$I,9,0) -> https://disk.yandex.ru/client/disk/Осмотры%20объектов%20АНО%20СМГ/1246.%20ДОО%20НА%20350%20мест%2C%20ул.Шеногина%2C%20зу%202-21
A99: 658 | B99: =VLOOKUP($A99,'Реестр объектов'!$A:$I,5,0) -> ул. Полярная, з/у 4 (вл. 4) район Южное Медведково, Полярная ул., вл. 4 | C99: =VLOOKUP($A99,'Реестр объектов'!$A:$I,6,0) -> 55.872678 | D99: =VLOOKUP($A99,'Реестр объектов'!$A:$I,7,0) -> 37.638506 | E99: Лашин Александр Николаевич | F99: МСУ-1 | G99: 45973.555 | H99: 45973.593 | I99: 55 мин | J99: =VLOOKUP($A99,'Реестр объектов'!$A:$I,8,0) -> https://docs.google.com/spreadsheets/d/1H1MjbG2y0oC0hhID4do1G0_gfyI1jag72lQd7nL3WDQ/edit?gid=617262299#gid=617262299 | K99: =VLOOKUP($A99,'Реестр объектов'!$A:$I,9,0) -> https://disk.yandex.ru/client/disk/Осмотры%20объектов%20АНО%20СМГ/658.%20Полярная%20ул.%2C%20зу%204
A100: 794 | B100: =VLOOKUP($A100,'Реестр объектов'!$A:$I,5,0) -> улица Полярная, з/у 17/1 (ул. Полярная, вл. 17, корп. 1) район Южное Медведково, ул. Полярная, вл. 17, корп. 1 | C100: =VLOOKUP($A100,'Реестр объектов'!$A:$I,6,0) -> 55.876455 | D100: =VLOOKUP($A100,'Реестр объектов'!$A:$I,7,0) -> 37.635792 | E100: Лашин Александр Николаевич | F100: МСУ-1 | G100: 45973.471 | H100: 45973.527 | I100: 81 мин | J100: =VLOOKUP($A100,'Реестр объектов'!$A:$I,8,0) -> https://docs.google.com/spreadsheets/d/1H1MjbG2y0oC0hhID4do1G0_gfyI1jag72lQd7nL3WDQ/edit?gid=540934155#gid=540934155 | K100: =VLOOKUP($A100,'Реестр объектов'!$A:$I,9,0) -> https://disk.yandex.ru/client/disk/Осмотры%20объектов%20АНО%20СМГ/794.%20Полярная%20ул.%2C%20зу%20вл.%2017%2C%20корп.%201
...

Sheet Реестр объектов
D1: https://docs.google.com/spreadsheets/d/1h7Zyn53eByFA_Wa7EnuJEIn9QqPaz6kDse3SZgRdd5g/edit?gid'=0#gid'=0 | J1: {=IF(A14:A1975="", "", IFNA( VLOOKUP( A14:A1975, SORT('АРХИВ'!A:H, ROW('АРХИВ'!A:A), FALSE), 8, FALSE ) ,""))} -> #REF! | M1: {=IF($A$14:$A1975="", "", IF(J14:J1975=100, "", IF(K14:K1975="", "", DATEVALUE(LEFT(K14:K1975, 10)) + L14:L1975)))} -> #REF!
C3: Чеки ДСТИ | D3: https://docs.google.com/spreadsheets/d/1MW8OIVEKRJEaLcG-KS0zwZPEQ0eRUWE2y9Gj77rgoxo/edit?gid=796994001#gid=796994001
C4: Чеги ДРНТ | D4: https://docs.google.com/spreadsheets/d/19THEBTE9q0fhN2eApZr6BgenIvLGh0AckaYxHQfHk5w/edit?gid=0#gid=0
C5: Чеки метро | D5: https://docs.google.com/spreadsheets/d/1jonEGMB3UFHiUZpltF1zURon8gYN7jGSHu-k9t5TXnA/edit?gid=0#gid=0
C6: Чеки Рен-25 | D6: https://docs.google.com/spreadsheets/d/1H1MjbG2y0oC0hhID4do1G0_gfyI1jag72lQd7nL3WDQ/edit?gid=0#gid=0
C7: Чеки Рен-26 | D7: https://docs.google.com/spreadsheets/d/1rbCD10ySi4YZEkJW2_Slmn9z7AI1WEsGsZaIJmnnT18/edit?gid=0#gid=0
C8: Чеки Рен-27 | D8: https://docs.google.com/spreadsheets/d/1lEcUd4exxkr5Za3IYZ0vdFNfMubnuMOOMXfmF3GYC9I/edit?gid=0#gid=0
C9: Чеки вне списка | D9: https://docs.google.com/spreadsheets/d/1EI7qusa674eJhuaw-nWWtWMEHVSYMQv7HLsInEZTWpE/edit?gid=0#gid=0
A12: ID | B12: Список | C12: Вид | D12: Внебюджет | E12: Adress | F12: latitude | G12: longitude | H12: chek | I12: yandex | J12: СГ | K12: Последний объезд | L12: Периодичность | M12: Плановая дата | N12: Статус
A13: =IFERROR(__xludf.DUMMYFUNCTION("QUERY(IMPORTRANGE(D1, ""АИП 25-27 / РЕН 25-27 / ВНЕ СПИСКА!A:ZZ""), ""SELECT Col6, Col4, Col5, Col38, Col52,Col55,Col56,Col53, Col54, Col28, Col30 OFFSET 12"", 1)"),"6") -> 6 | B13: =IFERROR(__xludf.DUMMYFUNCTION("""COMPUTED_VALUE"""),"4") -> 4 | C13: =IFERROR(__xludf.DUMMYFUNCTION("""COMPUTED_VALUE"""),"7") -> 7 | D13: =IFERROR(__xludf.DUMMYFUNCTION("""COMPUTED_VALUE"""),"38") -> 38 | E13: =IFERROR(__xludf.DUMMYFUNCTION("""COMPUTED_VALUE"""),"") | F13: =IFERROR(__xludf.DUMMYFUNCTION("""COMPUTED_VALUE"""),"") | G13: =IFERROR(__xludf.DUMMYFUNCTION("""COMPUTED_VALUE"""),"") | H13: =IFERROR(__xludf.DUMMYFUNCTION("""COMPUTED_VALUE"""),"") | I13: =IFERROR(__xludf.DUMMYFUNCTION("""COMPUTED_VALUE"""),"") | J13: =IFERROR(__xludf.DUMMYFUNCTION("""COMPUTED_VALUE"""),"28") -> 28 | K13: =IFERROR(__xludf.DUMMYFUNCTION("""COMPUTED_VALUE"""),"32") -> 32
A14: =IFERROR(__xludf.DUMMYFUNCTION("""COMPUTED_VALUE"""),"006") -> 006 | B14: =IFERROR(__xludf.DUMMYFUNCTION("""COMPUTED_VALUE"""),"АИП-25") -> АИП-25 | C14: =IFERROR(__xludf.DUMMYFUNCTION("""COMPUTED_VALUE"""),"ОКС") -> ОКС | E14: =IFERROR(__xludf.DUMMYFUNCTION("""COMPUTED_VALUE"""),"Осмотр итогов строительства объекта административного здания на территории поселения Внуковское район Внуково, поселение Внуковское, ул. Авиаконструктора Петлякова") -> Осмотр итогов строительства объекта административного здания на территории поселения Внуковское район Внуково, поселение Внуковское, ул. Авиаконструктора Петлякова | F14: =IFERROR(__xludf.DUMMYFUNCTION("""COMPUTED_VALUE"""),"#N/A") -> #N/A | G14: =IFERROR(__xludf.DUMMYFUNCTION("""COMPUTED_VALUE"""),"#N/A") -> #N/A | H14: =IFERROR(__xludf.DUMMYFUNCTION("""COMPUTED_VALUE"""),"https://docs.google.com/spreadsheets/d/19THEBTE9q0fhN2eApZr6BgenIvLGh0AckaYxHQfHk5w/edit?gid=1222968113#gid=1222968113") -> https://docs.google.com/spreadsheets/d/19THEBTE9q0fhN2eApZr6BgenIvLGh0AckaYxHQfHk5w/edit?gid=1222968113#gid=1222968113 | I14: =IFERROR(__xludf.DUMMYFUNCTION("""COMPUTED_VALUE"""),"https://disk.yandex.ru/client/disk/Осмотры%20объектов%20АНО%20СМГ/006.%20Административное%20здание%20на%20тер%20Внуковское%20д%20Лапшинка") -> https://disk.yandex.ru/client/disk/Осмотры%20объектов%20АНО%20СМГ/006.%20Административное%20здание%20на%20тер%20Внуковское%20д%20Лапшинка | J14: =IFERROR(__xludf.DUMMYFUNCTION("""COMPUTED_VALUE"""),100.0) -> 100 | K14: =IFERROR(__xludf.DUMMYFUNCTION("""COMPUTED_VALUE"""),45909.0) -> 45909 | L14: {=IF(A14:A1975="", "", IF(J14:J1975=100, "Завершен", IF(J14:J1975<=50, 30, IF(J14:J1975<=94, 14, 7))))} -> Завершен | M14: {=IF(A14:A1975="", "", IF(J14:J1975=100, "", IF(K14:K1975="", "", DATEVALUE(LEFT(K14:K1975, 10)) + L14:L1975)))} | N14: {=IF(A14:A1975="", "", IF(J14:J1975=100, "✅ Завершен", IF(LEFT(O14:O1975, 2)="РВ", "🔴 Объект введен", IF(K14:K1975="", "🆕 Нет объездов", IF(TODAY() - DATEVALUE(LEFT(K14:K1975, 10)) > L14:L1975, "🔴 ПРОСРОЧЕН", IF(L14:L1975 = 30, IF(TODAY() - DATEVALUE(LEFT(K14:K1975, 10)) > 23, "🔴 СРОЧНО", IF(TODAY() - DATEVALUE(LEFT(K14:K1975, 10)) > 16, "🟠 ВНИМАНИЕ", IF(TODAY() - DATEVALUE(LEFT(K14:K1975, 10)) > 9, "🟡 СКОРО", "🟢 ПО ПЛАНУ"))), IF(L14:L1975 = 14, IF(TODAY() - DATEVALUE(LEFT(K14:K1975, 10)) > 11, "🔴 СРОЧНО", IF(TODAY() - DATEVALUE(LEFT(K14:K1975, 10)) > 7, "🟠 ВНИМАНИЕ", IF(TODAY() - DATEVALUE(LEFT(K14:K1975, 10)) > 4, "🟡 СКОРО", "🟢 ПО ПЛАНУ"))), IF(TODAY() - DATEVALUE(LEFT(K14:K1975, 10)) > 6, "🔴 СРОЧНО", IF(TODAY() - DATEVALUE(LEFT(K14:K1975, 10)) > 4, "🟠 ВНИМАНИЕ", IF(TODAY() - DATEVALUE(LEFT(K14:K1975, 10)) > 2, "🟡 СКОРО", "🟢 ПО ПЛАНУ"))) ))) ))) )} -> ✅ Завершен | O14: РВ от 14.03.2025 № 77-17-012472-2025 По состоянию на 09.09.2025 Произошла смена Заказчика Не передана исполнительная документация по объекту в полном объеме
A15: =IFERROR(__xludf.DUMMYFUNCTION("""COMPUTED_VALUE"""),"160д") -> 160д | B15: =IFERROR(__xludf.DUMMYFUNCTION("""COMPUTED_VALUE"""),"АИП-25") -> АИП-25 | C15: =IFERROR(__xludf.DUMMYFUNCTION("""COMPUTED_VALUE"""),"УДС") -> УДС | E15: =IFERROR(__xludf.DUMMYFUNCTION("""COMPUTED_VALUE"""),"Развитие улично-дорожной сети городского округа Троицк (2 этап). (Строительство магистральной улицы районного значения от ул. Полковника милиции Курочкина до Октябрьского проспекта (Подъездная дорога к школе на 2100 мест в микрорайоне ""В"" г.о. Троицк в "&"городе Москве) Троицк") -> Развитие улично-дорожной сети городского округа Троицк (2 этап). (Строительство магистральной улицы районного значения от ул. Полковника милиции Курочкина до Октябрьского проспекта (Подъездная дорога к школе на 2100 мест в микрорайоне "В" г.о. Троицк в городе Москве) Троицк | F15: =IFERROR(__xludf.DUMMYFUNCTION("""COMPUTED_VALUE"""),"#N/A") -> #N/A | G15: =IFERROR(__xludf.DUMMYFUNCTION("""COMPUTED_VALUE"""),"#N/A") -> #N/A | J15: =IFERROR(__xludf.DUMMYFUNCTION("""COMPUTED_VALUE"""),98.0) -> 98 | K15: =IFERROR(__xludf.DUMMYFUNCTION("""COMPUTED_VALUE"""),45968.0) -> 45968 | L15: 7 | M15: 45975 | N15: 🔴 Объект введен | O15: РВ от 26.03.2025 № 77-19-012479-2025
A16: =IFERROR(__xludf.DUMMYFUNCTION("""COMPUTED_VALUE"""),"384д") -> 384д | B16: =IFERROR(__xludf.DUMMYFUNCTION("""COMPUTED_VALUE"""),"АИП-25") -> АИП-25 | C16: =IFERROR(__xludf.DUMMYFUNCTION("""COMPUTED_VALUE"""),"УДС") -> УДС | E16: =IFERROR(__xludf.DUMMYFUNCTION("""COMPUTED_VALUE"""),"Строительство автомобильной дороги ""Воскресенское - Каракашево - Щербинка"". этап: Этап 5.1 (ОРП) Воскресенское") -> Строительство автомобильной дороги "Воскресенское - Каракашево - Щербинка". этап: Этап 5.1 (ОРП) Воскресенское | F16: =IFERROR(__xludf.DUMMYFUNCTION("""COMPUTED_VALUE"""),"#N/A") -> #N/A | G16: =IFERROR(__xludf.DUMMYFUNCTION("""COMPUTED_VALUE"""),"#N/A") -> #N/A | J16: =IFERROR(__xludf.DUMMYFUNCTION("""COMPUTED_VALUE"""),100.0) -> 100 | K16: =IFERROR(__xludf.DUMMYFUNCTION("""COMPUTED_VALUE"""),45972.0) -> 45972 | L16: Завершен | N16: ✅ Завершен | O16: РВ от 10.03.2025 № 77-17-012467-2025
A17: =IFERROR(__xludf.DUMMYFUNCTION("""COMPUTED_VALUE"""),"012") -> 012 | B17: =IFERROR(__xludf.DUMMYFUNCTION("""COMPUTED_VALUE"""),"АИП-25") -> АИП-25 | C17: =IFERROR(__xludf.DUMMYFUNCTION("""COMPUTED_VALUE"""),"ОКС") -> ОКС | E17: =IFERROR(__xludf.DUMMYFUNCTION("""COMPUTED_VALUE"""),"Реконструкция школы № 2062 на 350 мест со строительством пристройки на 550 мест (2-й этап - реконструкция) ТАО, Новофёдоровское, д. Яковлевское, д. 29") -> Реконструкция школы № 2062 на 350 мест со строительством пристройки на 550 мест (2-й этап - реконструкция) ТАО, Новофёдоровское, д. Яковлевское, д. 29 | F17: =IFERROR(__xludf.DUMMYFUNCTION("""COMPUTED_VALUE"""),"#N/A") -> #N/A | G17: =IFERROR(__xludf.DUMMYFUNCTION("""COMPUTED_VALUE"""),"#N/A") -> #N/A | H17: =IFERROR(__xludf.DUMMYFUNCTION("""COMPUTED_VALUE"""),"https://docs.google.com/spreadsheets/d/19THEBTE9q0fhN2eApZr6BgenIvLGh0AckaYxHQfHk5w/edit?gid=1038633275#gid=1038633275") -> https://docs.google.com/spreadsheets/d/19THEBTE9q0fhN2eApZr6BgenIvLGh0AckaYxHQfHk5w/edit?gid=1038633275#gid=1038633275 | I17: =IFERROR(__xludf.DUMMYFUNCTION("""COMPUTED_VALUE"""),"https://disk.yandex.ru/client/disk/Осмотры%20объектов%20АНО%20СМГ/012.%20новофедоровское%20СОШ%202062") -> https://disk.yandex.ru/client/disk/Осмотры%20объектов%20АНО%20СМГ/012.%20новофедоровское%20СОШ%202062 | J17: =IFERROR(__xludf.DUMMYFUNCTION("""COMPUTED_VALUE"""),100.0) -> 100 | K17: =IFERROR(__xludf.DUMMYFUNCTION("""COMPUTED_VALUE"""),45889.0) -> 45889 | L17: Завершен | N17: ✅ Завершен | O17: РВ от 21.03.2025 №77-21-012476-2025
A18: =IFERROR(__xludf.DUMMYFUNCTION("""COMPUTED_VALUE"""),"120") -> 120 | B18: =IFERROR(__xludf.DUMMYFUNCTION("""COMPUTED_VALUE"""),"АИП-25") -> АИП-25 | C18: =IFERROR(__xludf.DUMMYFUNCTION("""COMPUTED_VALUE"""),"ОКС") -> ОКС | E18: =IFERROR(__xludf.DUMMYFUNCTION("""COMPUTED_VALUE"""),"Учебный корпус на 400 мест (этап 2) ориентир ул. Базовская, д. 15, корп.13 район Западное Дегунино, ул. Базовская, д. 15, корп. 13") -> Учебный корпус на 400 мест (этап 2) ориентир ул. Базовская, д. 15, корп.13 район Западное Дегунино, ул. Базовская, д. 15, корп. 13 | F18: =IFERROR(__xludf.DUMMYFUNCTION("""COMPUTED_VALUE"""),"#N/A") -> #N/A | G18: =IFERROR(__xludf.DUMMYFUNCTION("""COMPUTED_VALUE"""),"#N/A") -> #N/A | H18: =IFERROR(__xludf.DUMMYFUNCTION("""COMPUTED_VALUE"""),"https://docs.google.com/spreadsheets/d/19THEBTE9q0fhN2eApZr6BgenIvLGh0AckaYxHQfHk5w/edit?gid=717172873#gid=717172873") -> https://docs.google.com/spreadsheets/d/19THEBTE9q0fhN2eApZr6BgenIvLGh0AckaYxHQfHk5w/edit?gid=717172873#gid=717172873 | I18: =IFERROR(__xludf.DUMMYFUNCTION("""COMPUTED_VALUE"""),"https://disk.yandex.ru/client/disk/Осмотры%20объектов%20АНО%20СМГ/120.%20Базовская%20д15%20корп%2013") -> https://disk.yandex.ru/client/disk/Осмотры%20объектов%20АНО%20СМГ/120.%20Базовская%20д15%20корп%2013 | J18: =IFERROR(__xludf.DUMMYFUNCTION("""COMPUTED_VALUE"""),99.9685) -> 99.9685 | K18: =IFERROR(__xludf.DUMMYFUNCTION("""COMPUTED_VALUE"""),45889.0) -> 45889 | L18: 7 | M18: 45896 | N18: 🔴 Объект введен | O18: РВ от 03.03.2025 №77-09-012464-2025
A19: =IFERROR(__xludf.DUMMYFUNCTION("""COMPUTED_VALUE"""),"125") -> 125 | B19: =IFERROR(__xludf.DUMMYFUNCTION("""COMPUTED_VALUE"""),"АИП-25") -> АИП-25 | C19: =IFERROR(__xludf.DUMMYFUNCTION("""COMPUTED_VALUE"""),"ОКС") -> ОКС | E19: =IFERROR(__xludf.DUMMYFUNCTION("""COMPUTED_VALUE"""),"Скоропомощный стационарный комплекс на территории ГБУЗ «ГКБ им. В.М. Буянова» ДЗМ ул. Бакинская, д. 26 район Царицино, ул. Бакинская, д. 26 (со сносом объектов по адресам: Бакинская ул., д. 26, стр. 6, стр. 8)") -> Скоропомощный стационарный комплекс на территории ГБУЗ «ГКБ им. В.М. Буянова» ДЗМ ул. Бакинская, д. 26 район Царицино, ул. Бакинская, д. 26 (со сносом объектов по адресам: Бакинская ул., д. 26, стр. 6, стр. 8) | F19: =IFERROR(__xludf.DUMMYFUNCTION("""COMPUTED_VALUE"""),"#N/A") -> #N/A | G19: =IFERROR(__xludf.DUMMYFUNCTION("""COMPUTED_VALUE"""),"#N/A") -> #N/A | H19: =IFERROR(__xludf.DUMMYFUNCTION("""COMPUTED_VALUE"""),"https://docs.google.com/spreadsheets/d/19THEBTE9q0fhN2eApZr6BgenIvLGh0AckaYxHQfHk5w/edit?gid=2058696561#gid=2058696561") -> https://docs.google.com/spreadsheets/d/19THEBTE9q0fhN2eApZr6BgenIvLGh0AckaYxHQfHk5w/edit?gid=2058696561#gid=2058696561 | I19: =IFERROR(__xludf.DUMMYFUNCTION("""COMPUTED_VALUE"""),"https://disk.yandex.ru/client/disk/Осмотры%20объектов%20АНО%20СМГ/125.%20ГКБ%20им.%20В.И.%20Буянова%20ДЗМ%20Царицино%20ЮАО%20г.%20Москва%20Бакинская%20д.%2026%20с.%208") -> https://disk.yandex.ru/client/disk/Осмотры%20объектов%20АНО%20СМГ/125.%20ГКБ%20им.%20В.И.%20Буянова%20ДЗМ%20Царицино%20ЮАО%20г.%20Москва%20Бакинская%20д.%2026%20с.%208 | J19: =IFERROR(__xludf.DUMMYFUNCTION("""COMPUTED_VALUE"""),100.0) -> 100 | K19: =IFERROR(__xludf.DUMMYFUNCTION("""COMPUTED_VALUE"""),45828.0) -> 45828 | L19: Завершен | N19: ✅ Завершен | O19: РВ от 14.04.2025 №77-05-012515-2025
A20: =IFERROR(__xludf.DUMMYFUNCTION("""COMPUTED_VALUE"""),"259") -> 259 | B20: =IFERROR(__xludf.DUMMYFUNCTION("""COMPUTED_VALUE"""),"АИП-25") -> АИП-25 | C20: =IFERROR(__xludf.DUMMYFUNCTION("""COMPUTED_VALUE"""),"ОКС") -> ОКС | E20: =IFERROR(__xludf.DUMMYFUNCTION("""COMPUTED_VALUE"""),"Физкультурно-оздоровительный комплекс, ул. Павла Корчагина, вл. 7 район Алексеевский, ул. Павла Корчагина, вл. 7") -> Физкультурно-оздоровительный комплекс, ул. Павла Корчагина, вл. 7 район Алексеевский, ул. Павла Корчагина, вл. 7 | F20: =IFERROR(__xludf.DUMMYFUNCTION("""COMPUTED_VALUE"""),"#N/A") -> #N/A | G20: =IFERROR(__xludf.DUMMYFUNCTION("""COMPUTED_VALUE"""),"#N/A") -> #N/A | H20: =IFERROR(__xludf.DUMMYFUNCTION("""COMPUTED_VALUE"""),"https://docs.google.com/spreadsheets/d/19THEBTE9q0fhN2eApZr6BgenIvLGh0AckaYxHQfHk5w/edit?gid=600337697#gid=600337697") -> https://docs.google.com/spreadsheets/d/19THEBTE9q0fhN2eApZr6BgenIvLGh0AckaYxHQfHk5w/edit?gid=600337697#gid=600337697 | I20: =IFERROR(__xludf.DUMMYFUNCTION("""COMPUTED_VALUE"""),"https://disk.yandex.ru/client/disk/Осмотры%20объектов%20АНО%20СМГ/259.%20ул%20Павла%20Корчагина%2C%207") -> https://disk.yandex.ru/client/disk/Осмотры%20объектов%20АНО%20СМГ/259.%20ул%20Павла%20Корчагина%2C%207 | J20: =IFERROR(__xludf.DUMMYFUNCTION("""COMPUTED_VALUE"""),100.0) -> 100 | K20: =IFERROR(__xludf.DUMMYFUNCTION("""COMPUTED_VALUE"""),45828.0) -> 45828 | L20: Завершен | N20: ✅ Завершен | O20: РВ от 27.02.2025 № 77-02-012458-2025
A21: =IFERROR(__xludf.DUMMYFUNCTION("""COMPUTED_VALUE"""),"101") -> 101 | B21: =IFERROR(__xludf.DUMMYFUNCTION("""COMPUTED_VALUE"""),"АИП-25") -> АИП-25 | C21: =IFERROR(__xludf.DUMMYFUNCTION("""COMPUTED_VALUE"""),"ОКС") -> ОКС | E21: =IFERROR(__xludf.DUMMYFUNCTION("""COMPUTED_VALUE"""),"Жилой комплекс «Царицыно» подземный паркинг с благоустройством 6-я Радиальная ул., вл. 7 (корп. 5.4) район Бирюлево Восточное, 6-я Радиальная ул, вл. 7 (корп. 5.4)") -> Жилой комплекс «Царицыно» подземный паркинг с благоустройством 6-я Радиальная ул., вл. 7 (корп. 5.4) район Бирюлево Восточное, 6-я Радиальная ул, вл. 7 (корп. 5.4) | F21: =IFERROR(__xludf.DUMMYFUNCTION("""COMPUTED_VALUE"""),"#N/A") -> #N/A | G21: =IFERROR(__xludf.DUMMYFUNCTION("""COMPUTED_VALUE"""),"#N/A") -> #N/A | H21: =IFERROR(__xludf.DUMMYFUNCTION("""COMPUTED_VALUE"""),"https://docs.google.com/spreadsheets/d/19THEBTE9q0fhN2eApZr6BgenIvLGh0AckaYxHQfHk5w/edit?gid=23825357#gid=23825357") -> https://docs.google.com/spreadsheets/d/19THEBTE9q0fhN2eApZr6BgenIvLGh0AckaYxHQfHk5w/edit?gid=23825357#gid=23825357 | I21: =IFERROR(__xludf.DUMMYFUNCTION("""COMPUTED_VALUE"""),"https://disk.yandex.ru/client/disk/Осмотры%20объектов%20АНО%20СМГ/101.%20Подземный%20паркинг.%20ЖК%20%22Царицыно%22.%206-я%20Радиальная%20ул.%2C%20вл.%207%20(корп%205.4)") -> https://disk.yandex.ru/client/disk/Осмотры%20объектов%20АНО%20СМГ/101.%20Подземный%20паркинг.%20ЖК%20%22Царицыно%22.%206-я%20Радиальная%20ул.%2C%20вл.%207%20(корп%205.4) | J21: =IFERROR(__xludf.DUMMYFUNCTION("""COMPUTED_VALUE"""),99.724875) -> 99.724875 | K21: =IFERROR(__xludf.DUMMYFUNCTION("""COMPUTED_VALUE"""),45861.0) -> 45861 | L21: 7 | M21: 45868 | N21: 🔴 Объект введен | O21: РВ от 27.03.2025 № 77-05-012481-2025
A22: =IFERROR(__xludf.DUMMYFUNCTION("""COMPUTED_VALUE"""),"100") -> 100 | B22: =IFERROR(__xludf.DUMMYFUNCTION("""COMPUTED_VALUE"""),"АИП-25") -> АИП-25 | C22: =IFERROR(__xludf.DUMMYFUNCTION("""COMPUTED_VALUE"""),"ОКС") -> ОКС | E22: =IFERROR(__xludf.DUMMYFUNCTION("""COMPUTED_VALUE"""),"Жилой комплекс «Царицыно» подземный паркинг с благоустройством 6-я Радиальная ул., вл. 7 (корп. 5.1) район Бирюлево Восточное, 6-я Радиальная ул, вл. 7 (корп. 5.1)") -> Жилой комплекс «Царицыно» подземный паркинг с благоустройством 6-я Радиальная ул., вл. 7 (корп. 5.1) район Бирюлево Восточное, 6-я Радиальная ул, вл. 7 (корп. 5.1) | F22: =IFERROR(__xludf.DUMMYFUNCTION("""COMPUTED_VALUE"""),"#N/A") -> #N/A | G22: =IFERROR(__xludf.DUMMYFUNCTION("""COMPUTED_VALUE"""),"#N/A") -> #N/A | H22: =IFERROR(__xludf.DUMMYFUNCTION("""COMPUTED_VALUE"""),"https://docs.google.com/spreadsheets/d/19THEBTE9q0fhN2eApZr6BgenIvLGh0AckaYxHQfHk5w/edit?gid=1122822598#gid=1122822598") -> https://docs.google.com/spreadsheets/d/19THEBTE9q0fhN2eApZr6BgenIvLGh0AckaYxHQfHk5w/edit?gid=1122822598#gid=1122822598 | I22: =IFERROR(__xludf.DUMMYFUNCTION("""COMPUTED_VALUE"""),"https://disk.yandex.ru/client/disk/Осмотры%20объектов%20АНО%20СМГ/100.%20Подземный%20паркинг.%20ЖК%20%22Царицыно%22.%206-я%20Радиальная%20ул.%20%2C%20вл.%207%20(корп.%205.1)") -> https://disk.yandex.ru/client/disk/Осмотры%20объектов%20АНО%20СМГ/100.%20Подземный%20паркинг.%20ЖК%20%22Царицыно%22.%206-я%20Радиальная%20ул.%20%2C%20вл.%207%20(корп.%205.1) | J22: =IFERROR(__xludf.DUMMYFUNCTION("""COMPUTED_VALUE"""),99.6405) -> 99.6405 | K22: =IFERROR(__xludf.DUMMYFUNCTION("""COMPUTED_VALUE"""),45861.0) -> 45861 | L22: 7 | M22: 45868 | N22: 🔴 Объект введен | O22: РВ от 28.03.2025 № 77-05-012483-2025
A23: =IFERROR(__xludf.DUMMYFUNCTION("""COMPUTED_VALUE"""),"123") -> 123 | B23: =IFERROR(__xludf.DUMMYFUNCTION("""COMPUTED_VALUE"""),"АИП-25") -> АИП-25 | C23: =IFERROR(__xludf.DUMMYFUNCTION("""COMPUTED_VALUE"""),"ОКС") -> ОКС | E23: =IFERROR(__xludf.DUMMYFUNCTION("""COMPUTED_VALUE"""),"Жилой комплекс «Терлецкий парк» Новогиреевская ул., вл.5, корп.1, корп.2 район Новогиреево, Новогиреевская ул., вл. 5, корп. 1, корп. 2") -> Жилой комплекс «Терлецкий парк» Новогиреевская ул., вл.5, корп.1, корп.2 район Новогиреево, Новогиреевская ул., вл. 5, корп. 1, корп. 2 | F23: =IFERROR(__xludf.DUMMYFUNCTION("""COMPUTED_VALUE"""),"55.761429") -> 55.761429 | G23: =IFERROR(__xludf.DUMMYFUNCTION("""COMPUTED_VALUE"""),"37.796085") -> 37.796085 | H23: =IFERROR(__xludf.DUMMYFUNCTION("""COMPUTED_VALUE"""),"https://docs.google.com/spreadsheets/d/19THEBTE9q0fhN2eApZr6BgenIvLGh0AckaYxHQfHk5w/edit?gid=326698304#gid=326698304") -> https://docs.google.com/spreadsheets/d/19THEBTE9q0fhN2eApZr6BgenIvLGh0AckaYxHQfHk5w/edit?gid=326698304#gid=326698304 | I23: =IFERROR(__xludf.DUMMYFUNCTION("""COMPUTED_VALUE"""),"https://disk.yandex.ru/client/disk/Осмотры%20объектов%20АНО%20СМГ/123.%20ЖК%20«Терлецкий%20Парк»%20Новогиреевская%20ул.%2C%20вл.5%2C%20корп.1%2C%20корп.2") -> https://disk.yandex.ru/client/disk/Осмотры%20объектов%20АНО%20СМГ/123.%20ЖК%20«Терлецкий%20Парк»%20Новогиреевская%20ул.%2C%20вл.5%2C%20корп.1%2C%20корп.2 | J23: =IFERROR(__xludf.DUMMYFUNCTION("""COMPUTED_VALUE"""),99.757125) -> 99.757125 | K23: =IFERROR(__xludf.DUMMYFUNCTION("""COMPUTED_VALUE"""),45901.0) -> 45901 | L23: 7 | M23: 45908 | N23: 🔴 Объект введен | O23: РВ от 10.04.2025 № 77-03-012509-2025
A24: =IFERROR(__xludf.DUMMYFUNCTION("""COMPUTED_VALUE"""),"118") -> 118 | B24: =IFERROR(__xludf.DUMMYFUNCTION("""COMPUTED_VALUE"""),"АИП-25") -> АИП-25 | C24: =IFERROR(__xludf.DUMMYFUNCTION("""COMPUTED_VALUE"""),"ОКС") -> ОКС | E24: =IFERROR(__xludf.DUMMYFUNCTION("""COMPUTED_VALUE"""),"Жилой комплекс «Царицыно» подземный паркинг с благоустройством 6-я Радиальная ул., вл. 7 (корп. 30,31) район Бирюлево Восточное, 6-я Радиальная ул, вл. 7 (корп. 30, 31)") -> Жилой комплекс «Царицыно» подземный паркинг с благоустройством 6-я Радиальная ул., вл. 7 (корп. 30,31) район Бирюлево Восточное, 6-я Радиальная ул, вл. 7 (корп. 30, 31) | F24: =IFERROR(__xludf.DUMMYFUNCTION("""COMPUTED_VALUE"""),"#N/A") -> #N/A | G24: =IFERROR(__xludf.DUMMYFUNCTION("""COMPUTED_VALUE"""),"#N/A") -> #N/A | H24: =IFERROR(__xludf.DUMMYFUNCTION("""COMPUTED_VALUE"""),"https://docs.google.com/spreadsheets/d/19THEBTE9q0fhN2eApZr6BgenIvLGh0AckaYxHQfHk5w/edit?gid=739392640#gid=739392640") -> https://docs.google.com/spreadsheets/d/19THEBTE9q0fhN2eApZr6BgenIvLGh0AckaYxHQfHk5w/edit?gid=739392640#gid=739392640 | I24: =IFERROR(__xludf.DUMMYFUNCTION("""COMPUTED_VALUE"""),"https://disk.yandex.ru/client/disk/Осмотры%20объектов%20АНО%20СМГ/118.%206-я%20Радиальная%20ул.%2C%20вл.%207%20корп.%2030%2C%2031.%20Паркинг") -> https://disk.yandex.ru/client/disk/Осмотры%20объектов%20АНО%20СМГ/118.%206-я%20Радиальная%20ул.%2C%20вл.%207%20корп.%2030%2C%2031.%20Паркинг | J24: =IFERROR(__xludf.DUMMYFUNCTION("""COMPUTED_VALUE"""),99.87412499999999) -> 99.874125 | K24: =IFERROR(__xludf.DUMMYFUNCTION("""COMPUTED_VALUE"""),45861.0) -> 45861 | L24: 7 | M24: 45868 | N24: 🔴 Объект введен | O24: РВ №77-05-012497-2025 от 01.04.2025
A25: =IFERROR(__xludf.DUMMYFUNCTION("""COMPUTED_VALUE"""),"117") -> 117 | B25: =IFERROR(__xludf.DUMMYFUNCTION("""COMPUTED_VALUE"""),"АИП-25") -> АИП-25 | C25: =IFERROR(__xludf.DUMMYFUNCTION("""COMPUTED_VALUE"""),"ОКС") -> ОКС | E25: =IFERROR(__xludf.DUMMYFUNCTION("""COMPUTED_VALUE"""),"Жилой комплекс «Царицыно» подземный паркинг с благоустройством 6-я Радиальная ул., вл. 7 (корп. 27, 28/29) район Бирюлево Восточное, 6-я Радиальная ул, вл. 7 (корп. 27, 28/29)") -> Жилой комплекс «Царицыно» подземный паркинг с благоустройством 6-я Радиальная ул., вл. 7 (корп. 27, 28/29) район Бирюлево Восточное, 6-я Радиальная ул, вл. 7 (корп. 27, 28/29) | F25: =IFERROR(__xludf.DUMMYFUNCTION("""COMPUTED_VALUE"""),"#N/A") -> #N/A | G25: =IFERROR(__xludf.DUMMYFUNCTION("""COMPUTED_VALUE"""),"#N/A") -> #N/A | H25: =IFERROR(__xludf.DUMMYFUNCTION("""COMPUTED_VALUE"""),"https://docs.google.com/spreadsheets/d/19THEBTE9q0fhN2eApZr6BgenIvLGh0AckaYxHQfHk5w/edit?gid=891835937#gid=891835937") -> https://docs.google.com/spreadsheets/d/19THEBTE9q0fhN2eApZr6BgenIvLGh0AckaYxHQfHk5w/edit?gid=891835937#gid=891835937 | I25: =IFERROR(__xludf.DUMMYFUNCTION("""COMPUTED_VALUE"""),"https://disk.yandex.ru/client/disk/Осмотры%20объектов%20АНО%20СМГ/117.%206-я%20Радиальная%20вл.7%20Корп%2027%2C%2028-29.%20Паркинг") -> https://disk.yandex.ru/client/disk/Осмотры%20объектов%20АНО%20СМГ/117.%206-я%20Радиальная%20вл.7%20Корп%2027%2C%2028-29.%20Паркинг | J25: =IFERROR(__xludf.DUMMYFUNCTION("""COMPUTED_VALUE"""),99.86449999999999) -> 99.8645 | K25: =IFERROR(__xludf.DUMMYFUNCTION("""COMPUTED_VALUE"""),45861.0) -> 45861 | L25: 7 | M25: 45868 | N25: 🔴 Объект введен | O25: РВ №77-05-012493-2025 от 31.03.2025
A26: =IFERROR(__xludf.DUMMYFUNCTION("""COMPUTED_VALUE"""),"1034") -> 1034 | B26: =IFERROR(__xludf.DUMMYFUNCTION("""COMPUTED_VALUE"""),"АИП-25") -> АИП-25 | C26: =IFERROR(__xludf.DUMMYFUNCTION("""COMPUTED_VALUE"""),"УДС") -> УДС | E26: =IFERROR(__xludf.DUMMYFUNCTION("""COMPUTED_VALUE"""),"Пересадка на ст. ""Текстильщики"" (с БКЛ на ТКЛ) район Текстильщики, Пересадка на ст. ""Текстильщики"" (с БКЛ на ТКЛ)") -> Пересадка на ст. "Текстильщики" (с БКЛ на ТКЛ) район Текстильщики, Пересадка на ст. "Текстильщики" (с БКЛ на ТКЛ) | F26: =IFERROR(__xludf.DUMMYFUNCTION("""COMPUTED_VALUE"""),"55.708579") -> 55.708579 | G26: =IFERROR(__xludf.DUMMYFUNCTION("""COMPUTED_VALUE"""),"37.728959") -> 37.728959 | H26: =IFERROR(__xludf.DUMMYFUNCTION("""COMPUTED_VALUE"""),"https://docs.google.com/spreadsheets/d/1jonEGMB3UFHiUZpltF1zURon8gYN7jGSHu-k9t5TXnA/edit?gid=808640473#gid=808640473") -> https://docs.google.com/spreadsheets/d/1jonEGMB3UFHiUZpltF1zURon8gYN7jGSHu-k9t5TXnA/edit?gid=808640473#gid=808640473 | I26: =IFERROR(__xludf.DUMMYFUNCTION("""COMPUTED_VALUE"""),"https://disk.yandex.ru/client/disk/Осмотры%20объектов%20АНО%20СМГ/1034.%20Пересадка%20на%20станции%20метро%20Текстильщики%20(с%20БКЛ%20на%20ТКЛ)") -> https://disk.yandex.ru/client/disk/Осмотры%20объектов%20АНО%20СМГ/1034.%20Пересадка%20на%20станции%20метро%20Текстильщики%20(с%20БКЛ%20на%20ТКЛ) | J26: =IFERROR(__xludf.DUMMYFUNCTION("""COMPUTED_VALUE"""),99.9625) -> 99.9625 | K26: =IFERROR(__xludf.DUMMYFUNCTION("""COMPUTED_VALUE"""),45957.0) -> 45957 | L26: 7 | M26: 45964 | N26: 🔴 Объект введен | O26: РВ от 30.04.2025 № 77-04-012528-2025 По состоянию на 01.11.2025 Производяться работы по утранению замечаний ГУП «Московский метрополитен». Из 473 шт. замечаний устранено 441 шт. Плановая дата передачи 5-ти оставшихся помещений - 28.11.2025
A27: =IFERROR(__xludf.DUMMYFUNCTION("""COMPUTED_VALUE"""),"1038") -> 1038 | B27: =IFERROR(__xludf.DUMMYFUNCTION("""COMPUTED_VALUE"""),"АИП-25") -> АИП-25 | C27: =IFERROR(__xludf.DUMMYFUNCTION("""COMPUTED_VALUE"""),"УДС") -> УДС | E27: =IFERROR(__xludf.DUMMYFUNCTION("""COMPUTED_VALUE"""),"Соединительная ветка с э/депо «Столбово» район Коммунарка") -> Соединительная ветка с э/депо «Столбово» район Коммунарка | F27: =IFERROR(__xludf.DUMMYFUNCTION("""COMPUTED_VALUE"""),"#N/A") -> #N/A | G27: =IFERROR(__xludf.DUMMYFUNCTION("""COMPUTED_VALUE"""),"#N/A") -> #N/A | H27: =IFERROR(__xludf.DUMMYFUNCTION("""COMPUTED_VALUE"""),"https://docs.google.com/spreadsheets/d/1jonEGMB3UFHiUZpltF1zURon8gYN7jGSHu-k9t5TXnA/edit?gid=1039816960#gid=1039816960") -> https://docs.google.com/spreadsheets/d/1jonEGMB3UFHiUZpltF1zURon8gYN7jGSHu-k9t5TXnA/edit?gid=1039816960#gid=1039816960 | J27: =IFERROR(__xludf.DUMMYFUNCTION("""COMPUTED_VALUE"""),65.804) -> 65.804 | K27: =IFERROR(__xludf.DUMMYFUNCTION("""COMPUTED_VALUE"""),45750.0) -> 45750 | L27: 14 | M27: 45764 | N27: 🔴 ПРОСРОЧЕН | O27: Ведется строительство
A28: =IFERROR(__xludf.DUMMYFUNCTION("""COMPUTED_VALUE"""),"1116") -> 1116 | B28: =IFERROR(__xludf.DUMMYFUNCTION("""COMPUTED_VALUE"""),"АИП-25") -> АИП-25 | C28: =IFERROR(__xludf.DUMMYFUNCTION("""COMPUTED_VALUE"""),"УДС") -> УДС | E28: =IFERROR(__xludf.DUMMYFUNCTION("""COMPUTED_VALUE"""),"Электродепо «Столбово» район Коммунарка, квартал № 159") -> Электродепо «Столбово» район Коммунарка, квартал № 159 | F28: =IFERROR(__xludf.DUMMYFUNCTION("""COMPUTED_VALUE"""),"#N/A") -> #N/A | G28: =IFERROR(__xludf.DUMMYFUNCTION("""COMPUTED_VALUE"""),"#N/A") -> #N/A | H28: =IFERROR(__xludf.DUMMYFUNCTION("""COMPUTED_VALUE"""),"https://docs.google.com/spreadsheets/d/1jonEGMB3UFHiUZpltF1zURon8gYN7jGSHu-k9t5TXnA/edit?gid=1117601488#gid=1117601488") -> https://docs.google.com/spreadsheets/d/1jonEGMB3UFHiUZpltF1zURon8gYN7jGSHu-k9t5TXnA/edit?gid=1117601488#gid=1117601488 | I28: =IFERROR(__xludf.DUMMYFUNCTION("""COMPUTED_VALUE"""),"https://disk.yandex.ru/client/disk/Осмотры%20объектов%20АНО%20СМГ/1034.%20Пересадка%20на%20станции%20метро%20Текстильщики%20(с%20БКЛ%20на%20ТКЛ)") -> https://disk.yandex.ru/client/disk/Осмотры%20объектов%20АНО%20СМГ/1034.%20Пересадка%20на%20станции%20метро%20Текстильщики%20(с%20БКЛ%20на%20ТКЛ) | J28: =IFERROR(__xludf.DUMMYFUNCTION("""COMPUTED_VALUE"""),87.325) -> 87.325 | K28: =IFERROR(__xludf.DUMMYFUNCTION("""COMPUTED_VALUE"""),45769.0) -> 45769 | L28: 14 | M28: 45783 | N28: 🔴 ПРОСРОЧЕН | O28: По состоянию на 31.05.2024 Земляные работы, устройство соединительных веток, монолитные работы и монтаж металлоконструкций, устройство инженерных систем, устройство внутриплощадочных инженерных сетей.
A29: =IFERROR(__xludf.DUMMYFUNCTION("""COMPUTED_VALUE"""),"1132 (этап 2)") -> 1132 (этап 2) | B29: =IFERROR(__xludf.DUMMYFUNCTION("""COMPUTED_VALUE"""),"АИП-25") -> АИП-25 | C29: =IFERROR(__xludf.DUMMYFUNCTION("""COMPUTED_VALUE"""),"УДС") -> УДС | E29: =IFERROR(__xludf.DUMMYFUNCTION("""COMPUTED_VALUE"""),"Технологическая часть транспортно-пересадочного узла на станции метро «Авиамоторная». Этап 2 Пешеходный переход станции метро «Авиамоторная»") -> Технологическая часть транспортно-пересадочного узла на станции метро «Авиамоторная». Этап 2 Пешеходный переход станции метро «Авиамоторная» | F29: =IFERROR(__xludf.DUMMYFUNCTION("""COMPUTED_VALUE"""),"55.752962604373806") -> 55.752962604373806 | G29: =IFERROR(__xludf.DUMMYFUNCTION("""COMPUTED_VALUE"""),"37.71994250729798") -> 37.71994250729798 | H29: =IFERROR(__xludf.DUMMYFUNCTION("""COMPUTED_VALUE"""),"https://docs.google.com/spreadsheets/d/1jonEGMB3UFHiUZpltF1zURon8gYN7jGSHu-k9t5TXnA/edit?gid=77612996#gid=77612996") -> https://docs.google.com/spreadsheets/d/1jonEGMB3UFHiUZpltF1zURon8gYN7jGSHu-k9t5TXnA/edit?gid=77612996#gid=77612996 | I29: =IFERROR(__xludf.DUMMYFUNCTION("""COMPUTED_VALUE"""),"https://disk.yandex.ru/client/disk/%D0%9E%D1%81%D0%BC%D0%BE%D1%82%D1%80%D1%8B%20%D0%BE%D0%B1%D1%8A%D0%B5%D0%BA%D1%82%D0%BE%D0%B2%20%D0%90%D0%9D%D0%9E%20%D0%A1%D0%9C%D0%93/1132.%20%D0%A2%D0%B5%D1%85%D0%BD%D0%BE%D0%BB%D0%BE%D0%B3%D0%B8%D1%87%D0%B5%D1%81%D0%"&"BA%D0%B0%D1%8F%20%D1%87%D0%B0%D1%81%D1%82%D1%8C%20%D0%A2%D0%9F%D0%A3%20%D0%BD%D0%B0%20%D1%81%D1%82%D0%B0%D0%BD%D1%86%D0%B8%D0%B8%20%D0%BC%D0%B5%D1%82%D1%80%D0%BE%20%22%D0%90%D0%B2%D0%B8%D0%B0%D0%BC%D0%BE%D1%82%D0%BE%D1%80%D0%BD%D0%B0%D1%8F%22%20") -> https://disk.yandex.ru/client/disk/%D0%9E%D1%81%D0%BC%D0%BE%D1%82%D1%80%D1%8B%20%D0%BE%D0%B1%D1%8A%D0%B5%D0%BA%D1%82%D0%BE%D0%B2%20%D0%90%D0%9D%D0%9E%20%D0%A1%D0%9C%D0%93/1132.%20%D0%A2%D0%B5%D1%85%D0%BD%D0%BE%D0%BB%D0%BE%D0%B3%D0%B8%D1%87%D0%B5%D1%81%D0%BA%D0%B0%D1%8F%20%D1%87%D0%B0%D1%81%D1%82%D1%8C%20%D0%A2%D0%9F%D0%A3%20%D0%BD%D0%B0%20%D1%81%D1%82%D0%B0%D0%BD%D1%86%D0%B8%D0%B8%20%D0%BC%D0%B5%D1%82%D1%80%D0%BE%20%22%D0%90%D0%B2%D0%B8%D0%B0%D0%BC%D0%BE%D1%82%D0%BE%D1%80%D0%BD%D0%B0%D1%8F%22%20 | J29: =IFERROR(__xludf.DUMMYFUNCTION("""COMPUTED_VALUE"""),100.0) -> 100 | K29: =IFERROR(__xludf.DUMMYFUNCTION("""COMPUTED_VALUE"""),45959.0) -> 45959 | L29: Завершен | N29: ✅ Завершен | O29: РВ от 08.04.2025 № 77-04-012504-2025
A30: =IFERROR(__xludf.DUMMYFUNCTION("""COMPUTED_VALUE"""),"1065 (этап 2.2)") -> 1065 (этап 2.2) | B30: =IFERROR(__xludf.DUMMYFUNCTION("""COMPUTED_VALUE"""),"АИП-25") -> АИП-25 | C30: =IFERROR(__xludf.DUMMYFUNCTION("""COMPUTED_VALUE"""),"УДС") -> УДС | E30: =IFERROR(__xludf.DUMMYFUNCTION("""COMPUTED_VALUE"""),"Технологическая часть транспортно-пересадочного узла на станции метро «Рассказовка» («Новопеределкино»). Этап 2.2 Парковка район Внуково, территория ТПУ «Рассказовка» ") -> Технологическая часть транспортно-пересадочного узла на станции метро «Рассказовка» («Новопеределкино»). Этап 2.2 Парковка район Внуково, территория ТПУ «Рассказовка» | F30: =IFERROR(__xludf.DUMMYFUNCTION("""COMPUTED_VALUE"""),"55.633969596534705") -> 55.633969596534705 | G30: =IFERROR(__xludf.DUMMYFUNCTION("""COMPUTED_VALUE"""),"37.3346986726294") -> 37.3346986726294 | H30: =IFERROR(__xludf.DUMMYFUNCTION("""COMPUTED_VALUE"""),"https://docs.google.com/spreadsheets/d/1jonEGMB3UFHiUZpltF1zURon8gYN7jGSHu-k9t5TXnA/edit?gid=1143459343#gid=1143459343") -> https://docs.google.com/spreadsheets/d/1jonEGMB3UFHiUZpltF1zURon8gYN7jGSHu-k9t5TXnA/edit?gid=1143459343#gid=1143459343 | I30: =IFERROR(__xludf.DUMMYFUNCTION("""COMPUTED_VALUE"""),"https://disk.yandex.ru/client/disk/Осмотры%20объектов%20АНО%20СМГ/1065.%201066.%20Технологическая%20часть%20ТПУ%20на%20станции%20метро%20%22Рассказовка%22%20(%22Новопеределкино%22)") -> https://disk.yandex.ru/client/disk/Осмотры%20объектов%20АНО%20СМГ/1065.%201066.%20Технологическая%20часть%20ТПУ%20на%20станции%20метро%20%22Рассказовка%22%20(%22Новопеределкино%22) | J30: =IFERROR(__xludf.DUMMYFUNCTION("""COMPUTED_VALUE"""),100.0) -> 100 | K30: =IFERROR(__xludf.DUMMYFUNCTION("""COMPUTED_VALUE"""),45974.0) -> 45974 | L30: Завершен | N30: ✅ Завершен | O30: РВ № 77-17-012630-2025 от 24.07.2025
A31: =IFERROR(__xludf.DUMMYFUNCTION("""COMPUTED_VALUE"""),"270") -> 270 | B31: =IFERROR(__xludf.DUMMYFUNCTION("""COMPUTED_VALUE"""),"АИП-25") -> АИП-25 | C31: =IFERROR(__xludf.DUMMYFUNCTION("""COMPUTED_VALUE"""),"ОКС+УДС") -> ОКС+УДС | E31: =IFERROR(__xludf.DUMMYFUNCTION("""COMPUTED_VALUE"""),"Подъездная дорога к административному зданию по адресу: 3-я Хорошевская ул., влд.17. Этап 1 - участок № 13 3-я Хорошевская ул., влд.17") -> Подъездная дорога к административному зданию по адресу: 3-я Хорошевская ул., влд.17. Этап 1 - участок № 13 3-я Хорошевская ул., влд.17 | F31: =IFERROR(__xludf.DUMMYFUNCTION("""COMPUTED_VALUE"""),"#N/A") -> #N/A | G31: =IFERROR(__xludf.DUMMYFUNCTION("""COMPUTED_VALUE"""),"#N/A") -> #N/A | H31: =IFERROR(__xludf.DUMMYFUNCTION("""COMPUTED_VALUE"""),"https://docs.google.com/spreadsheets/d/19THEBTE9q0fhN2eApZr6BgenIvLGh0AckaYxHQfHk5w/edit?gid=1112644991#gid=1112644991") -> https://docs.google.com/spreadsheets/d/19THEBTE9q0fhN2eApZr6BgenIvLGh0AckaYxHQfHk5w/edit?gid=1112644991#gid=1112644991 | I31: =IFERROR(__xludf.DUMMYFUNCTION("""COMPUTED_VALUE"""),"https://disk.yandex.ru/client/disk/Осмотры%20объектов%20АНО%20СМГ/270.%20Дорога%203-я%20Хорошевская%20вл.17") -> https://disk.yandex.ru/client/disk/Осмотры%20объектов%20АНО%20СМГ/270.%20Дорога%203-я%20Хорошевская%20вл.17 | J31: =IFERROR(__xludf.DUMMYFUNCTION("""COMPUTED_VALUE"""),99.9) -> 99.9 | K31: =IFERROR(__xludf.DUMMYFUNCTION("""COMPUTED_VALUE"""),45887.0) -> 45887 | L31: 7 | M31: 45894 | N31: 🔴 Объект введен | O31: РВ Строительство завершено Акт приемки объекта капитального строительства от 24.03.2025 б/н
A32: =IFERROR(__xludf.DUMMYFUNCTION("""COMPUTED_VALUE"""),"243") -> 243 | B32: =IFERROR(__xludf.DUMMYFUNCTION("""COMPUTED_VALUE"""),"АИП-25") -> АИП-25 | C32: =IFERROR(__xludf.DUMMYFUNCTION("""COMPUTED_VALUE"""),"ОКС") -> ОКС | E32: =IFERROR(__xludf.DUMMYFUNCTION("""COMPUTED_VALUE"""),"Спортивный комплекс, ул. Остафьевская, к. «Г» район Южное Бутово, ул. Остафьевская 21, корпус «Г»") -> Спортивный комплекс, ул. Остафьевская, к. «Г» район Южное Бутово, ул. Остафьевская 21, корпус «Г» | F32: =IFERROR(__xludf.DUMMYFUNCTION("""COMPUTED_VALUE"""),"#N/A") -> #N/A | G32: =IFERROR(__xludf.DUMMYFUNCTION("""COMPUTED_VALUE"""),"#N/A") -> #N/A | H32: =IFERROR(__xludf.DUMMYFUNCTION("""COMPUTED_VALUE"""),"https://docs.google.com/spreadsheets/d/19THEBTE9q0fhN2eApZr6BgenIvLGh0AckaYxHQfHk5w/edit?gid=1098291501#gid=1098291501") -> https://docs.google.com/spreadsheets/d/19THEBTE9q0fhN2eApZr6BgenIvLGh0AckaYxHQfHk5w/edit?gid=1098291501#gid=1098291501 | I32: =IFERROR(__xludf.DUMMYFUNCTION("""COMPUTED_VALUE"""),"https://disk.yandex.ru/client/disk/Осмотры%20объектов%20АНО%20СМГ/243.Остафьевская%20к.Г%20Южное%20Бутово") -> https://disk.yandex.ru/client/disk/Осмотры%20объектов%20АНО%20СМГ/243.Остафьевская%20к.Г%20Южное%20Бутово | J32: =IFERROR(__xludf.DUMMYFUNCTION("""COMPUTED_VALUE"""),100.0) -> 100 | K32: =IFERROR(__xludf.DUMMYFUNCTION("""COMPUTED_VALUE"""),45860.0) -> 45860 | L32: Завершен | N32: ✅ Завершен | O32: РВ от 28.03.2025 № 77-06-012484-2025
A33: =IFERROR(__xludf.DUMMYFUNCTION("""COMPUTED_VALUE"""),"131") -> 131 | B33: =IFERROR(__xludf.DUMMYFUNCTION("""COMPUTED_VALUE"""),"АИП-25") -> АИП-25 | C33: =IFERROR(__xludf.DUMMYFUNCTION("""COMPUTED_VALUE"""),"ОКС") -> ОКС | E33: =IFERROR(__xludf.DUMMYFUNCTION("""COMPUTED_VALUE"""),"ДОУ на 350 мест с бассейном, ул. Дубнинская, д. 9 район Бескудниковский, ул. Дубнинская, д. 9") -> ДОУ на 350 мест с бассейном, ул. Дубнинская, д. 9 район Бескудниковский, ул. Дубнинская, д. 9 | F33: =IFERROR(__xludf.DUMMYFUNCTION("""COMPUTED_VALUE"""),"#N/A") -> #N/A | G33: =IFERROR(__xludf.DUMMYFUNCTION("""COMPUTED_VALUE"""),"#N/A") -> #N/A | H33: =IFERROR(__xludf.DUMMYFUNCTION("""COMPUTED_VALUE"""),"https://docs.google.com/spreadsheets/d/19THEBTE9q0fhN2eApZr6BgenIvLGh0AckaYxHQfHk5w/edit?gid=2086114011#gid=2086114011") -> https://docs.google.com/spreadsheets/d/19THEBTE9q0fhN2eApZr6BgenIvLGh0AckaYxHQfHk5w/edit?gid=2086114011#gid=2086114011 | I33: =IFERROR(__xludf.DUMMYFUNCTION("""COMPUTED_VALUE"""),"https://disk.yandex.ru/client/disk/Осмотры%20объектов%20АНО%20СМГ/131.%20ДОУ%20на%20350%20мест%20с%20бассейном%20на%20месте%20сноса%20дошкольного%20отделения%20ГБОУ%20Школа%20№%201383%09%09%09") -> https://disk.yandex.ru/client/disk/Осмотры%20объектов%20АНО%20СМГ/131.%20ДОУ%20на%20350%20мест%20с%20бассейном%20на%20месте%20сноса%20дошкольного%20отделения%20ГБОУ%20Школа%20№%201383%09%09%09 | J33: =IFERROR(__xludf.DUMMYFUNCTION("""COMPUTED_VALUE"""),99.9605) -> 99.9605 | K33: =IFERROR(__xludf.DUMMYFUNCTION("""COMPUTED_VALUE"""),45902.0) -> 45902 | L33: 7 | M33: 45909 | N33: 🔴 Объект введен | O33: РВ № 77-09-012606-2025 от 09.07.2025 По состоянию на 21.08.2025 Ведутся работы по устранению замечаний администрации ДОУ
A34: =IFERROR(__xludf.DUMMYFUNCTION("""COMPUTED_VALUE"""),"262") -> 262 | B34: =IFERROR(__xludf.DUMMYFUNCTION("""COMPUTED_VALUE"""),"АИП-25") -> АИП-25 | C34: =IFERROR(__xludf.DUMMYFUNCTION("""COMPUTED_VALUE"""),"ОКС") -> ОКС | E34: =IFERROR(__xludf.DUMMYFUNCTION("""COMPUTED_VALUE"""),"Инфекционный лечебно-диагностический комплекс на территории ГБУЗ «ИКБ №1 ДЗМ», (3 этап - ПАК), Волоколамское шоссе, вл. 63 район Покровское-Стрешнево, Волоколамское шоссе вл. 63") -> Инфекционный лечебно-диагностический комплекс на территории ГБУЗ «ИКБ №1 ДЗМ», (3 этап - ПАК), Волоколамское шоссе, вл. 63 район Покровское-Стрешнево, Волоколамское шоссе вл. 63 | F34: =IFERROR(__xludf.DUMMYFUNCTION("""COMPUTED_VALUE"""),"#N/A") -> #N/A | G34: =IFERROR(__xludf.DUMMYFUNCTION("""COMPUTED_VALUE"""),"#N/A") -> #N/A | H34: =IFERROR(__xludf.DUMMYFUNCTION("""COMPUTED_VALUE"""),"https://docs.google.com/spreadsheets/d/19THEBTE9q0fhN2eApZr6BgenIvLGh0AckaYxHQfHk5w/edit?gid=1094262803#gid=1094262803") -> https://docs.google.com/spreadsheets/d/19THEBTE9q0fhN2eApZr6BgenIvLGh0AckaYxHQfHk5w/edit?gid=1094262803#gid=1094262803 | I34: =IFERROR(__xludf.DUMMYFUNCTION("""COMPUTED_VALUE"""),"https://disk.yandex.ru/client/disk/Осмотры%20объектов%20АНО%20СМГ/262.%20Волоколамское%20шоссе%2C%20вл.%2063%20(3%20этап)") -> https://disk.yandex.ru/client/disk/Осмотры%20объектов%20АНО%20СМГ/262.%20Волоколамское%20шоссе%2C%20вл.%2063%20(3%20этап) | J34: =IFERROR(__xludf.DUMMYFUNCTION("""COMPUTED_VALUE"""),100.0) -> 100 | K34: =IFERROR(__xludf.DUMMYFUNCTION("""COMPUTED_VALUE"""),45838.0) -> 45838 | L34: Завершен | N34: ✅ Завершен | O34: РВ №77-08-012502-2025 от 08.04.2025
A35: =IFERROR(__xludf.DUMMYFUNCTION("""COMPUTED_VALUE"""),"114") -> 114 | B35: =IFERROR(__xludf.DUMMYFUNCTION("""COMPUTED_VALUE"""),"АИП-25") -> АИП-25 | C35: =IFERROR(__xludf.DUMMYFUNCTION("""COMPUTED_VALUE"""),"ОКС") -> ОКС | E35: =IFERROR(__xludf.DUMMYFUNCTION("""COMPUTED_VALUE"""),"Физкультурно-оздоровительный комплекс с бассейном, пересечение ул. Шипиловской и Орехового проезда ""Акварис"" район Зябликово, пересечение ул. Шипиловской и Орехового пр-да (Ореховый проезд, д.12)") -> Физкультурно-оздоровительный комплекс с бассейном, пересечение ул. Шипиловской и Орехового проезда "Акварис" район Зябликово, пересечение ул. Шипиловской и Орехового пр-да (Ореховый проезд, д.12) | F35: =IFERROR(__xludf.DUMMYFUNCTION("""COMPUTED_VALUE"""),"55.623316") -> 55.623316 | G35: =IFERROR(__xludf.DUMMYFUNCTION("""COMPUTED_VALUE"""),"37.729792") -> 37.729792 | H35: =IFERROR(__xludf.DUMMYFUNCTION("""COMPUTED_VALUE"""),"https://docs.google.com/spreadsheets/d/19THEBTE9q0fhN2eApZr6BgenIvLGh0AckaYxHQfHk5w/edit?gid=2132720371#gid=2132720371") -> https://docs.google.com/spreadsheets/d/19THEBTE9q0fhN2eApZr6BgenIvLGh0AckaYxHQfHk5w/edit?gid=2132720371#gid=2132720371 | I35: =IFERROR(__xludf.DUMMYFUNCTION("""COMPUTED_VALUE"""),"https://disk.yandex.ru/client/disk/%D0%9E%D1%81%D0%BC%D0%BE%D1%82%D1%80%D1%8B%20%D0%BE%D0%B1%D1%8A%D0%B5%D0%BA%D1%82%D0%BE%D0%B2%20%D0%90%D0%9D%D0%9E%20%D0%A1%D0%9C%D0%93/114.%20%D0%A4%D0%9E%D0%9A%20%D0%A1%D0%9A%20%D0%90%D0%BA%D0%B2%D0%B0%D1%80%D0%B8%D1%8"&"1%20%D0%BF%D0%B5%D1%80%D0%B5%D1%81%D0%B5%D1%87%D0%B5%D0%BD%D0%B8%D0%B5%20%D0%A8%D0%B8%D0%BF%D0%B8%D0%BB%D0%BE%D0%B2%D1%81%D0%BA%D0%BE%D0%B9%20%D0%B8%20%D0%9E%D1%80%D0%B5%D1%85%D0%BE%D0%B2%D0%BE%D0%B3%D0%BE%20%D0%BF%D1%80.") -> https://disk.yandex.ru/client/disk/%D0%9E%D1%81%D0%BC%D0%BE%D1%82%D1%80%D1%8B%20%D0%BE%D0%B1%D1%8A%D0%B5%D0%BA%D1%82%D0%BE%D0%B2%20%D0%90%D0%9D%D0%9E%20%D0%A1%D0%9C%D0%93/114.%20%D0%A4%D0%9E%D0%9A%20%D0%A1%D0%9A%20%D0%90%D0%BA%D0%B2%D0%B0%D1%80%D0%B8%D1%81%20%D0%BF%D0%B5%D1%80%D0%B5%D1%81%D0%B5%D1%87%D0%B5%D0%BD%D0%B8%D0%B5%20%D0%A8%D0%B8%D0%BF%D0%B8%D0%BB%D0%BE%D0%B2%D1%81%D0%BA%D0%BE%D0%B9%20%D0%B8%20%D0%9E%D1%80%D0%B5%D1%85%D0%BE%D0%B2%D0%BE%D0%B3%D0%BE%20%D0%BF%D1%80. | J35: =IFERROR(__xludf.DUMMYFUNCTION("""COMPUTED_VALUE"""),100.0) -> 100 | K35: =IFERROR(__xludf.DUMMYFUNCTION("""COMPUTED_VALUE"""),45972.0) -> 45972 | L35: Завершен | N35: ✅ Завершен | O35: РВ от 31.03.2025 №77-05-012492-2025
A36: =IFERROR(__xludf.DUMMYFUNCTION("""COMPUTED_VALUE"""),"113") -> 113 | B36: =IFERROR(__xludf.DUMMYFUNCTION("""COMPUTED_VALUE"""),"АИП-25") -> АИП-25 | C36: =IFERROR(__xludf.DUMMYFUNCTION("""COMPUTED_VALUE"""),"ОКС") -> ОКС | E36: =IFERROR(__xludf.DUMMYFUNCTION("""COMPUTED_VALUE"""),"Строительство школы на 800 мест (с дошкольным отделением на 150 мест) на месте сноса объекта незавершенного строительства (пристройка к школе - блоки А, Б, В) в пос. Щаповское пос. Щаповское, пос. Щапово, д. 21, стр. 2") -> Строительство школы на 800 мест (с дошкольным отделением на 150 мест) на месте сноса объекта незавершенного строительства (пристройка к школе - блоки А, Б, В) в пос. Щаповское пос. Щаповское, пос. Щапово, д. 21, стр. 2 | F36: =IFERROR(__xludf.DUMMYFUNCTION("""COMPUTED_VALUE"""),"#N/A") -> #N/A | G36: =IFERROR(__xludf.DUMMYFUNCTION("""COMPUTED_VALUE"""),"#N/A") -> #N/A | H36: =IFERROR(__xludf.DUMMYFUNCTION("""COMPUTED_VALUE"""),"https://docs.google.com/spreadsheets/d/19THEBTE9q0fhN2eApZr6BgenIvLGh0AckaYxHQfHk5w/edit?gid=1857713469#gid=1857713469") -> https://docs.google.com/spreadsheets/d/19THEBTE9q0fhN2eApZr6BgenIvLGh0AckaYxHQfHk5w/edit?gid=1857713469#gid=1857713469 | I36: =IFERROR(__xludf.DUMMYFUNCTION("""COMPUTED_VALUE"""),"https://disk.yandex.ru/client/disk/Осмотры%20объектов%20АНО%20СМГ/113.%20Щаповское%20(СОШ%20на%20800)") -> https://disk.yandex.ru/client/disk/Осмотры%20объектов%20АНО%20СМГ/113.%20Щаповское%20(СОШ%20на%20800) | J36: =IFERROR(__xludf.DUMMYFUNCTION("""COMPUTED_VALUE"""),100.0) -> 100 | K36: =IFERROR(__xludf.DUMMYFUNCTION("""COMPUTED_VALUE"""),45901.0) -> 45901 | L36: Завершен | N36: ✅ Завершен | O36: РВ от 18.07.2025 № 77-22-012624-2025 По состоянию на 13.10.2025 Ведутся работы по устранению замечаний выданных ГКУ ДИОМ по гарантийному письму
A37: =IFERROR(__xludf.DUMMYFUNCTION("""COMPUTED_VALUE"""),"010") -> 010 | B37: =IFERROR(__xludf.DUMMYFUNCTION("""COMPUTED_VALUE"""),"АИП-25") -> АИП-25 | C37: =IFERROR(__xludf.DUMMYFUNCTION("""COMPUTED_VALUE"""),"ОКС") -> ОКС | E37: =IFERROR(__xludf.DUMMYFUNCTION("""COMPUTED_VALUE"""),"Реконструкция дома культуры, п. Ватутинки п. Ватутинки, пос. Десеновское, ул. Дмитрия Рябинкина, вл. 13 и вл. 13А") -> Реконструкция дома культуры, п. Ватутинки п. Ватутинки, пос. Десеновское, ул. Дмитрия Рябинкина, вл. 13 и вл. 13А | F37: =IFERROR(__xludf.DUMMYFUNCTION("""COMPUTED_VALUE"""),"#N/A") -> #N/A | G37: =IFERROR(__xludf.DUMMYFUNCTION("""COMPUTED_VALUE"""),"#N/A") -> #N/A | H37: =IFERROR(__xludf.DUMMYFUNCTION("""COMPUTED_VALUE"""),"https://docs.google.com/spreadsheets/d/19THEBTE9q0fhN2eApZr6BgenIvLGh0AckaYxHQfHk5w/edit?gid=234638124#gid=234638124") -> https://docs.google.com/spreadsheets/d/19THEBTE9q0fhN2eApZr6BgenIvLGh0AckaYxHQfHk5w/edit?gid=234638124#gid=234638124 | I37: =IFERROR(__xludf.DUMMYFUNCTION("""COMPUTED_VALUE"""),"https://disk.yandex.ru/client/disk/Осмотры%20объектов%20АНО%20СМГ/010.%20Дом%20культуры%2C%20Дмитрия%20Рябинкина%2013") -> https://disk.yandex.ru/client/disk/Осмотры%20объектов%20АНО%20СМГ/010.%20Дом%20культуры%2C%20Дмитрия%20Рябинкина%2013 | J37: =IFERROR(__xludf.DUMMYFUNCTION("""COMPUTED_VALUE"""),100.0) -> 100 | K37: =IFERROR(__xludf.DUMMYFUNCTION("""COMPUTED_VALUE"""),45895.0) -> 45895 | L37: Завершен | N37: ✅ Завершен | O37: РВ от 26.06.2025 №77-17-012585-2025
A38: =IFERROR(__xludf.DUMMYFUNCTION("""COMPUTED_VALUE"""),"009") -> 009 | B38: =IFERROR(__xludf.DUMMYFUNCTION("""COMPUTED_VALUE"""),"АИП-25") -> АИП-25 | C38: =IFERROR(__xludf.DUMMYFUNCTION("""COMPUTED_VALUE"""),"ОКС") -> ОКС | E38: =IFERROR(__xludf.DUMMYFUNCTION("""COMPUTED_VALUE"""),"Школа искусств, п. Московский, мкр. Град Московский пос. Московский, мкр. Град Московский, ул. Никитина, д. 7") -> Школа искусств, п. Московский, мкр. Град Московский пос. Московский, мкр. Град Московский, ул. Никитина, д. 7 | F38: =IFERROR(__xludf.DUMMYFUNCTION("""COMPUTED_VALUE"""),"55.606054") -> 55.606054 | G38: =IFERROR(__xludf.DUMMYFUNCTION("""COMPUTED_VALUE"""),"37.369361") -> 37.369361 | H38: =IFERROR(__xludf.DUMMYFUNCTION("""COMPUTED_VALUE"""),"https://docs.google.com/spreadsheets/d/19THEBTE9q0fhN2eApZr6BgenIvLGh0AckaYxHQfHk5w/edit?gid=570396026#gid=570396026") -> https://docs.google.com/spreadsheets/d/19THEBTE9q0fhN2eApZr6BgenIvLGh0AckaYxHQfHk5w/edit?gid=570396026#gid=570396026 | I38: =IFERROR(__xludf.DUMMYFUNCTION("""COMPUTED_VALUE"""),"https://disk.yandex.ru/client/disk/Осмотры%20объектов%20АНО%20СМГ/009.%20Школа%20искусств%20п.%20Московский%20микрорайон%203%20д.8") -> https://disk.yandex.ru/client/disk/Осмотры%20объектов%20АНО%20СМГ/009.%20Школа%20искусств%20п.%20Московский%20микрорайон%203%20д.8 | J38: =IFERROR(__xludf.DUMMYFUNCTION("""COMPUTED_VALUE"""),100.0) -> 100 | K38: =IFERROR(__xludf.DUMMYFUNCTION("""COMPUTED_VALUE"""),45972.0) -> 45972 | L38: Завершен | N38: ✅ Завершен | O38: РВ № 77-17-012738-2025 от 24.09.2025 По состоянию на 06.11.2025 На обьекте идут работы по устранению замечаний по гарантийным обязательствам, монтажу мебели, уборке и передача помещений Отсутствует эксплуатирующая компания
A39: =IFERROR(__xludf.DUMMYFUNCTION("""COMPUTED_VALUE"""),"103") -> 103 | B39: =IFERROR(__xludf.DUMMYFUNCTION("""COMPUTED_VALUE"""),"АИП-25") -> АИП-25 | C39: =IFERROR(__xludf.DUMMYFUNCTION("""COMPUTED_VALUE"""),"ОКС") -> ОКС | E39: =IFERROR(__xludf.DUMMYFUNCTION("""COMPUTED_VALUE""")," Учебный корпус на 550 мест (в том числе дошкольное отделение на 150 мест), р-н Куркино, ул. Юровская, д. 99 с автономным источником тепла район Куркино, ул. Юровская, д. 99") -> Учебный корпус на 550 мест (в том числе дошкольное отделение на 150 мест), р-н Куркино, ул. Юровская, д. 99 с автономным источником тепла район Куркино, ул. Юровская, д. 99 | F39: =IFERROR(__xludf.DUMMYFUNCTION("""COMPUTED_VALUE"""),"#N/A") -> #N/A | G39: =IFERROR(__xludf.DUMMYFUNCTION("""COMPUTED_VALUE"""),"#N/A") -> #N/A | H39: =IFERROR(__xludf.DUMMYFUNCTION("""COMPUTED_VALUE"""),"https://docs.google.com/spreadsheets/d/19THEBTE9q0fhN2eApZr6BgenIvLGh0AckaYxHQfHk5w/edit?gid=418899370#gid=418899370") -> https://docs.google.com/spreadsheets/d/19THEBTE9q0fhN2eApZr6BgenIvLGh0AckaYxHQfHk5w/edit?gid=418899370#gid=418899370 | I39: =IFERROR(__xludf.DUMMYFUNCTION("""COMPUTED_VALUE"""),"https://disk.yandex.ru/client/disk/Осмотры%20объектов%20АНО%20СМГ/103.%20Юровская%2099%20УК%20550%20ДОУ%20150") -> https://disk.yandex.ru/client/disk/Осмотры%20объектов%20АНО%20СМГ/103.%20Юровская%2099%20УК%20550%20ДОУ%20150 | J39: =IFERROR(__xludf.DUMMYFUNCTION("""COMPUTED_VALUE"""),100.0) -> 100 | K39: =IFERROR(__xludf.DUMMYFUNCTION("""COMPUTED_VALUE"""),45901.0) -> 45901 | L39: Завершен | N39: ✅ Завершен | O39: РВ от 16.06.2025 №77-08-012572-2025
A40: =IFERROR(__xludf.DUMMYFUNCTION("""COMPUTED_VALUE"""),"013") -> 013 | B40: =IFERROR(__xludf.DUMMYFUNCTION("""COMPUTED_VALUE"""),"АИП-25") -> АИП-25 | C40: =IFERROR(__xludf.DUMMYFUNCTION("""COMPUTED_VALUE"""),"ОКС") -> ОКС | E40: =IFERROR(__xludf.DUMMYFUNCTION("""COMPUTED_VALUE"""),"Школа на 1100 мест (в части общестроительных работ и устройства наружных инженерных сетей) пос. Мосрентген, квартал 24, вл.2") -> Школа на 1100 мест (в части общестроительных работ и устройства наружных инженерных сетей) пос. Мосрентген, квартал 24, вл.2 | F40: =IFERROR(__xludf.DUMMYFUNCTION("""COMPUTED_VALUE"""),"#N/A") -> #N/A | G40: =IFERROR(__xludf.DUMMYFUNCTION("""COMPUTED_VALUE"""),"#N/A") -> #N/A | H40: =IFERROR(__xludf.DUMMYFUNCTION("""COMPUTED_VALUE"""),"https://docs.google.com/spreadsheets/d/19THEBTE9q0fhN2eApZr6BgenIvLGh0AckaYxHQfHk5w/edit?gid=1447691158#gid=1447691158") -> https://docs.google.com/spreadsheets/d/19THEBTE9q0fhN2eApZr6BgenIvLGh0AckaYxHQfHk5w/edit?gid=1447691158#gid=1447691158 | I40: =IFERROR(__xludf.DUMMYFUNCTION("""COMPUTED_VALUE"""),"https://disk.yandex.ru/client/disk/Осмотры%20объектов%20АНО%20СМГ/013.%20СОШ1100%20Мосренген") -> https://disk.yandex.ru/client/disk/Осмотры%20объектов%20АНО%20СМГ/013.%20СОШ1100%20Мосренген | J40: =IFERROR(__xludf.DUMMYFUNCTION("""COMPUTED_VALUE"""),100.0) -> 100 | K40: =IFERROR(__xludf.DUMMYFUNCTION("""COMPUTED_VALUE"""),45902.0) -> 45902 | L40: Завершен | N40: ✅ Завершен | O40: По состоянию на 21.08.2025 РВ № 77-17-012580-2025 от 20.06.2025 Ведутся работы по устранению замечаний, выданных ГКУ ДИОМ (остаток к устранению - 2 шт) Плановая дата устранения и передачи ГКУ ДИОМ до 30.09.2025
A41: =IFERROR(__xludf.DUMMYFUNCTION("""COMPUTED_VALUE"""),"013") -> 013 | B41: =IFERROR(__xludf.DUMMYFUNCTION("""COMPUTED_VALUE"""),"АИП-25") -> АИП-25 | C41: =IFERROR(__xludf.DUMMYFUNCTION("""COMPUTED_VALUE"""),"ОКС") -> ОКС | E41: =IFERROR(__xludf.DUMMYFUNCTION("""COMPUTED_VALUE"""),"Школа на 1100 мест (в части общестроительных работ и устройства наружных инженерных сетей) Школа на 1100 мест,поселение Мосрентген, квартал 24, д. 2") -> Школа на 1100 мест (в части общестроительных работ и устройства наружных инженерных сетей) Школа на 1100 мест,_x000b_поселение Мосрентген, квартал 24, д. 2 | F41: =IFERROR(__xludf.DUMMYFUNCTION("""COMPUTED_VALUE"""),"#N/A") -> #N/A | G41: =IFERROR(__xludf.DUMMYFUNCTION("""COMPUTED_VALUE"""),"#N/A") -> #N/A | H41: =IFERROR(__xludf.DUMMYFUNCTION("""COMPUTED_VALUE"""),"https://docs.google.com/spreadsheets/d/19THEBTE9q0fhN2eApZr6BgenIvLGh0AckaYxHQfHk5w/edit?gid=1447691158#gid=1447691158") -> https://docs.google.com/spreadsheets/d/19THEBTE9q0fhN2eApZr6BgenIvLGh0AckaYxHQfHk5w/edit?gid=1447691158#gid=1447691158 | I41: =IFERROR(__xludf.DUMMYFUNCTION("""COMPUTED_VALUE"""),"https://disk.yandex.ru/client/disk/Осмотры%20объектов%20АНО%20СМГ/013.%20СОШ1100%20Мосренген") -> https://disk.yandex.ru/client/disk/Осмотры%20объектов%20АНО%20СМГ/013.%20СОШ1100%20Мосренген | J41: =IFERROR(__xludf.DUMMYFUNCTION("""COMPUTED_VALUE"""),100.0) -> 100 | K41: =IFERROR(__xludf.DUMMYFUNCTION("""COMPUTED_VALUE"""),45902.0) -> 45902 | L41: Завершен | N41: ✅ Завершен | O41: -
A42: =IFERROR(__xludf.DUMMYFUNCTION("""COMPUTED_VALUE"""),"011") -> 011 | B42: =IFERROR(__xludf.DUMMYFUNCTION("""COMPUTED_VALUE"""),"АИП-25") -> АИП-25 | C42: =IFERROR(__xludf.DUMMYFUNCTION("""COMPUTED_VALUE"""),"ОКС") -> ОКС | E42: =IFERROR(__xludf.DUMMYFUNCTION("""COMPUTED_VALUE"""),"Реконструкция существующего здания школы № 2075 со строительством пристройки на 300 мест, пос. Красная Пахра, вл. 23-1 пос. Краснопахорское, пос. Красная Пахра, вл. 23-1") -> Реконструкция существующего здания школы _x000b_№ 2075 со строительством пристройки на 300 мест, пос. Красная Пахра, вл. 23-1 пос. Краснопахорское, пос. Красная Пахра, вл. 23-1 | F42: =IFERROR(__xludf.DUMMYFUNCTION("""COMPUTED_VALUE"""),"#N/A") -> #N/A | G42: =IFERROR(__xludf.DUMMYFUNCTION("""COMPUTED_VALUE"""),"#N/A") -> #N/A | H42: =IFERROR(__xludf.DUMMYFUNCTION("""COMPUTED_VALUE"""),"https://docs.google.com/spreadsheets/d/19THEBTE9q0fhN2eApZr6BgenIvLGh0AckaYxHQfHk5w/edit?gid=465129833#gid=465129833") -> https://docs.google.com/spreadsheets/d/19THEBTE9q0fhN2eApZr6BgenIvLGh0AckaYxHQfHk5w/edit?gid=465129833#gid=465129833 | I42: =IFERROR(__xludf.DUMMYFUNCTION("""COMPUTED_VALUE"""),"https://disk.yandex.ru/client/disk/Осмотры%20объектов%20АНО%20СМГ/011.%20СОШ%202075%20Красная%20Пахра") -> https://disk.yandex.ru/client/disk/Осмотры%20объектов%20АНО%20СМГ/011.%20СОШ%202075%20Красная%20Пахра | J42: =IFERROR(__xludf.DUMMYFUNCTION("""COMPUTED_VALUE"""),100.0) -> 100 | K42: =IFERROR(__xludf.DUMMYFUNCTION("""COMPUTED_VALUE"""),45901.0) -> 45901 | L42: Завершен | N42: ✅ Завершен | O42: РВ № 77-22-012638-2025 от 30.07.2025
A43: =IFERROR(__xludf.DUMMYFUNCTION("""COMPUTED_VALUE"""),"1153д (этап 5.1.3)") -> 1153д (этап 5.1.3) | B43: =IFERROR(__xludf.DUMMYFUNCTION("""COMPUTED_VALUE"""),"013") -> 013 | C43: =IFERROR(__xludf.DUMMYFUNCTION("""COMPUTED_VALUE"""),"УДС") -> УДС | E43: =IFERROR(__xludf.DUMMYFUNCTION("""COMPUTED_VALUE"""),"Прокладка водопровода Д1000 мм от деревни сосенки до города Троицк со строительством водопроводных узлов ""Станиславль"" и ""Красная Пахра"" этап 5.1.3. от деревни Сосенки до города Троицк") -> Прокладка водопровода Д1000 мм от деревни сосенки до города Троицк со строительством водопроводных узлов "Станиславль" и "Красная Пахра" этап 5.1.3. от деревни Сосенки до города Троицк | F43: =IFERROR(__xludf.DUMMYFUNCTION("""COMPUTED_VALUE"""),"55.523077578675746") -> 55.523077578675746 | G43: =IFERROR(__xludf.DUMMYFUNCTION("""COMPUTED_VALUE"""),"37.38505719530739") -> 37.38505719530739 | J43: =IFERROR(__xludf.DUMMYFUNCTION("""COMPUTED_VALUE"""),100.0) -> 100 | K43: =IFERROR(__xludf.DUMMYFUNCTION("""COMPUTED_VALUE"""),45887.0) -> 45887 | L43: Завершен | N43: ✅ Завершен | O43: Получен Акт приемки объекта капитального строительства от 28.04.2025
A44: =IFERROR(__xludf.DUMMYFUNCTION("""COMPUTED_VALUE"""),"1286") -> 1286 | B44: =IFERROR(__xludf.DUMMYFUNCTION("""COMPUTED_VALUE"""),"АИП-25") -> АИП-25 | C44: =IFERROR(__xludf.DUMMYFUNCTION("""COMPUTED_VALUE"""),"УДС") -> УДС | E44: =IFERROR(__xludf.DUMMYFUNCTION("""COMPUTED_VALUE"""),"ПР-56-01-7 Дорога и инженерные коммуникации для застройки мкр.19 (а, б, в) р-на Ховрино (7 пусковой комплекс) г. Москва, район Ховрино, мкр.19 а,б,в") -> ПР-56-01-7 Дорога и инженерные коммуникации для застройки мкр.19 (а, б, в) р-на Ховрино (7 пусковой комплекс) г. Москва, район Ховрино, мкр.19 а,б,в | F44: =IFERROR(__xludf.DUMMYFUNCTION("""COMPUTED_VALUE"""),"#N/A") -> #N/A | G44: =IFERROR(__xludf.DUMMYFUNCTION("""COMPUTED_VALUE"""),"#N/A") -> #N/A | H44: =IFERROR(__xludf.DUMMYFUNCTION("""COMPUTED_VALUE"""),"https://docs.google.com/spreadsheets/d/1MW8OIVEKRJEaLcG-KS0zwZPEQ0eRUWE2y9Gj77rgoxo/edit?gid=1454312032#gid=1454312032") -> https://docs.google.com/spreadsheets/d/1MW8OIVEKRJEaLcG-KS0zwZPEQ0eRUWE2y9Gj77rgoxo/edit?gid=1454312032#gid=1454312032 | J44: =IFERROR(__xludf.DUMMYFUNCTION("""COMPUTED_VALUE"""),100.0) -> 100 | K44: =IFERROR(__xludf.DUMMYFUNCTION("""COMPUTED_VALUE"""),45887.0) -> 45887 | L44: Завершен | N44: ✅ Завершен | O44: Акт приемки объекта капитального строительства от 15.05.2025
A45: =IFERROR(__xludf.DUMMYFUNCTION("""COMPUTED_VALUE"""),"182д") -> 182д | B45: =IFERROR(__xludf.DUMMYFUNCTION("""COMPUTED_VALUE"""),"АИП-25") -> АИП-25 | C45: =IFERROR(__xludf.DUMMYFUNCTION("""COMPUTED_VALUE"""),"УДС") -> УДС | E45: =IFERROR(__xludf.DUMMYFUNCTION("""COMPUTED_VALUE"""),"Многоуровневая транспортная развязка с прилегающей улично – дорожной сетью в районе станции метро ""Мамыри"" (Открытие многоуровневой транспортной развязки в районе станции метро «Корниловская») В районе станции метро «Мамыри» (НАО)") -> Многоуровневая транспортная развязка с прилегающей улично – дорожной сетью в районе станции метро "Мамыри" (Открытие многоуровневой транспортной развязки в районе станции метро «Корниловская») В районе станции метро «Мамыри» (НАО) | F45: =IFERROR(__xludf.DUMMYFUNCTION("""COMPUTED_VALUE"""),"#N/A") -> #N/A | G45: =IFERROR(__xludf.DUMMYFUNCTION("""COMPUTED_VALUE"""),"#N/A") -> #N/A | J45: =IFERROR(__xludf.DUMMYFUNCTION("""COMPUTED_VALUE"""),100.0) -> 100 | K45: =IFERROR(__xludf.DUMMYFUNCTION("""COMPUTED_VALUE"""),45972.0) -> 45972 | L45: Завершен | N45: ✅ Завершен | O45: РВ №77-0-012664-2025 от 08.08.2025
A46: =IFERROR(__xludf.DUMMYFUNCTION("""COMPUTED_VALUE"""),"217д") -> 217д | B46: =IFERROR(__xludf.DUMMYFUNCTION("""COMPUTED_VALUE"""),"АИП-25") -> АИП-25 | C46: =IFERROR(__xludf.DUMMYFUNCTION("""COMPUTED_VALUE"""),"УДС") -> УДС | E46: =IFERROR(__xludf.DUMMYFUNCTION("""COMPUTED_VALUE"""),"Улично-дорожная сеть в п.Мосрентген. Строительство магистральных улиц районного значения - проектируемые пр-ды 1-2-26, 1-2-23, 1-2-29, 1-2-7, от проектируемого пр-да 1-2-26 до ул. Адмирала Корнилова поселение «Мосрентген», Новомосковский административный "&"округ города Москвы") -> Улично-дорожная сеть в п.Мосрентген. Строительство магистральных улиц районного значения - проектируемые пр-ды 1-2-26, 1-2-23, 1-2-29, 1-2-7, от проектируемого пр-да 1-2-26 до ул. Адмирала Корнилова поселение «Мосрентген», Новомосковский административный округ города Москвы | F46: =IFERROR(__xludf.DUMMYFUNCTION("""COMPUTED_VALUE"""),"#N/A") -> #N/A | G46: =IFERROR(__xludf.DUMMYFUNCTION("""COMPUTED_VALUE"""),"#N/A") -> #N/A | J46: =IFERROR(__xludf.DUMMYFUNCTION("""COMPUTED_VALUE"""),99.4) -> 99.4 | K46: =IFERROR(__xludf.DUMMYFUNCTION("""COMPUTED_VALUE"""),45973.0) -> 45973 | L46: 7 | M46: 45980 | N46: 🔴 Объект введен | O46: РВ от 25.06.2025 № 77-0-012584-2025
A47: =IFERROR(__xludf.DUMMYFUNCTION("""COMPUTED_VALUE"""),"155д") -> 155д | B47: =IFERROR(__xludf.DUMMYFUNCTION("""COMPUTED_VALUE"""),"АИП-25") -> АИП-25 | C47: =IFERROR(__xludf.DUMMYFUNCTION("""COMPUTED_VALUE"""),"УДС") -> УДС | E47: =IFERROR(__xludf.DUMMYFUNCTION("""COMPUTED_VALUE"""),"Улично-дорожная сеть во 2-м мкр. р-на Северный район Северный, СВАО города Москвы") -> Улично-дорожная сеть во 2-м мкр. р-на Северный район Северный, СВАО города Москвы | F47: =IFERROR(__xludf.DUMMYFUNCTION("""COMPUTED_VALUE"""),"#N/A") -> #N/A | G47: =IFERROR(__xludf.DUMMYFUNCTION("""COMPUTED_VALUE"""),"#N/A") -> #N/A | J47: =IFERROR(__xludf.DUMMYFUNCTION("""COMPUTED_VALUE"""),100.0) -> 100 | K47: =IFERROR(__xludf.DUMMYFUNCTION("""COMPUTED_VALUE"""),45973.0) -> 45973 | L47: Завершен | N47: ✅ Завершен | O47: РВ от 29.09.2025 № 77-02-012745-2025
A48: =IFERROR(__xludf.DUMMYFUNCTION("""COMPUTED_VALUE"""),"175") -> 175 | B48: =IFERROR(__xludf.DUMMYFUNCTION("""COMPUTED_VALUE"""),"АИП-25") -> АИП-25 | C48: =IFERROR(__xludf.DUMMYFUNCTION("""COMPUTED_VALUE"""),"ОКС") -> ОКС | E48: =IFERROR(__xludf.DUMMYFUNCTION("""COMPUTED_VALUE"""),"Жилые дома с инженерными коммуникациями и благоустройством, Чечерский проезд, напротив вл. 54, 56 район Южное Бутово, Чечерский проезд, напротив вл. 54, 56") -> Жилые дома с инженерными коммуникациями и благоустройством, Чечерский проезд, напротив вл. 54, 56 район Южное Бутово, Чечерский проезд, напротив вл. 54, 56 | F48: =IFERROR(__xludf.DUMMYFUNCTION("""COMPUTED_VALUE"""),"#N/A") -> #N/A | G48: =IFERROR(__xludf.DUMMYFUNCTION("""COMPUTED_VALUE"""),"#N/A") -> #N/A | H48: =IFERROR(__xludf.DUMMYFUNCTION("""COMPUTED_VALUE"""),"https://docs.google.com/spreadsheets/d/19THEBTE9q0fhN2eApZr6BgenIvLGh0AckaYxHQfHk5w/edit?gid=1190089568#gid=1190089568") -> https://docs.google.com/spreadsheets/d/19THEBTE9q0fhN2eApZr6BgenIvLGh0AckaYxHQfHk5w/edit?gid=1190089568#gid=1190089568 | I48: =IFERROR(__xludf.DUMMYFUNCTION("""COMPUTED_VALUE"""),"https://disk.yandex.ru/client/disk/Осмотры%20объектов%20АНО%20СМГ/175.%20Южное%20Бутово%2C%20Чечëрский%20пр-д%2C%20вл.%2054%2C%2056.") -> https://disk.yandex.ru/client/disk/Осмотры%20объектов%20АНО%20СМГ/175.%20Южное%20Бутово%2C%20Чечëрский%20пр-д%2C%20вл.%2054%2C%2056. | J48: =IFERROR(__xludf.DUMMYFUNCTION("""COMPUTED_VALUE"""),99.94) -> 99.94 | K48: =IFERROR(__xludf.DUMMYFUNCTION("""COMPUTED_VALUE"""),45839.0) -> 45839 | L48: 7 | M48: 45846 | N48: 🔴 Объект введен | O48: РВ № 77-06-012560-2025 от 30.05.2025
A49: =IFERROR(__xludf.DUMMYFUNCTION("""COMPUTED_VALUE"""),"176") -> 176 | B49: =IFERROR(__xludf.DUMMYFUNCTION("""COMPUTED_VALUE"""),"АИП-25") -> АИП-25 | C49: =IFERROR(__xludf.DUMMYFUNCTION("""COMPUTED_VALUE"""),"ОКС") -> ОКС | E49: =IFERROR(__xludf.DUMMYFUNCTION("""COMPUTED_VALUE"""),"Административное здание, ул. Синявинская, вл. 11 Молжаниновский район, ул. Синявинская, вл. 11") -> Административное здание, ул. Синявинская, вл. 11 Молжаниновский район, ул. Синявинская, вл. 11 | F49: =IFERROR(__xludf.DUMMYFUNCTION("""COMPUTED_VALUE"""),"#N/A") -> #N/A | G49: =IFERROR(__xludf.DUMMYFUNCTION("""COMPUTED_VALUE"""),"#N/A") -> #N/A | H49: =IFERROR(__xludf.DUMMYFUNCTION("""COMPUTED_VALUE"""),"https://docs.google.com/spreadsheets/d/19THEBTE9q0fhN2eApZr6BgenIvLGh0AckaYxHQfHk5w/edit?gid=700032418#gid=700032418") -> https://docs.google.com/spreadsheets/d/19THEBTE9q0fhN2eApZr6BgenIvLGh0AckaYxHQfHk5w/edit?gid=700032418#gid=700032418 | I49: =IFERROR(__xludf.DUMMYFUNCTION("""COMPUTED_VALUE"""),"https://disk.yandex.ru/client/disk/Осмотры%20объектов%20АНО%20СМГ/176.%20Синявинская%20вл%2011%20(1в)") -> https://disk.yandex.ru/client/disk/Осмотры%20объектов%20АНО%20СМГ/176.%20Синявинская%20вл%2011%20(1в) | J49: =IFERROR(__xludf.DUMMYFUNCTION("""COMPUTED_VALUE"""),100.0) -> 100 | K49: =IFERROR(__xludf.DUMMYFUNCTION("""COMPUTED_VALUE"""),45839.0) -> 45839 | L49: Завершен | N49: ✅ Завершен | O49: РВ от 28.05.2025 №77-09-012548-2025
A50: =IFERROR(__xludf.DUMMYFUNCTION("""COMPUTED_VALUE"""),"116") -> 116 | B50: =IFERROR(__xludf.DUMMYFUNCTION("""COMPUTED_VALUE"""),"АИП-25") -> АИП-25 | C50: =IFERROR(__xludf.DUMMYFUNCTION("""COMPUTED_VALUE"""),"ОКС") -> ОКС | E50: =IFERROR(__xludf.DUMMYFUNCTION("""COMPUTED_VALUE"""),"Школа на 1200 мест, д. Ватутинки, пос. Десёновское, ул. Кварцевая, д. 3А пос. Десеновское, д. Ватутинки, ул. Кварцевая, 3А") -> Школа на 1200 мест, д. Ватутинки, пос. Десёновское, ул. Кварцевая, д. 3А пос. Десеновское, д. Ватутинки, ул. Кварцевая, 3А | F50: =IFERROR(__xludf.DUMMYFUNCTION("""COMPUTED_VALUE"""),"55.488695") -> 55.488695 | G50: =IFERROR(__xludf.DUMMYFUNCTION("""COMPUTED_VALUE"""),"37.339420") -> 37.339420 | H50: =IFERROR(__xludf.DUMMYFUNCTION("""COMPUTED_VALUE"""),"https://docs.google.com/spreadsheets/d/19THEBTE9q0fhN2eApZr6BgenIvLGh0AckaYxHQfHk5w/edit?gid=1830744104#gid=1830744104") -> https://docs.google.com/spreadsheets/d/19THEBTE9q0fhN2eApZr6BgenIvLGh0AckaYxHQfHk5w/edit?gid=1830744104#gid=1830744104 | I50: =IFERROR(__xludf.DUMMYFUNCTION("""COMPUTED_VALUE"""),"https://disk.yandex.ru/client/disk/Осмотры%20объектов%20АНО%20СМГ/116.%20Кварцевая%20ул.%203А%2C%20д.%20Ватутинки%20(СОШ%20на%201200%20м)") -> https://disk.yandex.ru/client/disk/Осмотры%20объектов%20АНО%20СМГ/116.%20Кварцевая%20ул.%203А%2C%20д.%20Ватутинки%20(СОШ%20на%201200%20м) | J50: =IFERROR(__xludf.DUMMYFUNCTION("""COMPUTED_VALUE"""),99.82400000000001) -> 99.824 | K50: =IFERROR(__xludf.DUMMYFUNCTION("""COMPUTED_VALUE"""),45971.0) -> 45971 | L50: 7 | M50: 45978 | N50: 🟡 СКОРО | O50: По состоянию на 30.10.2025 Фактическое состояние объекта: Ведется строительство Проблемные вопросы: Производится устранение замечаний от ГКУ ДИОМ (устранено 267 из 480 замечаний) Оформление документации для ввода объекта: - Папка «ЗОС»: 13 из 36 документов - Папка «Разрешение на ввод»: 21 из 23 документов Плановая дата получения «ЗОС» и «РВ» - ноябрь 2025
A51: =IFERROR(__xludf.DUMMYFUNCTION("""COMPUTED_VALUE"""),"254") -> 254 | B51: =IFERROR(__xludf.DUMMYFUNCTION("""COMPUTED_VALUE"""),"АИП-25") -> АИП-25 | C51: =IFERROR(__xludf.DUMMYFUNCTION("""COMPUTED_VALUE"""),"ОКС") -> ОКС | E51: =IFERROR(__xludf.DUMMYFUNCTION("""COMPUTED_VALUE"""),"ММК. Центр хронических болезней, территория инновационного центра «Сколково», ул. Большой бульвар, д. 46, строение 3 Территория инновационного центра «Сколково»") -> ММК. Центр хронических болезней, территория инновационного центра «Сколково», ул. Большой бульвар, д. 46, строение 3 Территория инновационного центра «Сколково» | F51: =IFERROR(__xludf.DUMMYFUNCTION("""COMPUTED_VALUE"""),"55.684365") -> 55.684365 | G51: =IFERROR(__xludf.DUMMYFUNCTION("""COMPUTED_VALUE"""),"37.348977") -> 37.348977 | H51: =IFERROR(__xludf.DUMMYFUNCTION("""COMPUTED_VALUE"""),"https://docs.google.com/spreadsheets/d/19THEBTE9q0fhN2eApZr6BgenIvLGh0AckaYxHQfHk5w/edit?gid=987830810#gid=987830810") -> https://docs.google.com/spreadsheets/d/19THEBTE9q0fhN2eApZr6BgenIvLGh0AckaYxHQfHk5w/edit?gid=987830810#gid=987830810 | I51: =IFERROR(__xludf.DUMMYFUNCTION("""COMPUTED_VALUE"""),"https://disk.yandex.ru/client/disk/Осмотры%20объектов%20АНО%20СМГ/254.%20Ммк%20Сколково%20ЦХБ%20ул%20Большой%20бульвар%2046с3") -> https://disk.yandex.ru/client/disk/Осмотры%20объектов%20АНО%20СМГ/254.%20Ммк%20Сколково%20ЦХБ%20ул%20Большой%20бульвар%2046с3 | J51: =IFERROR(__xludf.DUMMYFUNCTION("""COMPUTED_VALUE"""),99.9635) -> 99.9635 | K51: =IFERROR(__xludf.DUMMYFUNCTION("""COMPUTED_VALUE"""),45972.0) -> 45972 | L51: 7 | M51: 45979 | N51: 🟡 СКОРО | O51: По состоянию на 06.11.2025 Фактическое состояние объекта: Ведется строительство Проблемные вопросы: Проводится итоговая проверка МГСН в период с 29.10.2025 по 11.11.2025
A52: =IFERROR(__xludf.DUMMYFUNCTION("""COMPUTED_VALUE"""),"119") -> 119 | B52: =IFERROR(__xludf.DUMMYFUNCTION("""COMPUTED_VALUE"""),"АИП-25") -> АИП-25 | C52: =IFERROR(__xludf.DUMMYFUNCTION("""COMPUTED_VALUE"""),"ОКС") -> ОКС | E52: =IFERROR(__xludf.DUMMYFUNCTION("""COMPUTED_VALUE"""),"Учебный корпус на 300 мест с ДОУ на 125 мест просп. Вернадского вл., 12Б район Раменки, пр-кт Вернадского, влд.12Б") -> Учебный корпус на 300 мест с ДОУ на 125 мест просп. Вернадского вл., 12Б район Раменки, пр-кт Вернадского, влд.12Б | F52: =IFERROR(__xludf.DUMMYFUNCTION("""COMPUTED_VALUE"""),"#N/A") -> #N/A | G52: =IFERROR(__xludf.DUMMYFUNCTION("""COMPUTED_VALUE"""),"#N/A") -> #N/A | H52: =IFERROR(__xludf.DUMMYFUNCTION("""COMPUTED_VALUE"""),"https://docs.google.com/spreadsheets/d/19THEBTE9q0fhN2eApZr6BgenIvLGh0AckaYxHQfHk5w/edit?gid=1592533153#gid=1592533153") -> https://docs.google.com/spreadsheets/d/19THEBTE9q0fhN2eApZr6BgenIvLGh0AckaYxHQfHk5w/edit?gid=1592533153#gid=1592533153 | I52: =IFERROR(__xludf.DUMMYFUNCTION("""COMPUTED_VALUE"""),"https://disk.yandex.ru/client/disk/Осмотры%20объектов%20АНО%20СМГ/119.%20пр-т%20Вернадского%2012Б%2C%20СОШ%2C%20ДОО") -> https://disk.yandex.ru/client/disk/Осмотры%20объектов%20АНО%20СМГ/119.%20пр-т%20Вернадского%2012Б%2C%20СОШ%2C%20ДОО | J52: =IFERROR(__xludf.DUMMYFUNCTION("""COMPUTED_VALUE"""),100.0) -> 100 | K52: =IFERROR(__xludf.DUMMYFUNCTION("""COMPUTED_VALUE"""),45902.0) -> 45902 | L52: Завершен | N52: ✅ Завершен | O52: РВ от 31.07.2025 № 77-07-012644-2025
A53: =IFERROR(__xludf.DUMMYFUNCTION("""COMPUTED_VALUE"""),"018") -> 018 | B53: =IFERROR(__xludf.DUMMYFUNCTION("""COMPUTED_VALUE"""),"АИП-25") -> АИП-25 | C53: =IFERROR(__xludf.DUMMYFUNCTION("""COMPUTED_VALUE"""),"ОКС") -> ОКС | E53: =IFERROR(__xludf.DUMMYFUNCTION("""COMPUTED_VALUE"""),"Общеобразовательная организация на 1100 мест по адресу: г.п. Щербинка, м-ко Барыши (2 этап: Строительство учебного корпуса на 400 мест на месте сноса существующего здания школы) г.п. Щербинка, ул. Местечко Барыши, з/у 25") -> Общеобразовательная организация на 1100 мест по адресу: г.п. Щербинка, м-ко Барыши (2 этап: Строительство учебного корпуса на 400 мест на месте сноса существующего здания школы) г.п. Щербинка, ул. Местечко Барыши, з/у 25 | F53: =IFERROR(__xludf.DUMMYFUNCTION("""COMPUTED_VALUE"""),"#N/A") -> #N/A | G53: =IFERROR(__xludf.DUMMYFUNCTION("""COMPUTED_VALUE"""),"#N/A") -> #N/A | H53: =IFERROR(__xludf.DUMMYFUNCTION("""COMPUTED_VALUE"""),"https://docs.google.com/spreadsheets/d/19THEBTE9q0fhN2eApZr6BgenIvLGh0AckaYxHQfHk5w/edit?gid=2074952134#gid=2074952134") -> https://docs.google.com/spreadsheets/d/19THEBTE9q0fhN2eApZr6BgenIvLGh0AckaYxHQfHk5w/edit?gid=2074952134#gid=2074952134 | I53: =IFERROR(__xludf.DUMMYFUNCTION("""COMPUTED_VALUE"""),"https://disk.yandex.ru/client/disk/Осмотры%20объектов%20АНО%20СМГ/018.%20СОШ%20400%20Щербинка%2C%20ул.%20Барыши") -> https://disk.yandex.ru/client/disk/Осмотры%20объектов%20АНО%20СМГ/018.%20СОШ%20400%20Щербинка%2C%20ул.%20Барыши | J53: =IFERROR(__xludf.DUMMYFUNCTION("""COMPUTED_VALUE"""),100.0) -> 100 | K53: =IFERROR(__xludf.DUMMYFUNCTION("""COMPUTED_VALUE"""),45937.0) -> 45937 | L53: Завершен | N53: ✅ Завершен | O53: РВ от 13.08.2025 №77-13-012671-2025
A54: =IFERROR(__xludf.DUMMYFUNCTION("""COMPUTED_VALUE"""),"017") -> 017 | B54: =IFERROR(__xludf.DUMMYFUNCTION("""COMPUTED_VALUE"""),"АИП-25") -> АИП-25 | C54: =IFERROR(__xludf.DUMMYFUNCTION("""COMPUTED_VALUE"""),"ОКС") -> ОКС | E54: =IFERROR(__xludf.DUMMYFUNCTION("""COMPUTED_VALUE"""),"Культурно-досуговый центр п. Шишкин Лес, пос. Михайлово-Ярцевское п. Шишкин Лес, пос. Михайлово-Ярцевское") -> Культурно-досуговый центр п. Шишкин Лес, пос. Михайлово-Ярцевское п. Шишкин Лес, пос. Михайлово-Ярцевское | F54: =IFERROR(__xludf.DUMMYFUNCTION("""COMPUTED_VALUE"""),"55.413782") -> 55.413782 | G54: =IFERROR(__xludf.DUMMYFUNCTION("""COMPUTED_VALUE"""),"37.189248") -> 37.189248 | H54: =IFERROR(__xludf.DUMMYFUNCTION("""COMPUTED_VALUE"""),"https://docs.google.com/spreadsheets/d/19THEBTE9q0fhN2eApZr6BgenIvLGh0AckaYxHQfHk5w/edit?gid=1089584377#gid=1089584377") -> https://docs.google.com/spreadsheets/d/19THEBTE9q0fhN2eApZr6BgenIvLGh0AckaYxHQfHk5w/edit?gid=1089584377#gid=1089584377 | I54: =IFERROR(__xludf.DUMMYFUNCTION("""COMPUTED_VALUE"""),"https://disk.yandex.ru/client/disk/Осмотры%20объектов%20АНО%20СМГ/017.%20Шишкин%20лес%20КДЦ") -> https://disk.yandex.ru/client/disk/Осмотры%20объектов%20АНО%20СМГ/017.%20Шишкин%20лес%20КДЦ | J54: =IFERROR(__xludf.DUMMYFUNCTION("""COMPUTED_VALUE"""),91.8861275) -> 91.886128 | K54: =IFERROR(__xludf.DUMMYFUNCTION("""COMPUTED_VALUE"""),45968.0) -> 45968 | L54: 14 | M54: 45982 | N54: 🟡 СКОРО | O54: По состоянию на 07.10.2025 Фактическое состояние объекта: Ведется строительство Проблемные вопросы: ПД (корректировка) проходит согласование в МГЭ Откорректированный АГР не согласован МКА Проходит согласование РД с РСО (ИТП) и МГГТ (СС) Плановая дата получения ЗОС - ноябрь 2025
A55: =IFERROR(__xludf.DUMMYFUNCTION("""COMPUTED_VALUE"""),"389д (сводный)") -> 389д (сводный) | B55: =IFERROR(__xludf.DUMMYFUNCTION("""COMPUTED_VALUE"""),"АИП-25") -> АИП-25 | C55: =IFERROR(__xludf.DUMMYFUNCTION("""COMPUTED_VALUE"""),"УДС") -> УДС | E55: =IFERROR(__xludf.DUMMYFUNCTION("""COMPUTED_VALUE"""),"Строительство искусственного сооружения с улично-дорожной сетью и переустройством инженерных коммуникаций на участке от ул. Б. Филевской до Третьего транспортного кольца вдоль набережной р. Москвы. Этапы 1.1.2.2.,1.2.2. ") -> Строительство искусственного сооружения с улично-дорожной сетью и переустройством инженерных коммуникаций на участке от ул. Б. Филевской до Третьего транспортного кольца вдоль набережной р. Москвы. Этапы 1.1.2.2.,1.2.2. | F55: =IFERROR(__xludf.DUMMYFUNCTION("""COMPUTED_VALUE"""),"#N/A") -> #N/A | G55: =IFERROR(__xludf.DUMMYFUNCTION("""COMPUTED_VALUE"""),"#N/A") -> #N/A | L55: 30 | N55: 🆕 Нет объездов
A56: =IFERROR(__xludf.DUMMYFUNCTION("""COMPUTED_VALUE"""),"389д (этап 1.1.2.2)") -> 389д (этап 1.1.2.2) | C56: =IFERROR(__xludf.DUMMYFUNCTION("""COMPUTED_VALUE"""),"УДС") -> УДС | E56: =IFERROR(__xludf.DUMMYFUNCTION("""COMPUTED_VALUE"""),"Строительство искусственного сооружения с улично-дорожной сетью и переустройством инженерных коммуникаций на участке от ул. Б. Филевской до Третьего транспортного кольца вдоль набережной р. Москвы. Этап 1.1.2.2 г. Москва, ул. Большая Филевская") -> Строительство искусственного сооружения с улично-дорожной сетью и переустройством инженерных коммуникаций на участке от ул. Б. Филевской до Третьего транспортного кольца вдоль набережной р. Москвы. Этап 1.1.2.2 г. Москва, ул. Большая Филевская | F56: =IFERROR(__xludf.DUMMYFUNCTION("""COMPUTED_VALUE"""),"#N/A") -> #N/A | G56: =IFERROR(__xludf.DUMMYFUNCTION("""COMPUTED_VALUE"""),"#N/A") -> #N/A | L56: 30 | N56: 🆕 Нет объездов | O56: По состоянию на 04.07.2025 ООО «РГИ проект» прорабатывается вопрос разделения на подэтапы для получения ЗОС и РВ на отдельные инженерные сети.
A57: =IFERROR(__xludf.DUMMYFUNCTION("""COMPUTED_VALUE"""),"389д (этап 1.2.2)") -> 389д (этап 1.2.2) | C57: =IFERROR(__xludf.DUMMYFUNCTION("""COMPUTED_VALUE"""),"УДС") -> УДС | E57: =IFERROR(__xludf.DUMMYFUNCTION("""COMPUTED_VALUE"""),"Строительство искусственного сооружения с улично-дорожной сетью и переустройством инженерных коммуникаций на участке от ул. Б. Филевской до Третьего транспортного кольца вдоль набережной р. Москвы. Этап 1.2.2 г. Москва, ул. Большая Филевская") -> Строительство искусственного сооружения с улично-дорожной сетью и переустройством инженерных коммуникаций на участке от ул. Б. Филевской до Третьего транспортного кольца вдоль набережной р. Москвы. Этап 1.2.2 г. Москва, ул. Большая Филевская | F57: =IFERROR(__xludf.DUMMYFUNCTION("""COMPUTED_VALUE"""),"#N/A") -> #N/A | G57: =IFERROR(__xludf.DUMMYFUNCTION("""COMPUTED_VALUE"""),"#N/A") -> #N/A | L57: 30 | N57: 🆕 Нет объездов | O57: По состоянию на 04.07.2025 Проектно-сметная документация находится в экспертизе, плановое получение положительного заключения - июль 2025 года.
A58: =IFERROR(__xludf.DUMMYFUNCTION("""COMPUTED_VALUE"""),"390д (этап 3.2)") -> 390д (этап 3.2) | B58: =IFERROR(__xludf.DUMMYFUNCTION("""COMPUTED_VALUE"""),"АИП-25") -> АИП-25 | C58: =IFERROR(__xludf.DUMMYFUNCTION("""COMPUTED_VALUE"""),"УДС") -> УДС | E58: =IFERROR(__xludf.DUMMYFUNCTION("""COMPUTED_VALUE"""),"Строительство мостового сооружения через старое русло р. Москва с улично-дорожной сетью в южной части территории публичного акционерного общества ""Завод имени И.А. Лихачева"" с обустройством пешеходных переходов, отстойно-разворотной площадки, здания кон"&"ечной станции городского пассажирского транспорта. Обустройство набережной р. Москва в районе территории публичного акционерного общества ""Завод имени И.А. Лихачева"" . Этапы 3.2. (Очистное сооружение) ЗИЛ") -> Строительство мостового сооружения через старое русло р. Москва с улично-дорожной сетью в южной части территории публичного акционерного общества "Завод имени И.А. Лихачева" с обустройством пешеходных переходов, отстойно-разворотной площадки, здания конечной станции городского пассажирского транспорта. Обустройство набережной р. Москва в районе территории публичного акционерного общества "Завод имени И.А. Лихачева" . Этапы 3.2. (Очистное сооружение) ЗИЛ | F58: =IFERROR(__xludf.DUMMYFUNCTION("""COMPUTED_VALUE"""),"#N/A") -> #N/A | G58: =IFERROR(__xludf.DUMMYFUNCTION("""COMPUTED_VALUE"""),"#N/A") -> #N/A | J58: =IFERROR(__xludf.DUMMYFUNCTION("""COMPUTED_VALUE"""),98.0) -> 98 | K58: =IFERROR(__xludf.DUMMYFUNCTION("""COMPUTED_VALUE"""),45968.0) -> 45968 | L58: 7 | M58: 45975 | N58: 🔴 СРОЧНО | O58: По состоянию на 22.07.2025 Фактическое состояние объекта: Ведется строительство Проблемные вопросы: Проведена итоговая проверка МГСН от 09.07.2025. Получено 7 замечания в части пожарной безопасности, благоустройства, облицовочных плит фасада здания (не соответствует проекту); Плановая дата повторной проверки - 04.08.2025. Отсутствует возможность подключения ОС в связи с отсутствием ТП. Выполнена установка корпуса ТП. Расключение и сдача ТП - 04.08.2025. Необходима корректировка ПД в связи с несоответствием ТЭПов в ПД с фактически выполненными объемами (не учтена площадь подземной части). Плановавя дата выхода из МГЭ - 04.08.2025
A59: =IFERROR(__xludf.DUMMYFUNCTION("""COMPUTED_VALUE"""),"390д (этап 3.1)") -> 390д (этап 3.1) | B59: =IFERROR(__xludf.DUMMYFUNCTION("""COMPUTED_VALUE"""),"АИП-25") -> АИП-25 | C59: =IFERROR(__xludf.DUMMYFUNCTION("""COMPUTED_VALUE"""),"УДС") -> УДС | E59: =IFERROR(__xludf.DUMMYFUNCTION("""COMPUTED_VALUE"""),"Строительство мостового сооружения через старое русло р. Москвы с улично-дорожной сетью в южной части территории публичного акционерного общества ""Завод имени И.А. Лихачева"" с обустройством пешеходных переходов, отстойно-разворотной площадки, здания кон"&"ечной станции городского пассажирского транспорта. Обустройство набережной р. Москва в районе территории публичного акционерного общества ""Завод имени И.А. Лихачева"" . Этапы 3.1. ЗИЛ") -> Строительство мостового сооружения через старое русло р. Москвы с улично-дорожной сетью в южной части территории публичного акционерного общества "Завод имени И.А. Лихачева" с обустройством пешеходных переходов, отстойно-разворотной площадки, здания конечной станции городского пассажирского транспорта. Обустройство набережной р. Москва в районе территории публичного акционерного общества "Завод имени И.А. Лихачева" . Этапы 3.1. ЗИЛ | F59: =IFERROR(__xludf.DUMMYFUNCTION("""COMPUTED_VALUE"""),"#N/A") -> #N/A | G59: =IFERROR(__xludf.DUMMYFUNCTION("""COMPUTED_VALUE"""),"#N/A") -> #N/A | J59: =IFERROR(__xludf.DUMMYFUNCTION("""COMPUTED_VALUE"""),99.97500000000001) -> 99.975 | K59: =IFERROR(__xludf.DUMMYFUNCTION("""COMPUTED_VALUE"""),45968.0) -> 45968 | L59: 7 | M59: 45975 | N59: 🔴 СРОЧНО | O59: По состоянию на 22.07.2025 Фактическое состояние объекта: Ведется строительство Проблемные вопросы: Плановая дата итоговой проверки - 04.08.2025
A60: =IFERROR(__xludf.DUMMYFUNCTION("""COMPUTED_VALUE"""),"336д (этап 2.2.2)") -> 336д (этап 2.2.2) | B60: =IFERROR(__xludf.DUMMYFUNCTION("""COMPUTED_VALUE"""),"АИП-25") -> АИП-25 | C60: =IFERROR(__xludf.DUMMYFUNCTION("""COMPUTED_VALUE"""),"УДС") -> УДС | E60: =IFERROR(__xludf.DUMMYFUNCTION("""COMPUTED_VALUE"""),"Открытие участка ул. Ивана Франко от ул. Житомирская до ул. Герасима Курина (этап 2.2.2) район Фили-Давыдково") -> Открытие участка ул. Ивана Франко от ул. Житомирская до ул. Герасима Курина (этап 2.2.2) район Фили-Давыдково | F60: =IFERROR(__xludf.DUMMYFUNCTION("""COMPUTED_VALUE"""),"#N/A") -> #N/A | G60: =IFERROR(__xludf.DUMMYFUNCTION("""COMPUTED_VALUE"""),"#N/A") -> #N/A | J60: =IFERROR(__xludf.DUMMYFUNCTION("""COMPUTED_VALUE"""),100.0) -> 100 | K60: =IFERROR(__xludf.DUMMYFUNCTION("""COMPUTED_VALUE"""),45974.0) -> 45974 | L60: Завершен | N60: ✅ Завершен | O60: 99,9
A61: =IFERROR(__xludf.DUMMYFUNCTION("""COMPUTED_VALUE"""),"1288") -> 1288 | B61: =IFERROR(__xludf.DUMMYFUNCTION("""COMPUTED_VALUE"""),"АИП-25") -> АИП-25 | C61: =IFERROR(__xludf.DUMMYFUNCTION("""COMPUTED_VALUE"""),"УДС") -> УДС | E61: =IFERROR(__xludf.DUMMYFUNCTION("""COMPUTED_VALUE"""),"Подземный коллектор для инженерных коммуникаций от подстанции ""Чухлинка"" Окская ул., 7 корпус 1") -> Подземный коллектор для инженерных коммуникаций от подстанции "Чухлинка" Окская ул., 7 корпус 1 | F61: =IFERROR(__xludf.DUMMYFUNCTION("""COMPUTED_VALUE"""),"#N/A") -> #N/A | G61: =IFERROR(__xludf.DUMMYFUNCTION("""COMPUTED_VALUE"""),"#N/A") -> #N/A | H61: =IFERROR(__xludf.DUMMYFUNCTION("""COMPUTED_VALUE"""),"https://docs.google.com/spreadsheets/d/1MW8OIVEKRJEaLcG-KS0zwZPEQ0eRUWE2y9Gj77rgoxo/edit?gid=1838546198#gid=1838546198") -> https://docs.google.com/spreadsheets/d/1MW8OIVEKRJEaLcG-KS0zwZPEQ0eRUWE2y9Gj77rgoxo/edit?gid=1838546198#gid=1838546198 | J61: =IFERROR(__xludf.DUMMYFUNCTION("""COMPUTED_VALUE"""),90.0) -> 90 | K61: =IFERROR(__xludf.DUMMYFUNCTION("""COMPUTED_VALUE"""),45954.0) -> 45954 | L61: 14 | M61: 45968 | N61: 🔴 Объект введен | O61: РВ от 21.02.2025 №77-04-012449-2025
A62: =IFERROR(__xludf.DUMMYFUNCTION("""COMPUTED_VALUE"""),"113д (сводный)") -> 113д (сводный) | B62: =IFERROR(__xludf.DUMMYFUNCTION("""COMPUTED_VALUE"""),"АИП-25") -> АИП-25 | C62: =IFERROR(__xludf.DUMMYFUNCTION("""COMPUTED_VALUE"""),"УДС") -> УДС | E62: =IFERROR(__xludf.DUMMYFUNCTION("""COMPUTED_VALUE"""),"ЮВХ-8. Строительство улично-дорожной сети с искусственными сооружениями и переустройством инженерных коммуникаций на участке от ул. Маршала Шестопалова до Павелецкого направления Московской железной дороги. Этапы 2.3.2.2, 3.1 ") -> ЮВХ-8. Строительство улично-дорожной сети с искусственными сооружениями и переустройством инженерных коммуникаций на участке от ул. Маршала Шестопалова до Павелецкого направления Московской железной дороги. Этапы 2.3.2.2, 3.1 | F62: =IFERROR(__xludf.DUMMYFUNCTION("""COMPUTED_VALUE"""),"#N/A") -> #N/A | G62: =IFERROR(__xludf.DUMMYFUNCTION("""COMPUTED_VALUE"""),"#N/A") -> #N/A | L62: 30 | N62: 🆕 Нет объездов
A63: =IFERROR(__xludf.DUMMYFUNCTION("""COMPUTED_VALUE"""),"113д (этап 2.3.2.2)") -> 113д (этап 2.3.2.2) | C63: =IFERROR(__xludf.DUMMYFUNCTION("""COMPUTED_VALUE"""),"УДС") -> УДС | E63: =IFERROR(__xludf.DUMMYFUNCTION("""COMPUTED_VALUE"""),"ЮВХ-8.Строительство улично-дорожной сети с искусственными сооружениями и переустройством инженерных коммуникаций на участке от ул. Маршала Шестопалова до Павелецкого направления Московской железной дороги. Этап 2.3.2.2 от ул.Маршала Шестопалова до Павел"&"ецкого направления Московской железной дороги (ЮАО)") -> ЮВХ-8.Строительство улично-дорожной сети с искусственными сооружениями и переустройством инженерных коммуникаций на участке от ул. Маршала Шестопалова до Павелецкого направления Московской железной дороги. Этап 2.3.2.2 от ул.Маршала Шестопалова до Павелецкого направления Московской железной дороги (ЮАО) | F63: =IFERROR(__xludf.DUMMYFUNCTION("""COMPUTED_VALUE"""),"#N/A") -> #N/A | G63: =IFERROR(__xludf.DUMMYFUNCTION("""COMPUTED_VALUE"""),"#N/A") -> #N/A | L63: 30 | N63: 🆕 Нет объездов
